Workbook
Name lst_ChefsProjet: OFFSET(Data!$A$3,1,0,MAX(1,COUNTA(Data!$A$4:$A$203)),1)
Name lst_Projets: OFFSET(Data!$B$3,1,0,MAX(1,COUNTA(Data!$B$4:$B$203)),1)
Name lst_Types: OFFSET(Data!$C$3,1,0,MAX(1,COUNTA(Data!$C$4:$C$203)),1)
Name lst_Coordinateurs: OFFSET(Data!$D$3,1,0,MAX(1,COUNTA(Data!$D$4:$D$203)),1)
Name lst_Dessinateurs: OFFSET(Data!$E$3,1,0,MAX(1,COUNTA(Data!$E$4:$E$203)),1)
Name lst_Prestataires: OFFSET(Data!$H$3,1,0,MAX(1,COUNTA(Data!$H$4:$H$203)),1)
Name p_Perimetre: Dashboard!$F$5
Name p_Repartition: Dashboard!$R$5
Name p_PremierMois: Dashboard!$AK$5
Name p_HeuresETP: Dashboard!$AU$5
Name p_ChargeFixe: Dashboard!$BD$5
Name lst_Ressources: OFFSET(Calculs!$FA$4,0,0,MAX(1,Calculs!$CD$23+Calculs!$CD$26),1)
Name p_Dessinateur: Dessinateurs!$G$5

Sheet Charge
A1: PLAN DE CHARGE — BUREAU D'ÉTUDES
A2: UNE LIGNE = UNE RESSOURCE sur un sous-projet : un dessinateur (K) OU une ressource externe (L), avec SES heures en M. Pour mettre plusieurs personnes sur un sous-projet, recopier la ligne (colonnes A à J à l'identique) et changer la ressource et les heures. Couleurs : rouge = dessinateur ET externe sur la même ligne (à corriger, seul K est compté) ; orange = aucune ressource (charge à affecter). Insérer, supprimer ou trier des lignes est possible. Les lignes 4 à 27 sont des EXEMPLES FICTIFS à remplacer par vos données.
A3: Chef de projet | B3: Nom du projet | C3: Sous-projet | D3: Produit | E3: Type | F3: Date de besoin | G3: Description du projet | H3: Contraintes, spécifications, délais, budget | I3: Autres informations pertinentes / suggestions d'optimisation des ressources | J3: Coordinateur | K3: Dessinateur projeteur (interne) | L3: OU ressource externe | M3: Heures de cette ressource (h) | N3: Date de début planifiée | O3: Taux d'avancement
A4: Julie Martin | B4: ATLAS | C4: Lot 1 – Structure | D4: Châssis principal | E4: Étude de conception | F4: 46477 | G4: Conception du châssis mécano-soudé de la nouvelle gamme | H4: Masse < 450 kg ; budget étude 60 k€ | I4: Mutualiser les calculs RDM avec le lot 2 | J4: Marc Dubois | K4: Lucas Garnier | M4: 300 | N4: 46328 | O4: 0.15
A5: Julie Martin | B5: ATLAS | C5: Lot 1 – Structure | D5: Châssis principal | E5: Étude de conception | F5: 46477 | G5: Conception du châssis mécano-soudé de la nouvelle gamme | H5: Masse < 450 kg ; budget étude 60 k€ | I5: Mutualiser les calculs RDM avec le lot 2 | J5: Marc Dubois | L5: Paul Girard | M5: 120 | N5: 46328 | O5: 0
A6: Julie Martin | B6: ATLAS | C6: Lot 2 – Carénage | D6: Capots latéraux | E6: Étude de conception | F6: 46535 | G6: Dessin des capots et de leurs fixations | H6: Matière ABS, outillage existant | J6: Marc Dubois | K6: Emma Faure | M6: 260 | N6: 46398 | O6: 0
A7: Julie Martin | B7: ATLAS | C7: Lot 3 – Intégration | D7: Faisceau électrique | E7: Industrialisation | F7: 46598 | G7: Routage des faisceaux et supports | H7: Normes NF C 15-100 | J7: Marc Dubois | L7: Inès Morel | M7: 180 | N7: 46482 | O7: 0
A8: Thomas Bernard | B8: BORÉAL | C8: Phase APD | D8: Groupe froid | E8: Étude de conception | F8: 46416 | G8: Avant-projet détaillé du groupe froid | H8: Délai client ferme | J8: Isabelle Roux | K8: Léa Chevalier | M8: 310 | N8: 46300 | O8: 0.35
A9: Thomas Bernard | B9: BORÉAL | C9: Phase EXE | D9: Groupe froid | E9: Mise à jour de plans | F9: 46507 | G9: Plans d'exécution | H9: Budget 25 k€ | J9: Isabelle Roux | K9: Léa Chevalier | M9: 220 | N9: 46419 | O9: 0
A10: Thomas Bernard | B10: BORÉAL | C10: Phase EXE | D10: Armoire de commande | E10: Modification | F10: 46461 | G10: Reprise de l'armoire existante | J10: Isabelle Roux | L10: Karim Haddad | M10: 90 | N10: 46405 | O10: 0
A11: Sophie Lefèvre | B11: CASSIOPÉE | C11: Rétrofit ligne 2 | D11: Convoyeur | E11: Modification | F11: 46374 | G11: Adaptation du convoyeur au nouveau format | H11: Arrêt de ligne limité à 2 semaines | I11: Réutiliser les plans de la ligne 1 | J11: Marc Dubois | K11: Hugo Mercier | M11: 150 | N11: 46307 | O11: 0.5
A12: Sophie Lefèvre | B12: CASSIOPÉE | C12: Rétrofit ligne 2 | D12: Poste de contrôle | E12: Étude de conception | F12: 46444 | G12: Nouveau poste de contrôle vision | J12: Marc Dubois | K12: Emma Faure | M12: 160 | N12: 46357 | O12: 0.05
A13: Sophie Lefèvre | B13: CASSIOPÉE | C13: Rétrofit ligne 2 | D13: Poste de contrôle | E13: Étude de conception | F13: 46444 | G13: Nouveau poste de contrôle vision | J13: Marc Dubois | L13: Paul Girard | M13: 80 | N13: 46357 | O13: 0
A14: Sophie Lefèvre | B14: DELTA | C14: Lot unique | D14: Bâti machine | E14: Industrialisation | F14: 46568 | G14: Industrialisation du bâti | H14: Cible coût -10 % | J14: Isabelle Roux | K14: Antoine Blanc | M14: 240 | N14: 46433 | O14: 0
A15: Sophie Lefèvre | B15: DELTA | C15: Lot unique | D15: Bâti machine | E15: Industrialisation | F15: 46568 | G15: Industrialisation du bâti | H15: Cible coût -10 % | J15: Isabelle Roux | K15: Hugo Mercier | M15: 120 | N15: 46433 | O15: 0
A16: Nicolas Moreau | B16: ORION | C16: Tranche 1 | D16: Support moteur | E16: Étude de conception | F16: 46353 | G16: Conception du support moteur | J16: Isabelle Roux | K16: Lucas Garnier | M16: 120 | N16: 46279 | O16: 0.8
A17: Nicolas Moreau | B17: ORION | C17: Tranche 1 | D17: Carter de protection | E17: Mise à jour de plans | F17: 46304 | G17: Mise à jour indice C | J17: Isabelle Roux | K17: Lucas Garnier | M17: 40 | N17: 46286 | O17: 1
A18: Nicolas Moreau | B18: ORION | C18: Tranche 2 | D18: Support moteur | E18: Modification | F18: 46521 | G18: Évolution pour moteur 30 kW | J18: Isabelle Roux | K18: Emma Faure | M18: 160 | N18: 46447 | O18: 0
A19: Nicolas Moreau | B19: PÉGASE | C19: Avant-projet | D19: Ensemble complet | E19: Chiffrage / avant-projet | F19: 46367 | G19: Chiffrage et esquisses pour l'appel d'offres | H19: Remise d'offre le 15/12 | J19: Marc Dubois | K19: Léa Chevalier | M19: 70 | N19: 46342 | O19: 0.1
A20: Camille Laurent | B20: PÉGASE | C20: Lot 1 | D20: Ensemble complet | E20: Étude de conception | F20: 46660 | G20: Étude complète si commande | H20: Sous réserve de commande | I20: Renfort externe prévu | J20: Marc Dubois | K20: Hugo Mercier | M20: 300 | N20: 46461 | O20: 0
A21: Camille Laurent | B21: PÉGASE | C21: Lot 1 | D21: Ensemble complet | E21: Étude de conception | F21: 46660 | G21: Étude complète si commande | H21: Sous réserve de commande | I21: Renfort externe prévu | J21: Marc Dubois | L21: Karim Haddad | M21: 180 | N21: 46461 | O21: 0
A22: Camille Laurent | B22: VEGA | C22: Mise en conformité | D22: Garde-corps | E22: Modification | F22: 46402 | G22: Mise en conformité des garde-corps | H22: Norme NF E 85-015 | J22: Isabelle Roux | K22: Antoine Blanc | M22: 85 | N22: 46349 | O22: 0
A23: Camille Laurent | B23: VEGA | C23: Mise en conformité | D23: Passerelle | E23: Mise à jour de plans | F23: 46477 | G23: Plans de recollement | J23: Isabelle Roux | K23: Antoine Blanc | M23: 60 | N23: 46426 | O23: 0
A24: Camille Laurent | B24: VEGA | C24: Mise en conformité | D24: Escalier d'accès | E24: Modification | F24: 46507 | G24: Mise en conformité de l'escalier d'accès | I24: Ressource à définir | J24: Isabelle Roux | M24: 50 | N24: 46447 | O24: 0
A25: Julie Martin | B25: TITAN | C25: Lot 1 | D25: Poutre de levage | E25: Étude de conception | F25: 46295 | G25: Note de calcul et plans | J25: Marc Dubois | K25: Lucas Garnier | M25: 95 | N25: 46258 | O25: 1
A26: Thomas Bernard | B26: DELTA | C26: Lot unique | D26: Habillage | E26: Étude de conception | F26: 46626 | G26: Habillage design | J26: Isabelle Roux | K26: Emma Faure | M26: 120 | N26: 46510 | O26: 0
A27: Thomas Bernard | B27: DELTA | C27: Lot unique | D27: Habillage | E27: Étude de conception | F27: 46626 | G27: Habillage design | J27: Isabelle Roux | L27: Inès Morel | M27: 80 | N27: 46510 | O27: 0

Sheet Data
A1: LISTES DE RÉFÉRENCE
A2: Saisir une valeur par cellule, sans ligne vide, sous chaque en-tête : les listes déroulantes de l'onglet Charge se mettent à jour automatiquement (200 valeurs max par liste). Colonnes F-G et I-J : capacité et charge fixe propres à un dessinateur ou à une ressource externe (vide = valeurs par défaut réglées en haut du Dashboard). Colonne K (facultative) : jours non travaillés communs à tout le bureau (fériés, fermeture), retirés du lissage comme les week-ends. Les valeurs ci-dessous sont des exemples à remplacer.
A3: Chefs de projet | B3: Noms de projet | C3: Types | D3: Coordinateurs | E3: Dessinateurs projeteurs | F3: Capacité mensuelle (h) vide = défaut | G3: Charge fixe hors projet (h/mois) vide = défaut | H3: Ressources externes (personnes) | I3: Capacité mensuelle (h) vide = défaut | J3: Charge fixe hors projet (h/mois) vide = défaut | K3: Jours non travaillés (fériés, fermetures) facultatif
A4: Julie Martin | B4: ATLAS | C4: Étude de conception | D4: Marc Dubois | E4: Lucas Garnier | H4: Paul Girard
A5: Thomas Bernard | B5: BORÉAL | C5: Modification | D5: Isabelle Roux | E5: Emma Faure | H5: Inès Morel
A6: Sophie Lefèvre | B6: CASSIOPÉE | C6: Mise à jour de plans | E6: Hugo Mercier | H6: Karim Haddad
A7: Nicolas Moreau | B7: DELTA | C7: Industrialisation | E7: Léa Chevalier | F7: 96
A8: Camille Laurent | B8: ORION | C8: Chiffrage / avant-projet | E8: Antoine Blanc
B9: PÉGASE
B10: VEGA
B11: TITAN

Sheet Dashboard
C2: TABLEAU DE BORD — PLAN DE CHARGE DU BUREAU D'ÉTUDES | AT2: =TODAY() -> 46313
C3: Synthèse automatique de l'onglet Charge : mettre à jour Charge et Data, le tableau de bord se recalcule seul.
B5: Périmètre | F5: Projets en cours | N5: Répartition | R5: Lissée jusqu'à la date de besoin | AF5: 1er mois affiché | AQ5: Capacité | AU5: 120 | AZ5: Charge fixe | BD5: 20
F6: En cours = avancement < 100 % | R6: =IF(p_Repartition="Tout sur le mois de début","Toute la charge sur le mois de début planifié","Prorata des jours ouvrés entre début planifié et date de besoin") -> Prorata des jours ouvrés entre début planifié et date de besoin | AK6: =IF(ISNUMBER(p_PremierMois),"Saisi manuellement",Calculs!$AL$13) -> 46266 | AU6: par personne | BD6: hors projet
B8: =IF(p_Perimetre="Tous les projets","TOUS LES PROJETS","PROJETS EN COURS") -> PROJETS EN COURS | Z8: =IF(Calculs!$CD$27>0,"Attention : "&Calculs!$CD$27&" ligne(s) de Charge ont un dessinateur ET une ressource externe (en rouge dans Charge)","")
C11: CHEFS DE PROJET | R11: PROGRAMMES SUIVIS | AG11: CHARGE IDENTIFIÉE | AV11: ★ PLUS GROSSE AFFAIRE
C12: =Calculs!$AL$6 -> 5 | R12: =Calculs!$AL$7 -> 7 | AG12: =Calculs!$AL$4 -> 3455 | AV12: =IF(Calculs!$AL$23="",0,INDEX(Calculs!$EP$4:$EP$503,Calculs!$AL$23)) -> 480
C13: =IF(p_Perimetre="Tous les projets","sur l'ensemble des projets","sur les projets en cours") -> sur les projets en cours | R13: projets distincts · classés par charge | AG13: =Calculs!$AL$22 -> 34.55 | AV13: =IF(OR(Calculs!$AL$23="",Calculs!$AL$4=0),0,INDEX(Calculs!$EP$4:$EP$503,Calculs!$AL$23)/Calculs!$AL$4) -> 0.13892909
C15: =Calculs!BL4 -> Julie Martin | L15: =Calculs!BM4 -> 860 | S15: =Calculs!BP4 -> ATLAS | AA15: =Calculs!BQ4 -> 860 | AG15: Réalisé (selon avancement) | AP15: =Calculs!$AL$9 -> 339.5 | AV15: Projet | BA15: =IF(Calculs!$AL$23="","—",INDEX(Charge!$B:$B,Calculs!$AL$23+3)&"") -> PÉGASE
C16: =Calculs!BL5 -> Thomas Bernard | L16: =Calculs!BM5 -> 820 | S16: =Calculs!BP5 -> BORÉAL | AA16: =Calculs!BQ5 -> 620 | AG16: Reste à faire | AP16: =Calculs!$AL$10 -> 3115.5 | AV16: Sous-projet | BA16: =IF(Calculs!$AL$23="","—",INDEX(Charge!$C:$C,Calculs!$AL$23+3)&"") -> Lot 1
C17: =Calculs!BL6 -> Sophie Lefèvre | L17: =Calculs!BM6 -> 750 | S17: =Calculs!BP6 -> DELTA | AA17: =Calculs!BQ6 -> 560 | AV17: Produit | BA17: =IF(Calculs!$AL$23="","—",INDEX(Charge!$D:$D,Calculs!$AL$23+3)&"") -> Ensemble complet
C18: =Calculs!BL7 -> Camille Laurent | L18: =Calculs!BM7 -> 675 | S18: =Calculs!BP7 -> PÉGASE | AA18: =Calculs!BQ7 -> 550 | AG18: PAR TYPE D'AFFAIRE | AV18: Chef de projet | BA18: =IF(Calculs!$AL$23="","—",INDEX(Charge!$A:$A,Calculs!$AL$23+3)&"") -> Camille Laurent
C19: =Calculs!BL8 -> Nicolas Moreau | L19: =Calculs!BM8 -> 350 | S19: =Calculs!BP8 -> CASSIOPÉE | AA19: =Calculs!BQ8 -> 390 | AG19: =Calculs!BT4 -> Étude de conception | AP19: =Calculs!BU4 -> 2030 | AV19: Ressources | BA19: =IF(Calculs!$AL$23="","—",INDEX(Calculs!$ET$4:$ET$503,Calculs!$AL$23)&"") -> 2 dont 1 ext.
C20: =Calculs!BL9 | L20: =Calculs!BM9 | S20: =Calculs!BP9 -> ORION | AA20: =Calculs!BQ9 -> 280 | AG20: =Calculs!BT5 -> Industrialisation | AP20: =Calculs!BU5 -> 540 | AV20: Début planifié | BA20: =IF(Calculs!$AL$23="","",IF(INDEX(Calculs!$EW$4:$EW$503,Calculs!$AL$23)>=2958465,"—",INDEX(Calculs!$EW$4:$EW$503,Calculs!$AL$23))) -> 46461
C21: =Calculs!BL10 | L21: =Calculs!BM10 | S21: =Calculs!BP10 -> VEGA | AA21: =Calculs!BQ10 -> 195 | AG21: =Calculs!BT6 -> Modification | AP21: =Calculs!BU6 -> 535 | AV21: Date de besoin | BA21: =IF(Calculs!$AL$23="","",IF(INDEX(Calculs!$EY$4:$EY$503,Calculs!$AL$23)=0,"—",INDEX(Calculs!$EY$4:$EY$503,Calculs!$AL$23))) -> 46660
C22: =Calculs!BL11 | L22: =Calculs!BM11 | S22: =Calculs!BP11 | AA22: =Calculs!BQ11 | AG22: =Calculs!BT7 -> + 2 autres types | AP22: =Calculs!BU7 -> 350 | AV22: Avancement | BA22: =IF(Calculs!$AL$23="","",INDEX(Calculs!$EU$4:$EU$503,Calculs!$AL$23)) -> 0
B25: INDICATEURS CLÉS
C28: CHARGE TOTALE IDENTIFIÉE | O28: PIC DE CHARGE | AA28: MOIS LE PLUS CHARGÉ | AM28: NOMBRE D'AFFAIRES | AY28: TAUX D'AVANCEMENT MOYEN
C29: =Calculs!$AL$4 -> 3455 | O29: =Calculs!$AL$17 -> 507.8405 | AA29: =IF(Calculs!$AL$17=0,"—",Calculs!$AL$19) -> 46447 | AM29: =Calculs!$AL$5 -> 17 | AY29: =Calculs!$AL$11 -> 0.11120448
C30: =Calculs!$AL$10 -> 3115.5 | O30: =Calculs!$AL$19 -> 46447 | AA30: =Calculs!$AL$20 -> 9 | AM30: =Calculs!$AL$7 -> 7 | AY30: =Calculs!$AL$12 -> 0.098263386
C31: =Calculs!$AL$5 -> 17 | O31: =Calculs!$AL$21 -> 5.078405 | AA31: =Calculs!$AL$26 -> 0.15017462 | AM31: =IF(p_Perimetre="Tous les projets","dont "&Calculs!$AL$24&" ligne(s) terminée(s)",Calculs!$AL$24&" ligne(s) terminée(s) non comptée(s)") -> 2 ligne(s) terminée(s) non comptée(s) | AY31: moyenne simple par affaire
B34: RÉPARTITION DE LA CHARGE
C37: CHARGE EN HEURES PAR MOIS ET PAR PROJET | AI37: RÉPARTITION DE LA CHARGE PAR PROJET
C38: =Calculs!$AL$14 -> 46266 | Q38: =Calculs!$AL$16 -> 73.3 | AI38: Total au centre · une couleur par projet, commune aux deux graphiques
AX42: Projet | BC42: Heures | BF42: Part
AX43: =Calculs!AT4 -> ATLAS | BC43: =IF(Calculs!AT4="","",Calculs!AU4) -> 860 | BF43: =IF(Calculs!AT4="","",Calculs!AV4) -> 0.24891462
AX44: =Calculs!AT5 -> BORÉAL | BC44: =IF(Calculs!AT5="","",Calculs!AU5) -> 620 | BF44: =IF(Calculs!AT5="","",Calculs!AV5) -> 0.17945007
AI45: =Calculs!$AL$4 -> 3455 | AX45: =Calculs!AT6 -> DELTA | BC45: =IF(Calculs!AT6="","",Calculs!AU6) -> 560 | BF45: =IF(Calculs!AT6="","",Calculs!AV6) -> 0.16208394
AX46: =Calculs!AT7 -> PÉGASE | BC46: =IF(Calculs!AT7="","",Calculs!AU7) -> 550 | BF46: =IF(Calculs!AT7="","",Calculs!AV7) -> 0.15918958
AI47: au total | AX47: =Calculs!AT8 -> CASSIOPÉE | BC47: =IF(Calculs!AT8="","",Calculs!AU8) -> 390 | BF47: =IF(Calculs!AT8="","",Calculs!AV8) -> 0.11287988
AX48: =Calculs!AT9 -> ORION | BC48: =IF(Calculs!AT9="","",Calculs!AU9) -> 280 | BF48: =IF(Calculs!AT9="","",Calculs!AV9) -> 0.081041968
AX49: =Calculs!AT10 -> VEGA | BC49: =IF(Calculs!AT10="","",Calculs!AU10) -> 195 | BF49: =IF(Calculs!AT10="","",Calculs!AV10) -> 0.056439942
AX50: =Calculs!AT11 | BC50: =IF(Calculs!AT11="","",Calculs!AU11) | BF50: =IF(Calculs!AT11="","",Calculs!AV11)
AX51: =Calculs!AT12 | BC51: =IF(Calculs!AT12="","",Calculs!AU12) | BF51: =IF(Calculs!AT12="","",Calculs!AV12)
B57: LISTE DES AFFAIRES (un sous-projet par ligne, toutes ressources regroupées, par charge décroissante)
B59: N° | D59: Projet | L59: Sous-projet | T59: Produit | AB59: Chef de projet | AI59: Ressources | AM59: Charge (h) | AR59: % de la charge totale | AX59: Avancement | BD59: Date de début planifiée
B60: =IF(Calculs!$BX$4="","",Calculs!$BW$4) -> 1 | D60: =IF(Calculs!$BX$4="","",INDEX(Charge!$B:$B,Calculs!$BX$4+3)&"") -> PÉGASE | L60: =IF(Calculs!$BX$4="","",INDEX(Charge!$C:$C,Calculs!$BX$4+3)&"") -> Lot 1 | T60: =IF(Calculs!$BX$4="","",INDEX(Charge!$D:$D,Calculs!$BX$4+3)&"") -> Ensemble complet | AB60: =IF(Calculs!$BX$4="","",INDEX(Charge!$A:$A,Calculs!$BX$4+3)&"") -> Camille Laurent | AI60: =IF(Calculs!$BX$4="","",INDEX(Calculs!$ET$4:$ET$503,Calculs!$BX$4)) -> 2 dont 1 ext. | AM60: =IF(Calculs!$BX$4="","",INDEX(Calculs!$EP$4:$EP$503,Calculs!$BX$4)) -> 480 | AR60: =IF(Calculs!$BX$4="","",IF(Calculs!$AL$4=0,0,INDEX(Calculs!$EP$4:$EP$503,Calculs!$BX$4)/Calculs!$AL$4)) -> 0.13892909 | AX60: =IF(Calculs!$BX$4="","",INDEX(Calculs!$EU$4:$EU$503,Calculs!$BX$4)) -> 0 | BD60: =IF(Calculs!$BX$4="","",IF(INDEX(Calculs!$EW$4:$EW$503,Calculs!$BX$4)>=2958465,"à planifier",INDEX(Calculs!$EW$4:$EW$503,Calculs!$BX$4))) -> 46461
B61: =IF(Calculs!$BX$5="","",Calculs!$BW$5) -> 2 | D61: =IF(Calculs!$BX$5="","",INDEX(Charge!$B:$B,Calculs!$BX$5+3)&"") -> ATLAS | L61: =IF(Calculs!$BX$5="","",INDEX(Charge!$C:$C,Calculs!$BX$5+3)&"") -> Lot 1 – Structure | T61: =IF(Calculs!$BX$5="","",INDEX(Charge!$D:$D,Calculs!$BX$5+3)&"") -> Châssis principal | AB61: =IF(Calculs!$BX$5="","",INDEX(Charge!$A:$A,Calculs!$BX$5+3)&"") -> Julie Martin | AI61: =IF(Calculs!$BX$5="","",INDEX(Calculs!$ET$4:$ET$503,Calculs!$BX$5)) -> 2 dont 1 ext. | AM61: =IF(Calculs!$BX$5="","",INDEX(Calculs!$EP$4:$EP$503,Calculs!$BX$5)) -> 420 | AR61: =IF(Calculs!$BX$5="","",IF(Calculs!$AL$4=0,0,INDEX(Calculs!$EP$4:$EP$503,Calculs!$BX$5)/Calculs!$AL$4)) -> 0.12156295 | AX61: =IF(Calculs!$BX$5="","",INDEX(Calculs!$EU$4:$EU$503,Calculs!$BX$5)) -> 0.10714286 | BD61: =IF(Calculs!$BX$5="","",IF(INDEX(Calculs!$EW$4:$EW$503,Calculs!$BX$5)>=2958465,"à planifier",INDEX(Calculs!$EW$4:$EW$503,Calculs!$BX$5))) -> 46328
B62: =IF(Calculs!$BX$6="","",Calculs!$BW$6) -> 3 | D62: =IF(Calculs!$BX$6="","",INDEX(Charge!$B:$B,Calculs!$BX$6+3)&"") -> DELTA | L62: =IF(Calculs!$BX$6="","",INDEX(Charge!$C:$C,Calculs!$BX$6+3)&"") -> Lot unique | T62: =IF(Calculs!$BX$6="","",INDEX(Charge!$D:$D,Calculs!$BX$6+3)&"") -> Bâti machine | AB62: =IF(Calculs!$BX$6="","",INDEX(Charge!$A:$A,Calculs!$BX$6+3)&"") -> Sophie Lefèvre | AI62: =IF(Calculs!$BX$6="","",INDEX(Calculs!$ET$4:$ET$503,Calculs!$BX$6)) -> 2 | AM62: =IF(Calculs!$BX$6="","",INDEX(Calculs!$EP$4:$EP$503,Calculs!$BX$6)) -> 360 | AR62: =IF(Calculs!$BX$6="","",IF(Calculs!$AL$4=0,0,INDEX(Calculs!$EP$4:$EP$503,Calculs!$BX$6)/Calculs!$AL$4)) -> 0.10419682 | AX62: =IF(Calculs!$BX$6="","",INDEX(Calculs!$EU$4:$EU$503,Calculs!$BX$6)) -> 0 | BD62: =IF(Calculs!$BX$6="","",IF(INDEX(Calculs!$EW$4:$EW$503,Calculs!$BX$6)>=2958465,"à planifier",INDEX(Calculs!$EW$4:$EW$503,Calculs!$BX$6))) -> 46433
B63: =IF(Calculs!$BX$7="","",Calculs!$BW$7) -> 4 | D63: =IF(Calculs!$BX$7="","",INDEX(Charge!$B:$B,Calculs!$BX$7+3)&"") -> BORÉAL | L63: =IF(Calculs!$BX$7="","",INDEX(Charge!$C:$C,Calculs!$BX$7+3)&"") -> Phase APD | T63: =IF(Calculs!$BX$7="","",INDEX(Charge!$D:$D,Calculs!$BX$7+3)&"") -> Groupe froid | AB63: =IF(Calculs!$BX$7="","",INDEX(Charge!$A:$A,Calculs!$BX$7+3)&"") -> Thomas Bernard | AI63: =IF(Calculs!$BX$7="","",INDEX(Calculs!$ET$4:$ET$503,Calculs!$BX$7)) -> 1 | AM63: =IF(Calculs!$BX$7="","",INDEX(Calculs!$EP$4:$EP$503,Calculs!$BX$7)) -> 310 | AR63: =IF(Calculs!$BX$7="","",IF(Calculs!$AL$4=0,0,INDEX(Calculs!$EP$4:$EP$503,Calculs!$BX$7)/Calculs!$AL$4)) -> 0.089725036 | AX63: =IF(Calculs!$BX$7="","",INDEX(Calculs!$EU$4:$EU$503,Calculs!$BX$7)) -> 0.35 | BD63: =IF(Calculs!$BX$7="","",IF(INDEX(Calculs!$EW$4:$EW$503,Calculs!$BX$7)>=2958465,"à planifier",INDEX(Calculs!$EW$4:$EW$503,Calculs!$BX$7))) -> 46300
B64: =IF(Calculs!$BX$8="","",Calculs!$BW$8) -> 5 | D64: =IF(Calculs!$BX$8="","",INDEX(Charge!$B:$B,Calculs!$BX$8+3)&"") -> ATLAS | L64: =IF(Calculs!$BX$8="","",INDEX(Charge!$C:$C,Calculs!$BX$8+3)&"") -> Lot 2 – Carénage | T64: =IF(Calculs!$BX$8="","",INDEX(Charge!$D:$D,Calculs!$BX$8+3)&"") -> Capots latéraux | AB64: =IF(Calculs!$BX$8="","",INDEX(Charge!$A:$A,Calculs!$BX$8+3)&"") -> Julie Martin | AI64: =IF(Calculs!$BX$8="","",INDEX(Calculs!$ET$4:$ET$503,Calculs!$BX$8)) -> 1 | AM64: =IF(Calculs!$BX$8="","",INDEX(Calculs!$EP$4:$EP$503,Calculs!$BX$8)) -> 260 | AR64: =IF(Calculs!$BX$8="","",IF(Calculs!$AL$4=0,0,INDEX(Calculs!$EP$4:$EP$503,Calculs!$BX$8)/Calculs!$AL$4)) -> 0.075253256 | AX64: =IF(Calculs!$BX$8="","",INDEX(Calculs!$EU$4:$EU$503,Calculs!$BX$8)) -> 0 | BD64: =IF(Calculs!$BX$8="","",IF(INDEX(Calculs!$EW$4:$EW$503,Calculs!$BX$8)>=2958465,"à planifier",INDEX(Calculs!$EW$4:$EW$503,Calculs!$BX$8))) -> 46398
B65: =IF(Calculs!$BX$9="","",Calculs!$BW$9) -> 6 | D65: =IF(Calculs!$BX$9="","",INDEX(Charge!$B:$B,Calculs!$BX$9+3)&"") -> CASSIOPÉE | L65: =IF(Calculs!$BX$9="","",INDEX(Charge!$C:$C,Calculs!$BX$9+3)&"") -> Rétrofit ligne 2 | T65: =IF(Calculs!$BX$9="","",INDEX(Charge!$D:$D,Calculs!$BX$9+3)&"") -> Poste de contrôle | AB65: =IF(Calculs!$BX$9="","",INDEX(Charge!$A:$A,Calculs!$BX$9+3)&"") -> Sophie Lefèvre | AI65: =IF(Calculs!$BX$9="","",INDEX(Calculs!$ET$4:$ET$503,Calculs!$BX$9)) -> 2 dont 1 ext. | AM65: =IF(Calculs!$BX$9="","",INDEX(Calculs!$EP$4:$EP$503,Calculs!$BX$9)) -> 240 | AR65: =IF(Calculs!$BX$9="","",IF(Calculs!$AL$4=0,0,INDEX(Calculs!$EP$4:$EP$503,Calculs!$BX$9)/Calculs!$AL$4)) -> 0.069464544 | AX65: =IF(Calculs!$BX$9="","",INDEX(Calculs!$EU$4:$EU$503,Calculs!$BX$9)) -> 0.033333333 | BD65: =IF(Calculs!$BX$9="","",IF(INDEX(Calculs!$EW$4:$EW$503,Calculs!$BX$9)>=2958465,"à planifier",INDEX(Calculs!$EW$4:$EW$503,Calculs!$BX$9))) -> 46357
B66: =IF(Calculs!$BX$10="","",Calculs!$BW$10) -> 7 | D66: =IF(Calculs!$BX$10="","",INDEX(Charge!$B:$B,Calculs!$BX$10+3)&"") -> BORÉAL | L66: =IF(Calculs!$BX$10="","",INDEX(Charge!$C:$C,Calculs!$BX$10+3)&"") -> Phase EXE | T66: =IF(Calculs!$BX$10="","",INDEX(Charge!$D:$D,Calculs!$BX$10+3)&"") -> Groupe froid | AB66: =IF(Calculs!$BX$10="","",INDEX(Charge!$A:$A,Calculs!$BX$10+3)&"") -> Thomas Bernard | AI66: =IF(Calculs!$BX$10="","",INDEX(Calculs!$ET$4:$ET$503,Calculs!$BX$10)) -> 1 | AM66: =IF(Calculs!$BX$10="","",INDEX(Calculs!$EP$4:$EP$503,Calculs!$BX$10)) -> 220 | AR66: =IF(Calculs!$BX$10="","",IF(Calculs!$AL$4=0,0,INDEX(Calculs!$EP$4:$EP$503,Calculs!$BX$10)/Calculs!$AL$4)) -> 0.063675832 | AX66: =IF(Calculs!$BX$10="","",INDEX(Calculs!$EU$4:$EU$503,Calculs!$BX$10)) -> 0 | BD66: =IF(Calculs!$BX$10="","",IF(INDEX(Calculs!$EW$4:$EW$503,Calculs!$BX$10)>=2958465,"à planifier",INDEX(Calculs!$EW$4:$EW$503,Calculs!$BX$10))) -> 46419
B67: =IF(Calculs!$BX$11="","",Calculs!$BW$11) -> 8 | D67: =IF(Calculs!$BX$11="","",INDEX(Charge!$B:$B,Calculs!$BX$11+3)&"") -> DELTA | L67: =IF(Calculs!$BX$11="","",INDEX(Charge!$C:$C,Calculs!$BX$11+3)&"") -> Lot unique | T67: =IF(Calculs!$BX$11="","",INDEX(Charge!$D:$D,Calculs!$BX$11+3)&"") -> Habillage | AB67: =IF(Calculs!$BX$11="","",INDEX(Charge!$A:$A,Calculs!$BX$11+3)&"") -> Thomas Bernard | AI67: =IF(Calculs!$BX$11="","",INDEX(Calculs!$ET$4:$ET$503,Calculs!$BX$11)) -> 2 dont 1 ext. | AM67: =IF(Calculs!$BX$11="","",INDEX(Calculs!$EP$4:$EP$503,Calculs!$BX$11)) -> 200 | AR67: =IF(Calculs!$BX$11="","",IF(Calculs!$AL$4=0,0,INDEX(Calculs!$EP$4:$EP$503,Calculs!$BX$11)/Calculs!$AL$4)) -> 0.05788712 | AX67: =IF(Calculs!$BX$11="","",INDEX(Calculs!$EU$4:$EU$503,Calculs!$BX$11)) -> 0 | BD67: =IF(Calculs!$BX$11="","",IF(INDEX(Calculs!$EW$4:$EW$503,Calculs!$BX$11)>=2958465,"à planifier",INDEX(Calculs!$EW$4:$EW$503,Calculs!$BX$11))) -> 46510
B68: =IF(Calculs!$BX$12="","",Calculs!$BW$12) -> 9 | D68: =IF(Calculs!$BX$12="","",INDEX(Charge!$B:$B,Calculs!$BX$12+3)&"") -> ATLAS | L68: =IF(Calculs!$BX$12="","",INDEX(Charge!$C:$C,Calculs!$BX$12+3)&"") -> Lot 3 – Intégration | T68: =IF(Calculs!$BX$12="","",INDEX(Charge!$D:$D,Calculs!$BX$12+3)&"") -> Faisceau électrique | AB68: =IF(Calculs!$BX$12="","",INDEX(Charge!$A:$A,Calculs!$BX$12+3)&"") -> Julie Martin | AI68: =IF(Calculs!$BX$12="","",INDEX(Calculs!$ET$4:$ET$503,Calculs!$BX$12)) -> 1 ext. | AM68: =IF(Calculs!$BX$12="","",INDEX(Calculs!$EP$4:$EP$503,Calculs!$BX$12)) -> 180 | AR68: =IF(Calculs!$BX$12="","",IF(Calculs!$AL$4=0,0,INDEX(Calculs!$EP$4:$EP$503,Calculs!$BX$12)/Calculs!$AL$4)) -> 0.052098408 | AX68: =IF(Calculs!$BX$12="","",INDEX(Calculs!$EU$4:$EU$503,Calculs!$BX$12)) -> 0 | BD68: =IF(Calculs!$BX$12="","",IF(INDEX(Calculs!$EW$4:$EW$503,Calculs!$BX$12)>=2958465,"à planifier",INDEX(Calculs!$EW$4:$EW$503,Calculs!$BX$12))) -> 46482
B69: =IF(Calculs!$BX$13="","",Calculs!$BW$13) -> 10 | D69: =IF(Calculs!$BX$13="","",INDEX(Charge!$B:$B,Calculs!$BX$13+3)&"") -> ORION | L69: =IF(Calculs!$BX$13="","",INDEX(Charge!$C:$C,Calculs!$BX$13+3)&"") -> Tranche 2 | T69: =IF(Calculs!$BX$13="","",INDEX(Charge!$D:$D,Calculs!$BX$13+3)&"") -> Support moteur | AB69: =IF(Calculs!$BX$13="","",INDEX(Charge!$A:$A,Calculs!$BX$13+3)&"") -> Nicolas Moreau | AI69: =IF(Calculs!$BX$13="","",INDEX(Calculs!$ET$4:$ET$503,Calculs!$BX$13)) -> 1 | AM69: =IF(Calculs!$BX$13="","",INDEX(Calculs!$EP$4:$EP$503,Calculs!$BX$13)) -> 160 | AR69: =IF(Calculs!$BX$13="","",IF(Calculs!$AL$4=0,0,INDEX(Calculs!$EP$4:$EP$503,Calculs!$BX$13)/Calculs!$AL$4)) -> 0.046309696 | AX69: =IF(Calculs!$BX$13="","",INDEX(Calculs!$EU$4:$EU$503,Calculs!$BX$13)) -> 0 | BD69: =IF(Calculs!$BX$13="","",IF(INDEX(Calculs!$EW$4:$EW$503,Calculs!$BX$13)>=2958465,"à planifier",INDEX(Calculs!$EW$4:$EW$503,Calculs!$BX$13))) -> 46447
B70: =IF(Calculs!$BX$14="","",Calculs!$BW$14) -> 11 | D70: =IF(Calculs!$BX$14="","",INDEX(Charge!$B:$B,Calculs!$BX$14+3)&"") -> CASSIOPÉE | L70: =IF(Calculs!$BX$14="","",INDEX(Charge!$C:$C,Calculs!$BX$14+3)&"") -> Rétrofit ligne 2 | T70: =IF(Calculs!$BX$14="","",INDEX(Charge!$D:$D,Calculs!$BX$14+3)&"") -> Convoyeur | AB70: =IF(Calculs!$BX$14="","",INDEX(Charge!$A:$A,Calculs!$BX$14+3)&"") -> Sophie Lefèvre | AI70: =IF(Calculs!$BX$14="","",INDEX(Calculs!$ET$4:$ET$503,Calculs!$BX$14)) -> 1 | AM70: =IF(Calculs!$BX$14="","",INDEX(Calculs!$EP$4:$EP$503,Calculs!$BX$14)) -> 150 | AR70: =IF(Calculs!$BX$14="","",IF(Calculs!$AL$4=0,0,INDEX(Calculs!$EP$4:$EP$503,Calculs!$BX$14)/Calculs!$AL$4)) -> 0.04341534 | AX70: =IF(Calculs!$BX$14="","",INDEX(Calculs!$EU$4:$EU$503,Calculs!$BX$14)) -> 0.5 | BD70: =IF(Calculs!$BX$14="","",IF(INDEX(Calculs!$EW$4:$EW$503,Calculs!$BX$14)>=2958465,"à planifier",INDEX(Calculs!$EW$4:$EW$503,Calculs!$BX$14))) -> 46307
B71: =IF(Calculs!$BX$15="","",Calculs!$BW$15) -> 12 | D71: =IF(Calculs!$BX$15="","",INDEX(Charge!$B:$B,Calculs!$BX$15+3)&"") -> ORION | L71: =IF(Calculs!$BX$15="","",INDEX(Charge!$C:$C,Calculs!$BX$15+3)&"") -> Tranche 1 | T71: =IF(Calculs!$BX$15="","",INDEX(Charge!$D:$D,Calculs!$BX$15+3)&"") -> Support moteur | AB71: =IF(Calculs!$BX$15="","",INDEX(Charge!$A:$A,Calculs!$BX$15+3)&"") -> Nicolas Moreau | AI71: =IF(Calculs!$BX$15="","",INDEX(Calculs!$ET$4:$ET$503,Calculs!$BX$15)) -> 1 | AM71: =IF(Calculs!$BX$15="","",INDEX(Calculs!$EP$4:$EP$503,Calculs!$BX$15)) -> 120 | AR71: =IF(Calculs!$BX$15="","",IF(Calculs!$AL$4=0,0,INDEX(Calculs!$EP$4:$EP$503,Calculs!$BX$15)/Calculs!$AL$4)) -> 0.034732272 | AX71: =IF(Calculs!$BX$15="","",INDEX(Calculs!$EU$4:$EU$503,Calculs!$BX$15)) -> 0.8 | BD71: =IF(Calculs!$BX$15="","",IF(INDEX(Calculs!$EW$4:$EW$503,Calculs!$BX$15)>=2958465,"à planifier",INDEX(Calculs!$EW$4:$EW$503,Calculs!$BX$15))) -> 46279
B72: =IF(Calculs!$BX$16="","",Calculs!$BW$16) -> 13 | D72: =IF(Calculs!$BX$16="","",INDEX(Charge!$B:$B,Calculs!$BX$16+3)&"") -> BORÉAL | L72: =IF(Calculs!$BX$16="","",INDEX(Charge!$C:$C,Calculs!$BX$16+3)&"") -> Phase EXE | T72: =IF(Calculs!$BX$16="","",INDEX(Charge!$D:$D,Calculs!$BX$16+3)&"") -> Armoire de commande | AB72: =IF(Calculs!$BX$16="","",INDEX(Charge!$A:$A,Calculs!$BX$16+3)&"") -> Thomas Bernard | AI72: =IF(Calculs!$BX$16="","",INDEX(Calculs!$ET$4:$ET$503,Calculs!$BX$16)) -> 1 ext. | AM72: =IF(Calculs!$BX$16="","",INDEX(Calculs!$EP$4:$EP$503,Calculs!$BX$16)) -> 90 | AR72: =IF(Calculs!$BX$16="","",IF(Calculs!$AL$4=0,0,INDEX(Calculs!$EP$4:$EP$503,Calculs!$BX$16)/Calculs!$AL$4)) -> 0.026049204 | AX72: =IF(Calculs!$BX$16="","",INDEX(Calculs!$EU$4:$EU$503,Calculs!$BX$16)) -> 0 | BD72: =IF(Calculs!$BX$16="","",IF(INDEX(Calculs!$EW$4:$EW$503,Calculs!$BX$16)>=2958465,"à planifier",INDEX(Calculs!$EW$4:$EW$503,Calculs!$BX$16))) -> 46405
B73: =IF(Calculs!$BX$17="","",Calculs!$BW$17) -> 14 | D73: =IF(Calculs!$BX$17="","",INDEX(Charge!$B:$B,Calculs!$BX$17+3)&"") -> VEGA | L73: =IF(Calculs!$BX$17="","",INDEX(Charge!$C:$C,Calculs!$BX$17+3)&"") -> Mise en conformité | T73: =IF(Calculs!$BX$17="","",INDEX(Charge!$D:$D,Calculs!$BX$17+3)&"") -> Garde-corps | AB73: =IF(Calculs!$BX$17="","",INDEX(Charge!$A:$A,Calculs!$BX$17+3)&"") -> Camille Laurent | AI73: =IF(Calculs!$BX$17="","",INDEX(Calculs!$ET$4:$ET$503,Calculs!$BX$17)) -> 1 | AM73: =IF(Calculs!$BX$17="","",INDEX(Calculs!$EP$4:$EP$503,Calculs!$BX$17)) -> 85 | AR73: =IF(Calculs!$BX$17="","",IF(Calculs!$AL$4=0,0,INDEX(Calculs!$EP$4:$EP$503,Calculs!$BX$17)/Calculs!$AL$4)) -> 0.024602026 | AX73: =IF(Calculs!$BX$17="","",INDEX(Calculs!$EU$4:$EU$503,Calculs!$BX$17)) -> 0 | BD73: =IF(Calculs!$BX$17="","",IF(INDEX(Calculs!$EW$4:$EW$503,Calculs!$BX$17)>=2958465,"à planifier",INDEX(Calculs!$EW$4:$EW$503,Calculs!$BX$17))) -> 46349
B74: =IF(Calculs!$BX$18="","",Calculs!$BW$18) -> 15 | D74: =IF(Calculs!$BX$18="","",INDEX(Charge!$B:$B,Calculs!$BX$18+3)&"") -> PÉGASE | L74: =IF(Calculs!$BX$18="","",INDEX(Charge!$C:$C,Calculs!$BX$18+3)&"") -> Avant-projet | T74: =IF(Calculs!$BX$18="","",INDEX(Charge!$D:$D,Calculs!$BX$18+3)&"") -> Ensemble complet | AB74: =IF(Calculs!$BX$18="","",INDEX(Charge!$A:$A,Calculs!$BX$18+3)&"") -> Nicolas Moreau | AI74: =IF(Calculs!$BX$18="","",INDEX(Calculs!$ET$4:$ET$503,Calculs!$BX$18)) -> 1 | AM74: =IF(Calculs!$BX$18="","",INDEX(Calculs!$EP$4:$EP$503,Calculs!$BX$18)) -> 70 | AR74: =IF(Calculs!$BX$18="","",IF(Calculs!$AL$4=0,0,INDEX(Calculs!$EP$4:$EP$503,Calculs!$BX$18)/Calculs!$AL$4)) -> 0.020260492 | AX74: =IF(Calculs!$BX$18="","",INDEX(Calculs!$EU$4:$EU$503,Calculs!$BX$18)) -> 0.1 | BD74: =IF(Calculs!$BX$18="","",IF(INDEX(Calculs!$EW$4:$EW$503,Calculs!$BX$18)>=2958465,"à planifier",INDEX(Calculs!$EW$4:$EW$503,Calculs!$BX$18))) -> 46342
B75: =IF(Calculs!$BX$19="","",Calculs!$BW$19) -> 16 | D75: =IF(Calculs!$BX$19="","",INDEX(Charge!$B:$B,Calculs!$BX$19+3)&"") -> VEGA | L75: =IF(Calculs!$BX$19="","",INDEX(Charge!$C:$C,Calculs!$BX$19+3)&"") -> Mise en conformité | T75: =IF(Calculs!$BX$19="","",INDEX(Charge!$D:$D,Calculs!$BX$19+3)&"") -> Passerelle | AB75: =IF(Calculs!$BX$19="","",INDEX(Charge!$A:$A,Calculs!$BX$19+3)&"") -> Camille Laurent | AI75: =IF(Calculs!$BX$19="","",INDEX(Calculs!$ET$4:$ET$503,Calculs!$BX$19)) -> 1 | AM75: =IF(Calculs!$BX$19="","",INDEX(Calculs!$EP$4:$EP$503,Calculs!$BX$19)) -> 60 | AR75: =IF(Calculs!$BX$19="","",IF(Calculs!$AL$4=0,0,INDEX(Calculs!$EP$4:$EP$503,Calculs!$BX$19)/Calculs!$AL$4)) -> 0.017366136 | AX75: =IF(Calculs!$BX$19="","",INDEX(Calculs!$EU$4:$EU$503,Calculs!$BX$19)) -> 0 | BD75: =IF(Calculs!$BX$19="","",IF(INDEX(Calculs!$EW$4:$EW$503,Calculs!$BX$19)>=2958465,"à planifier",INDEX(Calculs!$EW$4:$EW$503,Calculs!$BX$19))) -> 46426
B76: =IF(Calculs!$BX$20="","",Calculs!$BW$20) -> 17 | D76: =IF(Calculs!$BX$20="","",INDEX(Charge!$B:$B,Calculs!$BX$20+3)&"") -> VEGA | L76: =IF(Calculs!$BX$20="","",INDEX(Charge!$C:$C,Calculs!$BX$20+3)&"") -> Mise en conformité | T76: =IF(Calculs!$BX$20="","",INDEX(Charge!$D:$D,Calculs!$BX$20+3)&"") -> Escalier d'accès | AB76: =IF(Calculs!$BX$20="","",INDEX(Charge!$A:$A,Calculs!$BX$20+3)&"") -> Camille Laurent | AI76: =IF(Calculs!$BX$20="","",INDEX(Calculs!$ET$4:$ET$503,Calculs!$BX$20)) -> à affecter | AM76: =IF(Calculs!$BX$20="","",INDEX(Calculs!$EP$4:$EP$503,Calculs!$BX$20)) -> 50 | AR76: =IF(Calculs!$BX$20="","",IF(Calculs!$AL$4=0,0,INDEX(Calculs!$EP$4:$EP$503,Calculs!$BX$20)/Calculs!$AL$4)) -> 0.01447178 | AX76: =IF(Calculs!$BX$20="","",INDEX(Calculs!$EU$4:$EU$503,Calculs!$BX$20)) -> 0 | BD76: =IF(Calculs!$BX$20="","",IF(INDEX(Calculs!$EW$4:$EW$503,Calculs!$BX$20)>=2958465,"à planifier",INDEX(Calculs!$EW$4:$EW$503,Calculs!$BX$20))) -> 46447
B77: =IF(Calculs!$BX$21="","",Calculs!$BW$21) | D77: =IF(Calculs!$BX$21="","",INDEX(Charge!$B:$B,Calculs!$BX$21+3)&"") | L77: =IF(Calculs!$BX$21="","",INDEX(Charge!$C:$C,Calculs!$BX$21+3)&"") | T77: =IF(Calculs!$BX$21="","",INDEX(Charge!$D:$D,Calculs!$BX$21+3)&"") | AB77: =IF(Calculs!$BX$21="","",INDEX(Charge!$A:$A,Calculs!$BX$21+3)&"") | AI77: =IF(Calculs!$BX$21="","",INDEX(Calculs!$ET$4:$ET$503,Calculs!$BX$21)) | AM77: =IF(Calculs!$BX$21="","",INDEX(Calculs!$EP$4:$EP$503,Calculs!$BX$21)) | AR77: =IF(Calculs!$BX$21="","",IF(Calculs!$AL$4=0,0,INDEX(Calculs!$EP$4:$EP$503,Calculs!$BX$21)/Calculs!$AL$4)) | AX77: =IF(Calculs!$BX$21="","",INDEX(Calculs!$EU$4:$EU$503,Calculs!$BX$21)) | BD77: =IF(Calculs!$BX$21="","",IF(INDEX(Calculs!$EW$4:$EW$503,Calculs!$BX$21)>=2958465,"à planifier",INDEX(Calculs!$EW$4:$EW$503,Calculs!$BX$21)))
B78: =IF(Calculs!$BX$22="","",Calculs!$BW$22) | D78: =IF(Calculs!$BX$22="","",INDEX(Charge!$B:$B,Calculs!$BX$22+3)&"") | L78: =IF(Calculs!$BX$22="","",INDEX(Charge!$C:$C,Calculs!$BX$22+3)&"") | T78: =IF(Calculs!$BX$22="","",INDEX(Charge!$D:$D,Calculs!$BX$22+3)&"") | AB78: =IF(Calculs!$BX$22="","",INDEX(Charge!$A:$A,Calculs!$BX$22+3)&"") | AI78: =IF(Calculs!$BX$22="","",INDEX(Calculs!$ET$4:$ET$503,Calculs!$BX$22)) | AM78: =IF(Calculs!$BX$22="","",INDEX(Calculs!$EP$4:$EP$503,Calculs!$BX$22)) | AR78: =IF(Calculs!$BX$22="","",IF(Calculs!$AL$4=0,0,INDEX(Calculs!$EP$4:$EP$503,Calculs!$BX$22)/Calculs!$AL$4)) | AX78: =IF(Calculs!$BX$22="","",INDEX(Calculs!$EU$4:$EU$503,Calculs!$BX$22)) | BD78: =IF(Calculs!$BX$22="","",IF(INDEX(Calculs!$EW$4:$EW$503,Calculs!$BX$22)>=2958465,"à planifier",INDEX(Calculs!$EW$4:$EW$503,Calculs!$BX$22)))
B79: =IF(Calculs!$BX$23="","",Calculs!$BW$23) | D79: =IF(Calculs!$BX$23="","",INDEX(Charge!$B:$B,Calculs!$BX$23+3)&"") | L79: =IF(Calculs!$BX$23="","",INDEX(Charge!$C:$C,Calculs!$BX$23+3)&"") | T79: =IF(Calculs!$BX$23="","",INDEX(Charge!$D:$D,Calculs!$BX$23+3)&"") | AB79: =IF(Calculs!$BX$23="","",INDEX(Charge!$A:$A,Calculs!$BX$23+3)&"") | AI79: =IF(Calculs!$BX$23="","",INDEX(Calculs!$ET$4:$ET$503,Calculs!$BX$23)) | AM79: =IF(Calculs!$BX$23="","",INDEX(Calculs!$EP$4:$EP$503,Calculs!$BX$23)) | AR79: =IF(Calculs!$BX$23="","",IF(Calculs!$AL$4=0,0,INDEX(Calculs!$EP$4:$EP$503,Calculs!$BX$23)/Calculs!$AL$4)) | AX79: =IF(Calculs!$BX$23="","",INDEX(Calculs!$EU$4:$EU$503,Calculs!$BX$23)) | BD79: =IF(Calculs!$BX$23="","",IF(INDEX(Calculs!$EW$4:$EW$503,Calculs!$BX$23)>=2958465,"à planifier",INDEX(Calculs!$EW$4:$EW$503,Calculs!$BX$23)))
B80: =IF(Calculs!$BX$24="","",Calculs!$BW$24) | D80: =IF(Calculs!$BX$24="","",INDEX(Charge!$B:$B,Calculs!$BX$24+3)&"") | L80: =IF(Calculs!$BX$24="","",INDEX(Charge!$C:$C,Calculs!$BX$24+3)&"") | T80: =IF(Calculs!$BX$24="","",INDEX(Charge!$D:$D,Calculs!$BX$24+3)&"") | AB80: =IF(Calculs!$BX$24="","",INDEX(Charge!$A:$A,Calculs!$BX$24+3)&"") | AI80: =IF(Calculs!$BX$24="","",INDEX(Calculs!$ET$4:$ET$503,Calculs!$BX$24)) | AM80: =IF(Calculs!$BX$24="","",INDEX(Calculs!$EP$4:$EP$503,Calculs!$BX$24)) | AR80: =IF(Calculs!$BX$24="","",IF(Calculs!$AL$4=0,0,INDEX(Calculs!$EP$4:$EP$503,Calculs!$BX$24)/Calculs!$AL$4)) | AX80: =IF(Calculs!$BX$24="","",INDEX(Calculs!$EU$4:$EU$503,Calculs!$BX$24)) | BD80: =IF(Calculs!$BX$24="","",IF(INDEX(Calculs!$EW$4:$EW$503,Calculs!$BX$24)>=2958465,"à planifier",INDEX(Calculs!$EW$4:$EW$503,Calculs!$BX$24)))
B81: =IF(Calculs!$BX$25="","",Calculs!$BW$25) | D81: =IF(Calculs!$BX$25="","",INDEX(Charge!$B:$B,Calculs!$BX$25+3)&"") | L81: =IF(Calculs!$BX$25="","",INDEX(Charge!$C:$C,Calculs!$BX$25+3)&"") | T81: =IF(Calculs!$BX$25="","",INDEX(Charge!$D:$D,Calculs!$BX$25+3)&"") | AB81: =IF(Calculs!$BX$25="","",INDEX(Charge!$A:$A,Calculs!$BX$25+3)&"") | AI81: =IF(Calculs!$BX$25="","",INDEX(Calculs!$ET$4:$ET$503,Calculs!$BX$25)) | AM81: =IF(Calculs!$BX$25="","",INDEX(Calculs!$EP$4:$EP$503,Calculs!$BX$25)) | AR81: =IF(Calculs!$BX$25="","",IF(Calculs!$AL$4=0,0,INDEX(Calculs!$EP$4:$EP$503,Calculs!$BX$25)/Calculs!$AL$4)) | AX81: =IF(Calculs!$BX$25="","",INDEX(Calculs!$EU$4:$EU$503,Calculs!$BX$25)) | BD81: =IF(Calculs!$BX$25="","",IF(INDEX(Calculs!$EW$4:$EW$503,Calculs!$BX$25)>=2958465,"à planifier",INDEX(Calculs!$EW$4:$EW$503,Calculs!$BX$25)))
B82: =IF(Calculs!$BX$26="","",Calculs!$BW$26) | D82: =IF(Calculs!$BX$26="","",INDEX(Charge!$B:$B,Calculs!$BX$26+3)&"") | L82: =IF(Calculs!$BX$26="","",INDEX(Charge!$C:$C,Calculs!$BX$26+3)&"") | T82: =IF(Calculs!$BX$26="","",INDEX(Charge!$D:$D,Calculs!$BX$26+3)&"") | AB82: =IF(Calculs!$BX$26="","",INDEX(Charge!$A:$A,Calculs!$BX$26+3)&"") | AI82: =IF(Calculs!$BX$26="","",INDEX(Calculs!$ET$4:$ET$503,Calculs!$BX$26)) | AM82: =IF(Calculs!$BX$26="","",INDEX(Calculs!$EP$4:$EP$503,Calculs!$BX$26)) | AR82: =IF(Calculs!$BX$26="","",IF(Calculs!$AL$4=0,0,INDEX(Calculs!$EP$4:$EP$503,Calculs!$BX$26)/Calculs!$AL$4)) | AX82: =IF(Calculs!$BX$26="","",INDEX(Calculs!$EU$4:$EU$503,Calculs!$BX$26)) | BD82: =IF(Calculs!$BX$26="","",IF(INDEX(Calculs!$EW$4:$EW$503,Calculs!$BX$26)>=2958465,"à planifier",INDEX(Calculs!$EW$4:$EW$503,Calculs!$BX$26)))
B83: =IF(Calculs!$BX$27="","",Calculs!$BW$27) | D83: =IF(Calculs!$BX$27="","",INDEX(Charge!$B:$B,Calculs!$BX$27+3)&"") | L83: =IF(Calculs!$BX$27="","",INDEX(Charge!$C:$C,Calculs!$BX$27+3)&"") | T83: =IF(Calculs!$BX$27="","",INDEX(Charge!$D:$D,Calculs!$BX$27+3)&"") | AB83: =IF(Calculs!$BX$27="","",INDEX(Charge!$A:$A,Calculs!$BX$27+3)&"") | AI83: =IF(Calculs!$BX$27="","",INDEX(Calculs!$ET$4:$ET$503,Calculs!$BX$27)) | AM83: =IF(Calculs!$BX$27="","",INDEX(Calculs!$EP$4:$EP$503,Calculs!$BX$27)) | AR83: =IF(Calculs!$BX$27="","",IF(Calculs!$AL$4=0,0,INDEX(Calculs!$EP$4:$EP$503,Calculs!$BX$27)/Calculs!$AL$4)) | AX83: =IF(Calculs!$BX$27="","",INDEX(Calculs!$EU$4:$EU$503,Calculs!$BX$27)) | BD83: =IF(Calculs!$BX$27="","",IF(INDEX(Calculs!$EW$4:$EW$503,Calculs!$BX$27)>=2958465,"à planifier",INDEX(Calculs!$EW$4:$EW$503,Calculs!$BX$27)))
B84: =IF(Calculs!$BX$28="","",Calculs!$BW$28) | D84: =IF(Calculs!$BX$28="","",INDEX(Charge!$B:$B,Calculs!$BX$28+3)&"") | L84: =IF(Calculs!$BX$28="","",INDEX(Charge!$C:$C,Calculs!$BX$28+3)&"") | T84: =IF(Calculs!$BX$28="","",INDEX(Charge!$D:$D,Calculs!$BX$28+3)&"") | AB84: =IF(Calculs!$BX$28="","",INDEX(Charge!$A:$A,Calculs!$BX$28+3)&"") | AI84: =IF(Calculs!$BX$28="","",INDEX(Calculs!$ET$4:$ET$503,Calculs!$BX$28)) | AM84: =IF(Calculs!$BX$28="","",INDEX(Calculs!$EP$4:$EP$503,Calculs!$BX$28)) | AR84: =IF(Calculs!$BX$28="","",IF(Calculs!$AL$4=0,0,INDEX(Calculs!$EP$4:$EP$503,Calculs!$BX$28)/Calculs!$AL$4)) | AX84: =IF(Calculs!$BX$28="","",INDEX(Calculs!$EU$4:$EU$503,Calculs!$BX$28)) | BD84: =IF(Calculs!$BX$28="","",IF(INDEX(Calculs!$EW$4:$EW$503,Calculs!$BX$28)>=2958465,"à planifier",INDEX(Calculs!$EW$4:$EW$503,Calculs!$BX$28)))
B85: =IF(Calculs!$BX$29="","",Calculs!$BW$29) | D85: =IF(Calculs!$BX$29="","",INDEX(Charge!$B:$B,Calculs!$BX$29+3)&"") | L85: =IF(Calculs!$BX$29="","",INDEX(Charge!$C:$C,Calculs!$BX$29+3)&"") | T85: =IF(Calculs!$BX$29="","",INDEX(Charge!$D:$D,Calculs!$BX$29+3)&"") | AB85: =IF(Calculs!$BX$29="","",INDEX(Charge!$A:$A,Calculs!$BX$29+3)&"") | AI85: =IF(Calculs!$BX$29="","",INDEX(Calculs!$ET$4:$ET$503,Calculs!$BX$29)) | AM85: =IF(Calculs!$BX$29="","",INDEX(Calculs!$EP$4:$EP$503,Calculs!$BX$29)) | AR85: =IF(Calculs!$BX$29="","",IF(Calculs!$AL$4=0,0,INDEX(Calculs!$EP$4:$EP$503,Calculs!$BX$29)/Calculs!$AL$4)) | AX85: =IF(Calculs!$BX$29="","",INDEX(Calculs!$EU$4:$EU$503,Calculs!$BX$29)) | BD85: =IF(Calculs!$BX$29="","",IF(INDEX(Calculs!$EW$4:$EW$503,Calculs!$BX$29)>=2958465,"à planifier",INDEX(Calculs!$EW$4:$EW$503,Calculs!$BX$29)))
B86: =IF(Calculs!$BX$30="","",Calculs!$BW$30) | D86: =IF(Calculs!$BX$30="","",INDEX(Charge!$B:$B,Calculs!$BX$30+3)&"") | L86: =IF(Calculs!$BX$30="","",INDEX(Charge!$C:$C,Calculs!$BX$30+3)&"") | T86: =IF(Calculs!$BX$30="","",INDEX(Charge!$D:$D,Calculs!$BX$30+3)&"") | AB86: =IF(Calculs!$BX$30="","",INDEX(Charge!$A:$A,Calculs!$BX$30+3)&"") | AI86: =IF(Calculs!$BX$30="","",INDEX(Calculs!$ET$4:$ET$503,Calculs!$BX$30)) | AM86: =IF(Calculs!$BX$30="","",INDEX(Calculs!$EP$4:$EP$503,Calculs!$BX$30)) | AR86: =IF(Calculs!$BX$30="","",IF(Calculs!$AL$4=0,0,INDEX(Calculs!$EP$4:$EP$503,Calculs!$BX$30)/Calculs!$AL$4)) | AX86: =IF(Calculs!$BX$30="","",INDEX(Calculs!$EU$4:$EU$503,Calculs!$BX$30)) | BD86: =IF(Calculs!$BX$30="","",IF(INDEX(Calculs!$EW$4:$EW$503,Calculs!$BX$30)>=2958465,"à planifier",INDEX(Calculs!$EW$4:$EW$503,Calculs!$BX$30)))
B87: =IF(Calculs!$BX$31="","",Calculs!$BW$31) | D87: =IF(Calculs!$BX$31="","",INDEX(Charge!$B:$B,Calculs!$BX$31+3)&"") | L87: =IF(Calculs!$BX$31="","",INDEX(Charge!$C:$C,Calculs!$BX$31+3)&"") | T87: =IF(Calculs!$BX$31="","",INDEX(Charge!$D:$D,Calculs!$BX$31+3)&"") | AB87: =IF(Calculs!$BX$31="","",INDEX(Charge!$A:$A,Calculs!$BX$31+3)&"") | AI87: =IF(Calculs!$BX$31="","",INDEX(Calculs!$ET$4:$ET$503,Calculs!$BX$31)) | AM87: =IF(Calculs!$BX$31="","",INDEX(Calculs!$EP$4:$EP$503,Calculs!$BX$31)) | AR87: =IF(Calculs!$BX$31="","",IF(Calculs!$AL$4=0,0,INDEX(Calculs!$EP$4:$EP$503,Calculs!$BX$31)/Calculs!$AL$4)) | AX87: =IF(Calculs!$BX$31="","",INDEX(Calculs!$EU$4:$EU$503,Calculs!$BX$31)) | BD87: =IF(Calculs!$BX$31="","",IF(INDEX(Calculs!$EW$4:$EW$503,Calculs!$BX$31)>=2958465,"à planifier",INDEX(Calculs!$EW$4:$EW$503,Calculs!$BX$31)))
B88: =IF(Calculs!$BX$32="","",Calculs!$BW$32) | D88: =IF(Calculs!$BX$32="","",INDEX(Charge!$B:$B,Calculs!$BX$32+3)&"") | L88: =IF(Calculs!$BX$32="","",INDEX(Charge!$C:$C,Calculs!$BX$32+3)&"") | T88: =IF(Calculs!$BX$32="","",INDEX(Charge!$D:$D,Calculs!$BX$32+3)&"") | AB88: =IF(Calculs!$BX$32="","",INDEX(Charge!$A:$A,Calculs!$BX$32+3)&"") | AI88: =IF(Calculs!$BX$32="","",INDEX(Calculs!$ET$4:$ET$503,Calculs!$BX$32)) | AM88: =IF(Calculs!$BX$32="","",INDEX(Calculs!$EP$4:$EP$503,Calculs!$BX$32)) | AR88: =IF(Calculs!$BX$32="","",IF(Calculs!$AL$4=0,0,INDEX(Calculs!$EP$4:$EP$503,Calculs!$BX$32)/Calculs!$AL$4)) | AX88: =IF(Calculs!$BX$32="","",INDEX(Calculs!$EU$4:$EU$503,Calculs!$BX$32)) | BD88: =IF(Calculs!$BX$32="","",IF(INDEX(Calculs!$EW$4:$EW$503,Calculs!$BX$32)>=2958465,"à planifier",INDEX(Calculs!$EW$4:$EW$503,Calculs!$BX$32)))
B89: =IF(Calculs!$BX$33="","",Calculs!$BW$33) | D89: =IF(Calculs!$BX$33="","",INDEX(Charge!$B:$B,Calculs!$BX$33+3)&"") | L89: =IF(Calculs!$BX$33="","",INDEX(Charge!$C:$C,Calculs!$BX$33+3)&"") | T89: =IF(Calculs!$BX$33="","",INDEX(Charge!$D:$D,Calculs!$BX$33+3)&"") | AB89: =IF(Calculs!$BX$33="","",INDEX(Charge!$A:$A,Calculs!$BX$33+3)&"") | AI89: =IF(Calculs!$BX$33="","",INDEX(Calculs!$ET$4:$ET$503,Calculs!$BX$33)) | AM89: =IF(Calculs!$BX$33="","",INDEX(Calculs!$EP$4:$EP$503,Calculs!$BX$33)) | AR89: =IF(Calculs!$BX$33="","",IF(Calculs!$AL$4=0,0,INDEX(Calculs!$EP$4:$EP$503,Calculs!$BX$33)/Calculs!$AL$4)) | AX89: =IF(Calculs!$BX$33="","",INDEX(Calculs!$EU$4:$EU$503,Calculs!$BX$33)) | BD89: =IF(Calculs!$BX$33="","",IF(INDEX(Calculs!$EW$4:$EW$503,Calculs!$BX$33)>=2958465,"à planifier",INDEX(Calculs!$EW$4:$EW$503,Calculs!$BX$33)))
B90: =IF(Calculs!$BX$34="","",Calculs!$BW$34) | D90: =IF(Calculs!$BX$34="","",INDEX(Charge!$B:$B,Calculs!$BX$34+3)&"") | L90: =IF(Calculs!$BX$34="","",INDEX(Charge!$C:$C,Calculs!$BX$34+3)&"") | T90: =IF(Calculs!$BX$34="","",INDEX(Charge!$D:$D,Calculs!$BX$34+3)&"") | AB90: =IF(Calculs!$BX$34="","",INDEX(Charge!$A:$A,Calculs!$BX$34+3)&"") | AI90: =IF(Calculs!$BX$34="","",INDEX(Calculs!$ET$4:$ET$503,Calculs!$BX$34)) | AM90: =IF(Calculs!$BX$34="","",INDEX(Calculs!$EP$4:$EP$503,Calculs!$BX$34)) | AR90: =IF(Calculs!$BX$34="","",IF(Calculs!$AL$4=0,0,INDEX(Calculs!$EP$4:$EP$503,Calculs!$BX$34)/Calculs!$AL$4)) | AX90: =IF(Calculs!$BX$34="","",INDEX(Calculs!$EU$4:$EU$503,Calculs!$BX$34)) | BD90: =IF(Calculs!$BX$34="","",IF(INDEX(Calculs!$EW$4:$EW$503,Calculs!$BX$34)>=2958465,"à planifier",INDEX(Calculs!$EW$4:$EW$503,Calculs!$BX$34)))
B91: =IF(Calculs!$BX$35="","",Calculs!$BW$35) | D91: =IF(Calculs!$BX$35="","",INDEX(Charge!$B:$B,Calculs!$BX$35+3)&"") | L91: =IF(Calculs!$BX$35="","",INDEX(Charge!$C:$C,Calculs!$BX$35+3)&"") | T91: =IF(Calculs!$BX$35="","",INDEX(Charge!$D:$D,Calculs!$BX$35+3)&"") | AB91: =IF(Calculs!$BX$35="","",INDEX(Charge!$A:$A,Calculs!$BX$35+3)&"") | AI91: =IF(Calculs!$BX$35="","",INDEX(Calculs!$ET$4:$ET$503,Calculs!$BX$35)) | AM91: =IF(Calculs!$BX$35="","",INDEX(Calculs!$EP$4:$EP$503,Calculs!$BX$35)) | AR91: =IF(Calculs!$BX$35="","",IF(Calculs!$AL$4=0,0,INDEX(Calculs!$EP$4:$EP$503,Calculs!$BX$35)/Calculs!$AL$4)) | AX91: =IF(Calculs!$BX$35="","",INDEX(Calculs!$EU$4:$EU$503,Calculs!$BX$35)) | BD91: =IF(Calculs!$BX$35="","",IF(INDEX(Calculs!$EW$4:$EW$503,Calculs!$BX$35)>=2958465,"à planifier",INDEX(Calculs!$EW$4:$EW$503,Calculs!$BX$35)))
B92: =IF(Calculs!$BX$36="","",Calculs!$BW$36) | D92: =IF(Calculs!$BX$36="","",INDEX(Charge!$B:$B,Calculs!$BX$36+3)&"") | L92: =IF(Calculs!$BX$36="","",INDEX(Charge!$C:$C,Calculs!$BX$36+3)&"") | T92: =IF(Calculs!$BX$36="","",INDEX(Charge!$D:$D,Calculs!$BX$36+3)&"") | AB92: =IF(Calculs!$BX$36="","",INDEX(Charge!$A:$A,Calculs!$BX$36+3)&"") | AI92: =IF(Calculs!$BX$36="","",INDEX(Calculs!$ET$4:$ET$503,Calculs!$BX$36)) | AM92: =IF(Calculs!$BX$36="","",INDEX(Calculs!$EP$4:$EP$503,Calculs!$BX$36)) | AR92: =IF(Calculs!$BX$36="","",IF(Calculs!$AL$4=0,0,INDEX(Calculs!$EP$4:$EP$503,Calculs!$BX$36)/Calculs!$AL$4)) | AX92: =IF(Calculs!$BX$36="","",INDEX(Calculs!$EU$4:$EU$503,Calculs!$BX$36)) | BD92: =IF(Calculs!$BX$36="","",IF(INDEX(Calculs!$EW$4:$EW$503,Calculs!$BX$36)>=2958465,"à planifier",INDEX(Calculs!$EW$4:$EW$503,Calculs!$BX$36)))
B93: =IF(Calculs!$BX$37="","",Calculs!$BW$37) | D93: =IF(Calculs!$BX$37="","",INDEX(Charge!$B:$B,Calculs!$BX$37+3)&"") | L93: =IF(Calculs!$BX$37="","",INDEX(Charge!$C:$C,Calculs!$BX$37+3)&"") | T93: =IF(Calculs!$BX$37="","",INDEX(Charge!$D:$D,Calculs!$BX$37+3)&"") | AB93: =IF(Calculs!$BX$37="","",INDEX(Charge!$A:$A,Calculs!$BX$37+3)&"") | AI93: =IF(Calculs!$BX$37="","",INDEX(Calculs!$ET$4:$ET$503,Calculs!$BX$37)) | AM93: =IF(Calculs!$BX$37="","",INDEX(Calculs!$EP$4:$EP$503,Calculs!$BX$37)) | AR93: =IF(Calculs!$BX$37="","",IF(Calculs!$AL$4=0,0,INDEX(Calculs!$EP$4:$EP$503,Calculs!$BX$37)/Calculs!$AL$4)) | AX93: =IF(Calculs!$BX$37="","",INDEX(Calculs!$EU$4:$EU$503,Calculs!$BX$37)) | BD93: =IF(Calculs!$BX$37="","",IF(INDEX(Calculs!$EW$4:$EW$503,Calculs!$BX$37)>=2958465,"à planifier",INDEX(Calculs!$EW$4:$EW$503,Calculs!$BX$37)))
B94: =IF(Calculs!$BX$38="","",Calculs!$BW$38) | D94: =IF(Calculs!$BX$38="","",INDEX(Charge!$B:$B,Calculs!$BX$38+3)&"") | L94: =IF(Calculs!$BX$38="","",INDEX(Charge!$C:$C,Calculs!$BX$38+3)&"") | T94: =IF(Calculs!$BX$38="","",INDEX(Charge!$D:$D,Calculs!$BX$38+3)&"") | AB94: =IF(Calculs!$BX$38="","",INDEX(Charge!$A:$A,Calculs!$BX$38+3)&"") | AI94: =IF(Calculs!$BX$38="","",INDEX(Calculs!$ET$4:$ET$503,Calculs!$BX$38)) | AM94: =IF(Calculs!$BX$38="","",INDEX(Calculs!$EP$4:$EP$503,Calculs!$BX$38)) | AR94: =IF(Calculs!$BX$38="","",IF(Calculs!$AL$4=0,0,INDEX(Calculs!$EP$4:$EP$503,Calculs!$BX$38)/Calculs!$AL$4)) | AX94: =IF(Calculs!$BX$38="","",INDEX(Calculs!$EU$4:$EU$503,Calculs!$BX$38)) | BD94: =IF(Calculs!$BX$38="","",IF(INDEX(Calculs!$EW$4:$EW$503,Calculs!$BX$38)>=2958465,"à planifier",INDEX(Calculs!$EW$4:$EW$503,Calculs!$BX$38)))
B95: =IF(Calculs!$BX$39="","",Calculs!$BW$39) | D95: =IF(Calculs!$BX$39="","",INDEX(Charge!$B:$B,Calculs!$BX$39+3)&"") | L95: =IF(Calculs!$BX$39="","",INDEX(Charge!$C:$C,Calculs!$BX$39+3)&"") | T95: =IF(Calculs!$BX$39="","",INDEX(Charge!$D:$D,Calculs!$BX$39+3)&"") | AB95: =IF(Calculs!$BX$39="","",INDEX(Charge!$A:$A,Calculs!$BX$39+3)&"") | AI95: =IF(Calculs!$BX$39="","",INDEX(Calculs!$ET$4:$ET$503,Calculs!$BX$39)) | AM95: =IF(Calculs!$BX$39="","",INDEX(Calculs!$EP$4:$EP$503,Calculs!$BX$39)) | AR95: =IF(Calculs!$BX$39="","",IF(Calculs!$AL$4=0,0,INDEX(Calculs!$EP$4:$EP$503,Calculs!$BX$39)/Calculs!$AL$4)) | AX95: =IF(Calculs!$BX$39="","",INDEX(Calculs!$EU$4:$EU$503,Calculs!$BX$39)) | BD95: =IF(Calculs!$BX$39="","",IF(INDEX(Calculs!$EW$4:$EW$503,Calculs!$BX$39)>=2958465,"à planifier",INDEX(Calculs!$EW$4:$EW$503,Calculs!$BX$39)))
B96: =IF(Calculs!$BX$40="","",Calculs!$BW$40) | D96: =IF(Calculs!$BX$40="","",INDEX(Charge!$B:$B,Calculs!$BX$40+3)&"") | L96: =IF(Calculs!$BX$40="","",INDEX(Charge!$C:$C,Calculs!$BX$40+3)&"") | T96: =IF(Calculs!$BX$40="","",INDEX(Charge!$D:$D,Calculs!$BX$40+3)&"") | AB96: =IF(Calculs!$BX$40="","",INDEX(Charge!$A:$A,Calculs!$BX$40+3)&"") | AI96: =IF(Calculs!$BX$40="","",INDEX(Calculs!$ET$4:$ET$503,Calculs!$BX$40)) | AM96: =IF(Calculs!$BX$40="","",INDEX(Calculs!$EP$4:$EP$503,Calculs!$BX$40)) | AR96: =IF(Calculs!$BX$40="","",IF(Calculs!$AL$4=0,0,INDEX(Calculs!$EP$4:$EP$503,Calculs!$BX$40)/Calculs!$AL$4)) | AX96: =IF(Calculs!$BX$40="","",INDEX(Calculs!$EU$4:$EU$503,Calculs!$BX$40)) | BD96: =IF(Calculs!$BX$40="","",IF(INDEX(Calculs!$EW$4:$EW$503,Calculs!$BX$40)>=2958465,"à planifier",INDEX(Calculs!$EW$4:$EW$503,Calculs!$BX$40)))
B97: =IF(Calculs!$BX$41="","",Calculs!$BW$41) | D97: =IF(Calculs!$BX$41="","",INDEX(Charge!$B:$B,Calculs!$BX$41+3)&"") | L97: =IF(Calculs!$BX$41="","",INDEX(Charge!$C:$C,Calculs!$BX$41+3)&"") | T97: =IF(Calculs!$BX$41="","",INDEX(Charge!$D:$D,Calculs!$BX$41+3)&"") | AB97: =IF(Calculs!$BX$41="","",INDEX(Charge!$A:$A,Calculs!$BX$41+3)&"") | AI97: =IF(Calculs!$BX$41="","",INDEX(Calculs!$ET$4:$ET$503,Calculs!$BX$41)) | AM97: =IF(Calculs!$BX$41="","",INDEX(Calculs!$EP$4:$EP$503,Calculs!$BX$41)) | AR97: =IF(Calculs!$BX$41="","",IF(Calculs!$AL$4=0,0,INDEX(Calculs!$EP$4:$EP$503,Calculs!$BX$41)/Calculs!$AL$4)) | AX97: =IF(Calculs!$BX$41="","",INDEX(Calculs!$EU$4:$EU$503,Calculs!$BX$41)) | BD97: =IF(Calculs!$BX$41="","",IF(INDEX(Calculs!$EW$4:$EW$503,Calculs!$BX$41)>=2958465,"à planifier",INDEX(Calculs!$EW$4:$EW$503,Calculs!$BX$41)))
B98: =IF(Calculs!$BX$42="","",Calculs!$BW$42) | D98: =IF(Calculs!$BX$42="","",INDEX(Charge!$B:$B,Calculs!$BX$42+3)&"") | L98: =IF(Calculs!$BX$42="","",INDEX(Charge!$C:$C,Calculs!$BX$42+3)&"") | T98: =IF(Calculs!$BX$42="","",INDEX(Charge!$D:$D,Calculs!$BX$42+3)&"") | AB98: =IF(Calculs!$BX$42="","",INDEX(Charge!$A:$A,Calculs!$BX$42+3)&"") | AI98: =IF(Calculs!$BX$42="","",INDEX(Calculs!$ET$4:$ET$503,Calculs!$BX$42)) | AM98: =IF(Calculs!$BX$42="","",INDEX(Calculs!$EP$4:$EP$503,Calculs!$BX$42)) | AR98: =IF(Calculs!$BX$42="","",IF(Calculs!$AL$4=0,0,INDEX(Calculs!$EP$4:$EP$503,Calculs!$BX$42)/Calculs!$AL$4)) | AX98: =IF(Calculs!$BX$42="","",INDEX(Calculs!$EU$4:$EU$503,Calculs!$BX$42)) | BD98: =IF(Calculs!$BX$42="","",IF(INDEX(Calculs!$EW$4:$EW$503,Calculs!$BX$42)>=2958465,"à planifier",INDEX(Calculs!$EW$4:$EW$503,Calculs!$BX$42)))
B99: =IF(Calculs!$BX$43="","",Calculs!$BW$43) | D99: =IF(Calculs!$BX$43="","",INDEX(Charge!$B:$B,Calculs!$BX$43+3)&"") | L99: =IF(Calculs!$BX$43="","",INDEX(Charge!$C:$C,Calculs!$BX$43+3)&"") | T99: =IF(Calculs!$BX$43="","",INDEX(Charge!$D:$D,Calculs!$BX$43+3)&"") | AB99: =IF(Calculs!$BX$43="","",INDEX(Charge!$A:$A,Calculs!$BX$43+3)&"") | AI99: =IF(Calculs!$BX$43="","",INDEX(Calculs!$ET$4:$ET$503,Calculs!$BX$43)) | AM99: =IF(Calculs!$BX$43="","",INDEX(Calculs!$EP$4:$EP$503,Calculs!$BX$43)) | AR99: =IF(Calculs!$BX$43="","",IF(Calculs!$AL$4=0,0,INDEX(Calculs!$EP$4:$EP$503,Calculs!$BX$43)/Calculs!$AL$4)) | AX99: =IF(Calculs!$BX$43="","",INDEX(Calculs!$EU$4:$EU$503,Calculs!$BX$43)) | BD99: =IF(Calculs!$BX$43="","",IF(INDEX(Calculs!$EW$4:$EW$503,Calculs!$BX$43)>=2958465,"à planifier",INDEX(Calculs!$EW$4:$EW$503,Calculs!$BX$43)))
B100: =IF(Calculs!$BX$44="","",Calculs!$BW$44) | D100: =IF(Calculs!$BX$44="","",INDEX(Charge!$B:$B,Calculs!$BX$44+3)&"") | L100: =IF(Calculs!$BX$44="","",INDEX(Charge!$C:$C,Calculs!$BX$44+3)&"") | T100: =IF(Calculs!$BX$44="","",INDEX(Charge!$D:$D,Calculs!$BX$44+3)&"") | AB100: =IF(Calculs!$BX$44="","",INDEX(Charge!$A:$A,Calculs!$BX$44+3)&"") | AI100: =IF(Calculs!$BX$44="","",INDEX(Calculs!$ET$4:$ET$503,Calculs!$BX$44)) | AM100: =IF(Calculs!$BX$44="","",INDEX(Calculs!$EP$4:$EP$503,Calculs!$BX$44)) | AR100: =IF(Calculs!$BX$44="","",IF(Calculs!$AL$4=0,0,INDEX(Calculs!$EP$4:$EP$503,Calculs!$BX$44)/Calculs!$AL$4)) | AX100: =IF(Calculs!$BX$44="","",INDEX(Calculs!$EU$4:$EU$503,Calculs!$BX$44)) | BD100: =IF(Calculs!$BX$44="","",IF(INDEX(Calculs!$EW$4:$EW$503,Calculs!$BX$44)>=2958465,"à planifier",INDEX(Calculs!$EW$4:$EW$503,Calculs!$BX$44)))
B101: =IF(Calculs!$BX$45="","",Calculs!$BW$45) | D101: =IF(Calculs!$BX$45="","",INDEX(Charge!$B:$B,Calculs!$BX$45+3)&"") | L101: =IF(Calculs!$BX$45="","",INDEX(Charge!$C:$C,Calculs!$BX$45+3)&"") | T101: =IF(Calculs!$BX$45="","",INDEX(Charge!$D:$D,Calculs!$BX$45+3)&"") | AB101: =IF(Calculs!$BX$45="","",INDEX(Charge!$A:$A,Calculs!$BX$45+3)&"") | AI101: =IF(Calculs!$BX$45="","",INDEX(Calculs!$ET$4:$ET$503,Calculs!$BX$45)) | AM101: =IF(Calculs!$BX$45="","",INDEX(Calculs!$EP$4:$EP$503,Calculs!$BX$45)) | AR101: =IF(Calculs!$BX$45="","",IF(Calculs!$AL$4=0,0,INDEX(Calculs!$EP$4:$EP$503,Calculs!$BX$45)/Calculs!$AL$4)) | AX101: =IF(Calculs!$BX$45="","",INDEX(Calculs!$EU$4:$EU$503,Calculs!$BX$45)) | BD101: =IF(Calculs!$BX$45="","",IF(INDEX(Calculs!$EW$4:$EW$503,Calculs!$BX$45)>=2958465,"à planifier",INDEX(Calculs!$EW$4:$EW$503,Calculs!$BX$45)))
B102: =IF(Calculs!$BX$46="","",Calculs!$BW$46) | D102: =IF(Calculs!$BX$46="","",INDEX(Charge!$B:$B,Calculs!$BX$46+3)&"") | L102: =IF(Calculs!$BX$46="","",INDEX(Charge!$C:$C,Calculs!$BX$46+3)&"") | T102: =IF(Calculs!$BX$46="","",INDEX(Charge!$D:$D,Calculs!$BX$46+3)&"") | AB102: =IF(Calculs!$BX$46="","",INDEX(Charge!$A:$A,Calculs!$BX$46+3)&"") | AI102: =IF(Calculs!$BX$46="","",INDEX(Calculs!$ET$4:$ET$503,Calculs!$BX$46)) | AM102: =IF(Calculs!$BX$46="","",INDEX(Calculs!$EP$4:$EP$503,Calculs!$BX$46)) | AR102: =IF(Calculs!$BX$46="","",IF(Calculs!$AL$4=0,0,INDEX(Calculs!$EP$4:$EP$503,Calculs!$BX$46)/Calculs!$AL$4)) | AX102: =IF(Calculs!$BX$46="","",INDEX(Calculs!$EU$4:$EU$503,Calculs!$BX$46)) | BD102: =IF(Calculs!$BX$46="","",IF(INDEX(Calculs!$EW$4:$EW$503,Calculs!$BX$46)>=2958465,"à planifier",INDEX(Calculs!$EW$4:$EW$503,Calculs!$BX$46)))
B103: =IF(Calculs!$BX$47="","",Calculs!$BW$47) | D103: =IF(Calculs!$BX$47="","",INDEX(Charge!$B:$B,Calculs!$BX$47+3)&"") | L103: =IF(Calculs!$BX$47="","",INDEX(Charge!$C:$C,Calculs!$BX$47+3)&"") | T103: =IF(Calculs!$BX$47="","",INDEX(Charge!$D:$D,Calculs!$BX$47+3)&"") | AB103: =IF(Calculs!$BX$47="","",INDEX(Charge!$A:$A,Calculs!$BX$47+3)&"") | AI103: =IF(Calculs!$BX$47="","",INDEX(Calculs!$ET$4:$ET$503,Calculs!$BX$47)) | AM103: =IF(Calculs!$BX$47="","",INDEX(Calculs!$EP$4:$EP$503,Calculs!$BX$47)) | AR103: =IF(Calculs!$BX$47="","",IF(Calculs!$AL$4=0,0,INDEX(Calculs!$EP$4:$EP$503,Calculs!$BX$47)/Calculs!$AL$4)) | AX103: =IF(Calculs!$BX$47="","",INDEX(Calculs!$EU$4:$EU$503,Calculs!$BX$47)) | BD103: =IF(Calculs!$BX$47="","",IF(INDEX(Calculs!$EW$4:$EW$503,Calculs!$BX$47)>=2958465,"à planifier",INDEX(Calculs!$EW$4:$EW$503,Calculs!$BX$47)))
B104: =IF(Calculs!$BX$48="","",Calculs!$BW$48) | D104: =IF(Calculs!$BX$48="","",INDEX(Charge!$B:$B,Calculs!$BX$48+3)&"") | L104: =IF(Calculs!$BX$48="","",INDEX(Charge!$C:$C,Calculs!$BX$48+3)&"") | T104: =IF(Calculs!$BX$48="","",INDEX(Charge!$D:$D,Calculs!$BX$48+3)&"") | AB104: =IF(Calculs!$BX$48="","",INDEX(Charge!$A:$A,Calculs!$BX$48+3)&"") | AI104: =IF(Calculs!$BX$48="","",INDEX(Calculs!$ET$4:$ET$503,Calculs!$BX$48)) | AM104: =IF(Calculs!$BX$48="","",INDEX(Calculs!$EP$4:$EP$503,Calculs!$BX$48)) | AR104: =IF(Calculs!$BX$48="","",IF(Calculs!$AL$4=0,0,INDEX(Calculs!$EP$4:$EP$503,Calculs!$BX$48)/Calculs!$AL$4)) | AX104: =IF(Calculs!$BX$48="","",INDEX(Calculs!$EU$4:$EU$503,Calculs!$BX$48)) | BD104: =IF(Calculs!$BX$48="","",IF(INDEX(Calculs!$EW$4:$EW$503,Calculs!$BX$48)>=2958465,"à planifier",INDEX(Calculs!$EW$4:$EW$503,Calculs!$BX$48)))
B105: =IF(Calculs!$BX$49="","",Calculs!$BW$49) | D105: =IF(Calculs!$BX$49="","",INDEX(Charge!$B:$B,Calculs!$BX$49+3)&"") | L105: =IF(Calculs!$BX$49="","",INDEX(Charge!$C:$C,Calculs!$BX$49+3)&"") | T105: =IF(Calculs!$BX$49="","",INDEX(Charge!$D:$D,Calculs!$BX$49+3)&"") | AB105: =IF(Calculs!$BX$49="","",INDEX(Charge!$A:$A,Calculs!$BX$49+3)&"") | AI105: =IF(Calculs!$BX$49="","",INDEX(Calculs!$ET$4:$ET$503,Calculs!$BX$49)) | AM105: =IF(Calculs!$BX$49="","",INDEX(Calculs!$EP$4:$EP$503,Calculs!$BX$49)) | AR105: =IF(Calculs!$BX$49="","",IF(Calculs!$AL$4=0,0,INDEX(Calculs!$EP$4:$EP$503,Calculs!$BX$49)/Calculs!$AL$4)) | AX105: =IF(Calculs!$BX$49="","",INDEX(Calculs!$EU$4:$EU$503,Calculs!$BX$49)) | BD105: =IF(Calculs!$BX$49="","",IF(INDEX(Calculs!$EW$4:$EW$503,Calculs!$BX$49)>=2958465,"à planifier",INDEX(Calculs!$EW$4:$EW$503,Calculs!$BX$49)))
B106: =IF(Calculs!$BX$50="","",Calculs!$BW$50) | D106: =IF(Calculs!$BX$50="","",INDEX(Charge!$B:$B,Calculs!$BX$50+3)&"") | L106: =IF(Calculs!$BX$50="","",INDEX(Charge!$C:$C,Calculs!$BX$50+3)&"") | T106: =IF(Calculs!$BX$50="","",INDEX(Charge!$D:$D,Calculs!$BX$50+3)&"") | AB106: =IF(Calculs!$BX$50="","",INDEX(Charge!$A:$A,Calculs!$BX$50+3)&"") | AI106: =IF(Calculs!$BX$50="","",INDEX(Calculs!$ET$4:$ET$503,Calculs!$BX$50)) | AM106: =IF(Calculs!$BX$50="","",INDEX(Calculs!$EP$4:$EP$503,Calculs!$BX$50)) | AR106: =IF(Calculs!$BX$50="","",IF(Calculs!$AL$4=0,0,INDEX(Calculs!$EP$4:$EP$503,Calculs!$BX$50)/Calculs!$AL$4)) | AX106: =IF(Calculs!$BX$50="","",INDEX(Calculs!$EU$4:$EU$503,Calculs!$BX$50)) | BD106: =IF(Calculs!$BX$50="","",IF(INDEX(Calculs!$EW$4:$EW$503,Calculs!$BX$50)>=2958465,"à planifier",INDEX(Calculs!$EW$4:$EW$503,Calculs!$BX$50)))
B107: =IF(Calculs!$BX$51="","",Calculs!$BW$51) | D107: =IF(Calculs!$BX$51="","",INDEX(Charge!$B:$B,Calculs!$BX$51+3)&"") | L107: =IF(Calculs!$BX$51="","",INDEX(Charge!$C:$C,Calculs!$BX$51+3)&"") | T107: =IF(Calculs!$BX$51="","",INDEX(Charge!$D:$D,Calculs!$BX$51+3)&"") | AB107: =IF(Calculs!$BX$51="","",INDEX(Charge!$A:$A,Calculs!$BX$51+3)&"") | AI107: =IF(Calculs!$BX$51="","",INDEX(Calculs!$ET$4:$ET$503,Calculs!$BX$51)) | AM107: =IF(Calculs!$BX$51="","",INDEX(Calculs!$EP$4:$EP$503,Calculs!$BX$51)) | AR107: =IF(Calculs!$BX$51="","",IF(Calculs!$AL$4=0,0,INDEX(Calculs!$EP$4:$EP$503,Calculs!$BX$51)/Calculs!$AL$4)) | AX107: =IF(Calculs!$BX$51="","",INDEX(Calculs!$EU$4:$EU$503,Calculs!$BX$51)) | BD107: =IF(Calculs!$BX$51="","",IF(INDEX(Calculs!$EW$4:$EW$503,Calculs!$BX$51)>=2958465,"à planifier",INDEX(Calculs!$EW$4:$EW$503,Calculs!$BX$51)))
B108: =IF(Calculs!$BX$52="","",Calculs!$BW$52) | D108: =IF(Calculs!$BX$52="","",INDEX(Charge!$B:$B,Calculs!$BX$52+3)&"") | L108: =IF(Calculs!$BX$52="","",INDEX(Charge!$C:$C,Calculs!$BX$52+3)&"") | T108: =IF(Calculs!$BX$52="","",INDEX(Charge!$D:$D,Calculs!$BX$52+3)&"") | AB108: =IF(Calculs!$BX$52="","",INDEX(Charge!$A:$A,Calculs!$BX$52+3)&"") | AI108: =IF(Calculs!$BX$52="","",INDEX(Calculs!$ET$4:$ET$503,Calculs!$BX$52)) | AM108: =IF(Calculs!$BX$52="","",INDEX(Calculs!$EP$4:$EP$503,Calculs!$BX$52)) | AR108: =IF(Calculs!$BX$52="","",IF(Calculs!$AL$4=0,0,INDEX(Calculs!$EP$4:$EP$503,Calculs!$BX$52)/Calculs!$AL$4)) | AX108: =IF(Calculs!$BX$52="","",INDEX(Calculs!$EU$4:$EU$503,Calculs!$BX$52)) | BD108: =IF(Calculs!$BX$52="","",IF(INDEX(Calculs!$EW$4:$EW$503,Calculs!$BX$52)>=2958465,"à planifier",INDEX(Calculs!$EW$4:$EW$503,Calculs!$BX$52)))
B109: =IF(Calculs!$BX$53="","",Calculs!$BW$53) | D109: =IF(Calculs!$BX$53="","",INDEX(Charge!$B:$B,Calculs!$BX$53+3)&"") | L109: =IF(Calculs!$BX$53="","",INDEX(Charge!$C:$C,Calculs!$BX$53+3)&"") | T109: =IF(Calculs!$BX$53="","",INDEX(Charge!$D:$D,Calculs!$BX$53+3)&"") | AB109: =IF(Calculs!$BX$53="","",INDEX(Charge!$A:$A,Calculs!$BX$53+3)&"") | AI109: =IF(Calculs!$BX$53="","",INDEX(Calculs!$ET$4:$ET$503,Calculs!$BX$53)) | AM109: =IF(Calculs!$BX$53="","",INDEX(Calculs!$EP$4:$EP$503,Calculs!$BX$53)) | AR109: =IF(Calculs!$BX$53="","",IF(Calculs!$AL$4=0,0,INDEX(Calculs!$EP$4:$EP$503,Calculs!$BX$53)/Calculs!$AL$4)) | AX109: =IF(Calculs!$BX$53="","",INDEX(Calculs!$EU$4:$EU$503,Calculs!$BX$53)) | BD109: =IF(Calculs!$BX$53="","",IF(INDEX(Calculs!$EW$4:$EW$503,Calculs!$BX$53)>=2958465,"à planifier",INDEX(Calculs!$EW$4:$EW$503,Calculs!$BX$53)))
B110: =IF(Calculs!$BX$54="","",Calculs!$BW$54) | D110: =IF(Calculs!$BX$54="","",INDEX(Charge!$B:$B,Calculs!$BX$54+3)&"") | L110: =IF(Calculs!$BX$54="","",INDEX(Charge!$C:$C,Calculs!$BX$54+3)&"") | T110: =IF(Calculs!$BX$54="","",INDEX(Charge!$D:$D,Calculs!$BX$54+3)&"") | AB110: =IF(Calculs!$BX$54="","",INDEX(Charge!$A:$A,Calculs!$BX$54+3)&"") | AI110: =IF(Calculs!$BX$54="","",INDEX(Calculs!$ET$4:$ET$503,Calculs!$BX$54)) | AM110: =IF(Calculs!$BX$54="","",INDEX(Calculs!$EP$4:$EP$503,Calculs!$BX$54)) | AR110: =IF(Calculs!$BX$54="","",IF(Calculs!$AL$4=0,0,INDEX(Calculs!$EP$4:$EP$503,Calculs!$BX$54)/Calculs!$AL$4)) | AX110: =IF(Calculs!$BX$54="","",INDEX(Calculs!$EU$4:$EU$503,Calculs!$BX$54)) | BD110: =IF(Calculs!$BX$54="","",IF(INDEX(Calculs!$EW$4:$EW$503,Calculs!$BX$54)>=2958465,"à planifier",INDEX(Calculs!$EW$4:$EW$503,Calculs!$BX$54)))
B111: =IF(Calculs!$BX$55="","",Calculs!$BW$55) | D111: =IF(Calculs!$BX$55="","",INDEX(Charge!$B:$B,Calculs!$BX$55+3)&"") | L111: =IF(Calculs!$BX$55="","",INDEX(Charge!$C:$C,Calculs!$BX$55+3)&"") | T111: =IF(Calculs!$BX$55="","",INDEX(Charge!$D:$D,Calculs!$BX$55+3)&"") | AB111: =IF(Calculs!$BX$55="","",INDEX(Charge!$A:$A,Calculs!$BX$55+3)&"") | AI111: =IF(Calculs!$BX$55="","",INDEX(Calculs!$ET$4:$ET$503,Calculs!$BX$55)) | AM111: =IF(Calculs!$BX$55="","",INDEX(Calculs!$EP$4:$EP$503,Calculs!$BX$55)) | AR111: =IF(Calculs!$BX$55="","",IF(Calculs!$AL$4=0,0,INDEX(Calculs!$EP$4:$EP$503,Calculs!$BX$55)/Calculs!$AL$4)) | AX111: =IF(Calculs!$BX$55="","",INDEX(Calculs!$EU$4:$EU$503,Calculs!$BX$55)) | BD111: =IF(Calculs!$BX$55="","",IF(INDEX(Calculs!$EW$4:$EW$503,Calculs!$BX$55)>=2958465,"à planifier",INDEX(Calculs!$EW$4:$EW$503,Calculs!$BX$55)))
B112: =IF(Calculs!$BX$56="","",Calculs!$BW$56) | D112: =IF(Calculs!$BX$56="","",INDEX(Charge!$B:$B,Calculs!$BX$56+3)&"") | L112: =IF(Calculs!$BX$56="","",INDEX(Charge!$C:$C,Calculs!$BX$56+3)&"") | T112: =IF(Calculs!$BX$56="","",INDEX(Charge!$D:$D,Calculs!$BX$56+3)&"") | AB112: =IF(Calculs!$BX$56="","",INDEX(Charge!$A:$A,Calculs!$BX$56+3)&"") | AI112: =IF(Calculs!$BX$56="","",INDEX(Calculs!$ET$4:$ET$503,Calculs!$BX$56)) | AM112: =IF(Calculs!$BX$56="","",INDEX(Calculs!$EP$4:$EP$503,Calculs!$BX$56)) | AR112: =IF(Calculs!$BX$56="","",IF(Calculs!$AL$4=0,0,INDEX(Calculs!$EP$4:$EP$503,Calculs!$BX$56)/Calculs!$AL$4)) | AX112: =IF(Calculs!$BX$56="","",INDEX(Calculs!$EU$4:$EU$503,Calculs!$BX$56)) | BD112: =IF(Calculs!$BX$56="","",IF(INDEX(Calculs!$EW$4:$EW$503,Calculs!$BX$56)>=2958465,"à planifier",INDEX(Calculs!$EW$4:$EW$503,Calculs!$BX$56)))
B113: =IF(Calculs!$BX$57="","",Calculs!$BW$57) | D113: =IF(Calculs!$BX$57="","",INDEX(Charge!$B:$B,Calculs!$BX$57+3)&"") | L113: =IF(Calculs!$BX$57="","",INDEX(Charge!$C:$C,Calculs!$BX$57+3)&"") | T113: =IF(Calculs!$BX$57="","",INDEX(Charge!$D:$D,Calculs!$BX$57+3)&"") | AB113: =IF(Calculs!$BX$57="","",INDEX(Charge!$A:$A,Calculs!$BX$57+3)&"") | AI113: =IF(Calculs!$BX$57="","",INDEX(Calculs!$ET$4:$ET$503,Calculs!$BX$57)) | AM113: =IF(Calculs!$BX$57="","",INDEX(Calculs!$EP$4:$EP$503,Calculs!$BX$57)) | AR113: =IF(Calculs!$BX$57="","",IF(Calculs!$AL$4=0,0,INDEX(Calculs!$EP$4:$EP$503,Calculs!$BX$57)/Calculs!$AL$4)) | AX113: =IF(Calculs!$BX$57="","",INDEX(Calculs!$EU$4:$EU$503,Calculs!$BX$57)) | BD113: =IF(Calculs!$BX$57="","",IF(INDEX(Calculs!$EW$4:$EW$503,Calculs!$BX$57)>=2958465,"à planifier",INDEX(Calculs!$EW$4:$EW$503,Calculs!$BX$57)))
B114: =IF(Calculs!$BX$58="","",Calculs!$BW$58) | D114: =IF(Calculs!$BX$58="","",INDEX(Charge!$B:$B,Calculs!$BX$58+3)&"") | L114: =IF(Calculs!$BX$58="","",INDEX(Charge!$C:$C,Calculs!$BX$58+3)&"") | T114: =IF(Calculs!$BX$58="","",INDEX(Charge!$D:$D,Calculs!$BX$58+3)&"") | AB114: =IF(Calculs!$BX$58="","",INDEX(Charge!$A:$A,Calculs!$BX$58+3)&"") | AI114: =IF(Calculs!$BX$58="","",INDEX(Calculs!$ET$4:$ET$503,Calculs!$BX$58)) | AM114: =IF(Calculs!$BX$58="","",INDEX(Calculs!$EP$4:$EP$503,Calculs!$BX$58)) | AR114: =IF(Calculs!$BX$58="","",IF(Calculs!$AL$4=0,0,INDEX(Calculs!$EP$4:$EP$503,Calculs!$BX$58)/Calculs!$AL$4)) | AX114: =IF(Calculs!$BX$58="","",INDEX(Calculs!$EU$4:$EU$503,Calculs!$BX$58)) | BD114: =IF(Calculs!$BX$58="","",IF(INDEX(Calculs!$EW$4:$EW$503,Calculs!$BX$58)>=2958465,"à planifier",INDEX(Calculs!$EW$4:$EW$503,Calculs!$BX$58)))
B115: =IF(Calculs!$BX$59="","",Calculs!$BW$59) | D115: =IF(Calculs!$BX$59="","",INDEX(Charge!$B:$B,Calculs!$BX$59+3)&"") | L115: =IF(Calculs!$BX$59="","",INDEX(Charge!$C:$C,Calculs!$BX$59+3)&"") | T115: =IF(Calculs!$BX$59="","",INDEX(Charge!$D:$D,Calculs!$BX$59+3)&"") | AB115: =IF(Calculs!$BX$59="","",INDEX(Charge!$A:$A,Calculs!$BX$59+3)&"") | AI115: =IF(Calculs!$BX$59="","",INDEX(Calculs!$ET$4:$ET$503,Calculs!$BX$59)) | AM115: =IF(Calculs!$BX$59="","",INDEX(Calculs!$EP$4:$EP$503,Calculs!$BX$59)) | AR115: =IF(Calculs!$BX$59="","",IF(Calculs!$AL$4=0,0,INDEX(Calculs!$EP$4:$EP$503,Calculs!$BX$59)/Calculs!$AL$4)) | AX115: =IF(Calculs!$BX$59="","",INDEX(Calculs!$EU$4:$EU$503,Calculs!$BX$59)) | BD115: =IF(Calculs!$BX$59="","",IF(INDEX(Calculs!$EW$4:$EW$503,Calculs!$BX$59)>=2958465,"à planifier",INDEX(Calculs!$EW$4:$EW$503,Calculs!$BX$59)))
B116: =IF(Calculs!$BX$60="","",Calculs!$BW$60) | D116: =IF(Calculs!$BX$60="","",INDEX(Charge!$B:$B,Calculs!$BX$60+3)&"") | L116: =IF(Calculs!$BX$60="","",INDEX(Charge!$C:$C,Calculs!$BX$60+3)&"") | T116: =IF(Calculs!$BX$60="","",INDEX(Charge!$D:$D,Calculs!$BX$60+3)&"") | AB116: =IF(Calculs!$BX$60="","",INDEX(Charge!$A:$A,Calculs!$BX$60+3)&"") | AI116: =IF(Calculs!$BX$60="","",INDEX(Calculs!$ET$4:$ET$503,Calculs!$BX$60)) | AM116: =IF(Calculs!$BX$60="","",INDEX(Calculs!$EP$4:$EP$503,Calculs!$BX$60)) | AR116: =IF(Calculs!$BX$60="","",IF(Calculs!$AL$4=0,0,INDEX(Calculs!$EP$4:$EP$503,Calculs!$BX$60)/Calculs!$AL$4)) | AX116: =IF(Calculs!$BX$60="","",INDEX(Calculs!$EU$4:$EU$503,Calculs!$BX$60)) | BD116: =IF(Calculs!$BX$60="","",IF(INDEX(Calculs!$EW$4:$EW$503,Calculs!$BX$60)>=2958465,"à planifier",INDEX(Calculs!$EW$4:$EW$503,Calculs!$BX$60)))
B117: =IF(Calculs!$BX$61="","",Calculs!$BW$61) | D117: =IF(Calculs!$BX$61="","",INDEX(Charge!$B:$B,Calculs!$BX$61+3)&"") | L117: =IF(Calculs!$BX$61="","",INDEX(Charge!$C:$C,Calculs!$BX$61+3)&"") | T117: =IF(Calculs!$BX$61="","",INDEX(Charge!$D:$D,Calculs!$BX$61+3)&"") | AB117: =IF(Calculs!$BX$61="","",INDEX(Charge!$A:$A,Calculs!$BX$61+3)&"") | AI117: =IF(Calculs!$BX$61="","",INDEX(Calculs!$ET$4:$ET$503,Calculs!$BX$61)) | AM117: =IF(Calculs!$BX$61="","",INDEX(Calculs!$EP$4:$EP$503,Calculs!$BX$61)) | AR117: =IF(Calculs!$BX$61="","",IF(Calculs!$AL$4=0,0,INDEX(Calculs!$EP$4:$EP$503,Calculs!$BX$61)/Calculs!$AL$4)) | AX117: =IF(Calculs!$BX$61="","",INDEX(Calculs!$EU$4:$EU$503,Calculs!$BX$61)) | BD117: =IF(Calculs!$BX$61="","",IF(INDEX(Calculs!$EW$4:$EW$503,Calculs!$BX$61)>=2958465,"à planifier",INDEX(Calculs!$EW$4:$EW$503,Calculs!$BX$61)))
B118: =IF(Calculs!$BX$62="","",Calculs!$BW$62) | D118: =IF(Calculs!$BX$62="","",INDEX(Charge!$B:$B,Calculs!$BX$62+3)&"") | L118: =IF(Calculs!$BX$62="","",INDEX(Charge!$C:$C,Calculs!$BX$62+3)&"") | T118: =IF(Calculs!$BX$62="","",INDEX(Charge!$D:$D,Calculs!$BX$62+3)&"") | AB118: =IF(Calculs!$BX$62="","",INDEX(Charge!$A:$A,Calculs!$BX$62+3)&"") | AI118: =IF(Calculs!$BX$62="","",INDEX(Calculs!$ET$4:$ET$503,Calculs!$BX$62)) | AM118: =IF(Calculs!$BX$62="","",INDEX(Calculs!$EP$4:$EP$503,Calculs!$BX$62)) | AR118: =IF(Calculs!$BX$62="","",IF(Calculs!$AL$4=0,0,INDEX(Calculs!$EP$4:$EP$503,Calculs!$BX$62)/Calculs!$AL$4)) | AX118: =IF(Calculs!$BX$62="","",INDEX(Calculs!$EU$4:$EU$503,Calculs!$BX$62)) | BD118: =IF(Calculs!$BX$62="","",IF(INDEX(Calculs!$EW$4:$EW$503,Calculs!$BX$62)>=2958465,"à planifier",INDEX(Calculs!$EW$4:$EW$503,Calculs!$BX$62)))
B119: =IF(Calculs!$BX$63="","",Calculs!$BW$63) | D119: =IF(Calculs!$BX$63="","",INDEX(Charge!$B:$B,Calculs!$BX$63+3)&"") | L119: =IF(Calculs!$BX$63="","",INDEX(Charge!$C:$C,Calculs!$BX$63+3)&"") | T119: =IF(Calculs!$BX$63="","",INDEX(Charge!$D:$D,Calculs!$BX$63+3)&"") | AB119: =IF(Calculs!$BX$63="","",INDEX(Charge!$A:$A,Calculs!$BX$63+3)&"") | AI119: =IF(Calculs!$BX$63="","",INDEX(Calculs!$ET$4:$ET$503,Calculs!$BX$63)) | AM119: =IF(Calculs!$BX$63="","",INDEX(Calculs!$EP$4:$EP$503,Calculs!$BX$63)) | AR119: =IF(Calculs!$BX$63="","",IF(Calculs!$AL$4=0,0,INDEX(Calculs!$EP$4:$EP$503,Calculs!$BX$63)/Calculs!$AL$4)) | AX119: =IF(Calculs!$BX$63="","",INDEX(Calculs!$EU$4:$EU$503,Calculs!$BX$63)) | BD119: =IF(Calculs!$BX$63="","",IF(INDEX(Calculs!$EW$4:$EW$503,Calculs!$BX$63)>=2958465,"à planifier",INDEX(Calculs!$EW$4:$EW$503,Calculs!$BX$63)))
B120: =IF(Calculs!$BX$64="","",Calculs!$BW$64) | D120: =IF(Calculs!$BX$64="","",INDEX(Charge!$B:$B,Calculs!$BX$64+3)&"") | L120: =IF(Calculs!$BX$64="","",INDEX(Charge!$C:$C,Calculs!$BX$64+3)&"") | T120: =IF(Calculs!$BX$64="","",INDEX(Charge!$D:$D,Calculs!$BX$64+3)&"") | AB120: =IF(Calculs!$BX$64="","",INDEX(Charge!$A:$A,Calculs!$BX$64+3)&"") | AI120: =IF(Calculs!$BX$64="","",INDEX(Calculs!$ET$4:$ET$503,Calculs!$BX$64)) | AM120: =IF(Calculs!$BX$64="","",INDEX(Calculs!$EP$4:$EP$503,Calculs!$BX$64)) | AR120: =IF(Calculs!$BX$64="","",IF(Calculs!$AL$4=0,0,INDEX(Calculs!$EP$4:$EP$503,Calculs!$BX$64)/Calculs!$AL$4)) | AX120: =IF(Calculs!$BX$64="","",INDEX(Calculs!$EU$4:$EU$503,Calculs!$BX$64)) | BD120: =IF(Calculs!$BX$64="","",IF(INDEX(Calculs!$EW$4:$EW$503,Calculs!$BX$64)>=2958465,"à planifier",INDEX(Calculs!$EW$4:$EW$503,Calculs!$BX$64)))
B121: =IF(Calculs!$BX$65="","",Calculs!$BW$65) | D121: =IF(Calculs!$BX$65="","",INDEX(Charge!$B:$B,Calculs!$BX$65+3)&"") | L121: =IF(Calculs!$BX$65="","",INDEX(Charge!$C:$C,Calculs!$BX$65+3)&"") | T121: =IF(Calculs!$BX$65="","",INDEX(Charge!$D:$D,Calculs!$BX$65+3)&"") | AB121: =IF(Calculs!$BX$65="","",INDEX(Charge!$A:$A,Calculs!$BX$65+3)&"") | AI121: =IF(Calculs!$BX$65="","",INDEX(Calculs!$ET$4:$ET$503,Calculs!$BX$65)) | AM121: =IF(Calculs!$BX$65="","",INDEX(Calculs!$EP$4:$EP$503,Calculs!$BX$65)) | AR121: =IF(Calculs!$BX$65="","",IF(Calculs!$AL$4=0,0,INDEX(Calculs!$EP$4:$EP$503,Calculs!$BX$65)/Calculs!$AL$4)) | AX121: =IF(Calculs!$BX$65="","",INDEX(Calculs!$EU$4:$EU$503,Calculs!$BX$65)) | BD121: =IF(Calculs!$BX$65="","",IF(INDEX(Calculs!$EW$4:$EW$503,Calculs!$BX$65)>=2958465,"à planifier",INDEX(Calculs!$EW$4:$EW$503,Calculs!$BX$65)))
B122: =IF(Calculs!$BX$66="","",Calculs!$BW$66) | D122: =IF(Calculs!$BX$66="","",INDEX(Charge!$B:$B,Calculs!$BX$66+3)&"") | L122: =IF(Calculs!$BX$66="","",INDEX(Charge!$C:$C,Calculs!$BX$66+3)&"") | T122: =IF(Calculs!$BX$66="","",INDEX(Charge!$D:$D,Calculs!$BX$66+3)&"") | AB122: =IF(Calculs!$BX$66="","",INDEX(Charge!$A:$A,Calculs!$BX$66+3)&"") | AI122: =IF(Calculs!$BX$66="","",INDEX(Calculs!$ET$4:$ET$503,Calculs!$BX$66)) | AM122: =IF(Calculs!$BX$66="","",INDEX(Calculs!$EP$4:$EP$503,Calculs!$BX$66)) | AR122: =IF(Calculs!$BX$66="","",IF(Calculs!$AL$4=0,0,INDEX(Calculs!$EP$4:$EP$503,Calculs!$BX$66)/Calculs!$AL$4)) | AX122: =IF(Calculs!$BX$66="","",INDEX(Calculs!$EU$4:$EU$503,Calculs!$BX$66)) | BD122: =IF(Calculs!$BX$66="","",IF(INDEX(Calculs!$EW$4:$EW$503,Calculs!$BX$66)>=2958465,"à planifier",INDEX(Calculs!$EW$4:$EW$503,Calculs!$BX$66)))
B123: =IF(Calculs!$BX$67="","",Calculs!$BW$67) | D123: =IF(Calculs!$BX$67="","",INDEX(Charge!$B:$B,Calculs!$BX$67+3)&"") | L123: =IF(Calculs!$BX$67="","",INDEX(Charge!$C:$C,Calculs!$BX$67+3)&"") | T123: =IF(Calculs!$BX$67="","",INDEX(Charge!$D:$D,Calculs!$BX$67+3)&"") | AB123: =IF(Calculs!$BX$67="","",INDEX(Charge!$A:$A,Calculs!$BX$67+3)&"") | AI123: =IF(Calculs!$BX$67="","",INDEX(Calculs!$ET$4:$ET$503,Calculs!$BX$67)) | AM123: =IF(Calculs!$BX$67="","",INDEX(Calculs!$EP$4:$EP$503,Calculs!$BX$67)) | AR123: =IF(Calculs!$BX$67="","",IF(Calculs!$AL$4=0,0,INDEX(Calculs!$EP$4:$EP$503,Calculs!$BX$67)/Calculs!$AL$4)) | AX123: =IF(Calculs!$BX$67="","",INDEX(Calculs!$EU$4:$EU$503,Calculs!$BX$67)) | BD123: =IF(Calculs!$BX$67="","",IF(INDEX(Calculs!$EW$4:$EW$503,Calculs!$BX$67)>=2958465,"à planifier",INDEX(Calculs!$EW$4:$EW$503,Calculs!$BX$67)))
...

Sheet Dessinateurs
C2: CHARGE PAR RESSOURCE (DESSINATEURS ET EXTERNES) | AT2: =TODAY() -> 46313
C3: Charge fixe hors projet + heures de ses lignes dans l'onglet Charge, comparées à la capacité mensuelle de la personne.
B5: Ressource | G5: Lucas Garnier | T5: Capacité | X5: =Calculs!$CD$6 -> 120 | AC5: Charge fixe | AH5: =Calculs!$CD$7 -> 20 | AL5: Dispo. projets | AS5: =Calculs!$CD$8 -> 100 | AX5: =Calculs!$CD$22 -> 46266
G6: =IF(Calculs!$CD$25="Hors liste","Absent des listes Data : réglages par défaut",IF(Calculs!$CD$25="Externe","Ressource externe (Data, colonne H)","Dessinateur interne (Data, colonne E)")) -> Dessinateur interne (Data, colonne E) | T6: par mois · valeurs propres à la personne (Data, colonnes F-G ou I-J) ou valeurs par défaut du Dashboard | AX6: ="Périmètre : "&Calculs!$CD$21 -> Périmètre : Projets en cours
B8: =IF(Calculs!$CD$4="","SYNTHÈSE — choisir une ressource","SYNTHÈSE — "&UPPER(Calculs!$CD$4)&IF(Calculs!$CD$25="Externe"," (RESSOURCE EXTERNE)","")) -> SYNTHÈSE — LUCAS GARNIER | AF8: =IF(Calculs!$CD$27>0,"Attention : "&Calculs!$CD$27&" ligne(s) de Charge ont un dessinateur ET une ressource externe (en rouge dans Charge)","")
C11: CAPACITÉ MENSUELLE | O11: CHARGE PROJETS AFFECTÉE | AA11: MOIS LE PLUS CHARGÉ | AM11: MOIS EN SURCHARGE | AY11: OCCUPATION MOYENNE
C12: =Calculs!$CD$6 -> 120 | O12: =Calculs!$CD$9 -> 420 | AA12: =IF(OR(Calculs!$CD$4="",Calculs!$CD$11=0),"—",Calculs!$CD$14) -> 46327 | AM12: =Calculs!$CD$16 -> 1 | AY12: =Calculs!$CD$19 -> 0.45833333
C13: =Calculs!$CD$7 -> 20 | O13: =Calculs!$CD$10 -> 2 | AA13: =Calculs!$CD$12 -> 121.9697 | AM13: =Calculs!$CD$17 -> 2 | AY13: =Calculs!$CD$18 -> 782
C14: =IF(AND(Calculs!$CD$4<>"",Calculs!$CD$7>=Calculs!$CD$6),"Attention : charge fixe ≥ capacité",Calculs!$CD$8) -> 100 | O14: =Calculs!$CD$11 -> 420 | AA14: =Calculs!$CD$15 -> 1.0166667 | AM14: =IF(Calculs!$CD$16=0,"Aucun dépassement prévu",Calculs!$CD$20) -> 46327 | AY14: sur les 12 mois affichés
B17: CHARGE MENSUELLE
C20: =IF(Calculs!$CD$4="","CHARGE MENSUELLE (HEURES)","CHARGE MENSUELLE DE "&UPPER(Calculs!$CD$4)&" (HEURES)") -> CHARGE MENSUELLE DE LUCAS GARNIER (HEURES)
D21: Charge fixe hors projet | O21: Charge projets | Z21: Dépassement de capacité | AM21: Capacité mensuelle
C39: Heures par mois | L39: =Calculs!CG4 -> 46266 | P39: =Calculs!CG5 -> 46296 | T39: =Calculs!CG6 -> 46327 | X39: =Calculs!CG7 -> 46357 | AB39: =Calculs!CG8 -> 46388 | AF39: =Calculs!CG9 -> 46419 | AJ39: =Calculs!CG10 -> 46447 | AN39: =Calculs!CG11 -> 46478 | AR39: =Calculs!CG12 -> 46508 | AV39: =Calculs!CG13 -> 46539 | AZ39: =Calculs!CG14 -> 46569 | BD39: =Calculs!CG15 -> 46600
C40: Charge fixe hors projet | L40: =Calculs!CH4 -> 20 | P40: =Calculs!CH5 -> 20 | T40: =Calculs!CH6 -> 20 | X40: =Calculs!CH7 -> 20 | AB40: =Calculs!CH8 -> 20 | AF40: =Calculs!CH9 -> 20 | AJ40: =Calculs!CH10 -> 20 | AN40: =Calculs!CH11 -> 20 | AR40: =Calculs!CH12 -> 20 | AV40: =Calculs!CH13 -> 20 | AZ40: =Calculs!CH14 -> 20 | BD40: =Calculs!CH15 -> 20
C41: Charge projets | L41: =Calculs!CI4 -> 28.363636 | P41: =Calculs!CI5 -> 48 | T41: =Calculs!CI6 -> 101.9697 | X41: =Calculs!CI7 -> 63.888889 | AB41: =Calculs!CI8 -> 58.333333 | AF41: =Calculs!CI9 -> 55.555556 | AJ41: =Calculs!CI10 -> 63.888889 | AN41: =Calculs!CI11 -> 0 | AR41: =Calculs!CI12 -> 0 | AV41: =Calculs!CI13 -> 0 | AZ41: =Calculs!CI14 -> 0 | BD41: =Calculs!CI15 -> 0
C42: Charge totale | L42: =Calculs!CJ4 -> 48.363636 | P42: =Calculs!CJ5 -> 68 | T42: =Calculs!CJ6 -> 121.9697 | X42: =Calculs!CJ7 -> 83.888889 | AB42: =Calculs!CJ8 -> 78.333333 | AF42: =Calculs!CJ9 -> 75.555556 | AJ42: =Calculs!CJ10 -> 83.888889 | AN42: =Calculs!CJ11 -> 20 | AR42: =Calculs!CJ12 -> 20 | AV42: =Calculs!CJ13 -> 20 | AZ42: =Calculs!CJ14 -> 20 | BD42: =Calculs!CJ15 -> 20
C43: Capacité | L43: =Calculs!CK4 -> 120 | P43: =Calculs!CK5 -> 120 | T43: =Calculs!CK6 -> 120 | X43: =Calculs!CK7 -> 120 | AB43: =Calculs!CK8 -> 120 | AF43: =Calculs!CK9 -> 120 | AJ43: =Calculs!CK10 -> 120 | AN43: =Calculs!CK11 -> 120 | AR43: =Calculs!CK12 -> 120 | AV43: =Calculs!CK13 -> 120 | AZ43: =Calculs!CK14 -> 120 | BD43: =Calculs!CK15 -> 120
C44: Marge (+) / dépassement (−) | L44: =Calculs!CN4 -> 72 | P44: =Calculs!CN5 -> 52 | T44: =Calculs!CN6 -> -2 | X44: =Calculs!CN7 -> 36 | AB44: =Calculs!CN8 -> 42 | AF44: =Calculs!CN9 -> 44 | AJ44: =Calculs!CN10 -> 36 | AN44: =Calculs!CN11 -> 100 | AR44: =Calculs!CN12 -> 100 | AV44: =Calculs!CN13 -> 100 | AZ44: =Calculs!CN14 -> 100 | BD44: =Calculs!CN15 -> 100
C45: Occupation | L45: =Calculs!CO4 -> 0.4 | P45: =Calculs!CO5 -> 0.56666667 | T45: =Calculs!CO6 -> 1.0166667 | X45: =Calculs!CO7 -> 0.7 | AB45: =Calculs!CO8 -> 0.65 | AF45: =Calculs!CO9 -> 0.63333333 | AJ45: =Calculs!CO10 -> 0.7 | AN45: =Calculs!CO11 -> 0.16666667 | AR45: =Calculs!CO12 -> 0.16666667 | AV45: =Calculs!CO13 -> 0.16666667 | AZ45: =Calculs!CO14 -> 0.16666667 | BD45: =Calculs!CO15 -> 0.16666667
B48: =IF(Calculs!$CD$4="","AFFAIRES DE LA RESSOURCE","AFFAIRES DE "&UPPER(Calculs!$CD$4)&" (par charge décroissante)") -> AFFAIRES DE LUCAS GARNIER (par charge décroissante)
B50: N° | D50: Projet | M50: Sous-projet | V50: Produit | AE50: Chef de projet | AL50: Charge (h) | AQ50: Heures sur la période | AW50: Début planifié | BA50: Date de besoin | BE50: Avancement
B51: =IF(Calculs!$DY$4="","",Calculs!DX4) -> 1 | D51: =IF(Calculs!$DY$4="","",Calculs!DZ4) -> ATLAS | M51: =IF(Calculs!$DY$4="","",Calculs!EA4) -> Lot 1 – Structure | V51: =IF(Calculs!$DY$4="","",Calculs!EB4) -> Châssis principal | AE51: =IF(Calculs!$DY$4="","",Calculs!EC4) -> Julie Martin | AL51: =IF(Calculs!$DY$4="","",Calculs!ED4) -> 300 | AQ51: =IF(Calculs!$DY$4="","",Calculs!EE4) -> 300 | AW51: =IF(Calculs!$DY$4="","",Calculs!EF4) -> 46328 | BA51: =IF(Calculs!$DY$4="","",Calculs!EG4) -> 46477 | BE51: =IF(Calculs!$DY$4="","",Calculs!EH4) -> 0.15
B52: =IF(Calculs!$DY$5="","",Calculs!DX5) -> 2 | D52: =IF(Calculs!$DY$5="","",Calculs!DZ5) -> ORION | M52: =IF(Calculs!$DY$5="","",Calculs!EA5) -> Tranche 1 | V52: =IF(Calculs!$DY$5="","",Calculs!EB5) -> Support moteur | AE52: =IF(Calculs!$DY$5="","",Calculs!EC5) -> Nicolas Moreau | AL52: =IF(Calculs!$DY$5="","",Calculs!ED5) -> 120 | AQ52: =IF(Calculs!$DY$5="","",Calculs!EE5) -> 120 | AW52: =IF(Calculs!$DY$5="","",Calculs!EF5) -> 46279 | BA52: =IF(Calculs!$DY$5="","",Calculs!EG5) -> 46353 | BE52: =IF(Calculs!$DY$5="","",Calculs!EH5) -> 0.8
B53: =IF(Calculs!$DY$6="","",Calculs!DX6) | D53: =IF(Calculs!$DY$6="","",Calculs!DZ6) | M53: =IF(Calculs!$DY$6="","",Calculs!EA6) | V53: =IF(Calculs!$DY$6="","",Calculs!EB6) | AE53: =IF(Calculs!$DY$6="","",Calculs!EC6) | AL53: =IF(Calculs!$DY$6="","",Calculs!ED6) | AQ53: =IF(Calculs!$DY$6="","",Calculs!EE6) | AW53: =IF(Calculs!$DY$6="","",Calculs!EF6) | BA53: =IF(Calculs!$DY$6="","",Calculs!EG6) | BE53: =IF(Calculs!$DY$6="","",Calculs!EH6)
B54: =IF(Calculs!$DY$7="","",Calculs!DX7) | D54: =IF(Calculs!$DY$7="","",Calculs!DZ7) | M54: =IF(Calculs!$DY$7="","",Calculs!EA7) | V54: =IF(Calculs!$DY$7="","",Calculs!EB7) | AE54: =IF(Calculs!$DY$7="","",Calculs!EC7) | AL54: =IF(Calculs!$DY$7="","",Calculs!ED7) | AQ54: =IF(Calculs!$DY$7="","",Calculs!EE7) | AW54: =IF(Calculs!$DY$7="","",Calculs!EF7) | BA54: =IF(Calculs!$DY$7="","",Calculs!EG7) | BE54: =IF(Calculs!$DY$7="","",Calculs!EH7)
B55: =IF(Calculs!$DY$8="","",Calculs!DX8) | D55: =IF(Calculs!$DY$8="","",Calculs!DZ8) | M55: =IF(Calculs!$DY$8="","",Calculs!EA8) | V55: =IF(Calculs!$DY$8="","",Calculs!EB8) | AE55: =IF(Calculs!$DY$8="","",Calculs!EC8) | AL55: =IF(Calculs!$DY$8="","",Calculs!ED8) | AQ55: =IF(Calculs!$DY$8="","",Calculs!EE8) | AW55: =IF(Calculs!$DY$8="","",Calculs!EF8) | BA55: =IF(Calculs!$DY$8="","",Calculs!EG8) | BE55: =IF(Calculs!$DY$8="","",Calculs!EH8)
B56: =IF(Calculs!$DY$9="","",Calculs!DX9) | D56: =IF(Calculs!$DY$9="","",Calculs!DZ9) | M56: =IF(Calculs!$DY$9="","",Calculs!EA9) | V56: =IF(Calculs!$DY$9="","",Calculs!EB9) | AE56: =IF(Calculs!$DY$9="","",Calculs!EC9) | AL56: =IF(Calculs!$DY$9="","",Calculs!ED9) | AQ56: =IF(Calculs!$DY$9="","",Calculs!EE9) | AW56: =IF(Calculs!$DY$9="","",Calculs!EF9) | BA56: =IF(Calculs!$DY$9="","",Calculs!EG9) | BE56: =IF(Calculs!$DY$9="","",Calculs!EH9)
B57: =IF(Calculs!$DY$10="","",Calculs!DX10) | D57: =IF(Calculs!$DY$10="","",Calculs!DZ10) | M57: =IF(Calculs!$DY$10="","",Calculs!EA10) | V57: =IF(Calculs!$DY$10="","",Calculs!EB10) | AE57: =IF(Calculs!$DY$10="","",Calculs!EC10) | AL57: =IF(Calculs!$DY$10="","",Calculs!ED10) | AQ57: =IF(Calculs!$DY$10="","",Calculs!EE10) | AW57: =IF(Calculs!$DY$10="","",Calculs!EF10) | BA57: =IF(Calculs!$DY$10="","",Calculs!EG10) | BE57: =IF(Calculs!$DY$10="","",Calculs!EH10)
B58: =IF(Calculs!$DY$11="","",Calculs!DX11) | D58: =IF(Calculs!$DY$11="","",Calculs!DZ11) | M58: =IF(Calculs!$DY$11="","",Calculs!EA11) | V58: =IF(Calculs!$DY$11="","",Calculs!EB11) | AE58: =IF(Calculs!$DY$11="","",Calculs!EC11) | AL58: =IF(Calculs!$DY$11="","",Calculs!ED11) | AQ58: =IF(Calculs!$DY$11="","",Calculs!EE11) | AW58: =IF(Calculs!$DY$11="","",Calculs!EF11) | BA58: =IF(Calculs!$DY$11="","",Calculs!EG11) | BE58: =IF(Calculs!$DY$11="","",Calculs!EH11)
B59: =IF(Calculs!$DY$12="","",Calculs!DX12) | D59: =IF(Calculs!$DY$12="","",Calculs!DZ12) | M59: =IF(Calculs!$DY$12="","",Calculs!EA12) | V59: =IF(Calculs!$DY$12="","",Calculs!EB12) | AE59: =IF(Calculs!$DY$12="","",Calculs!EC12) | AL59: =IF(Calculs!$DY$12="","",Calculs!ED12) | AQ59: =IF(Calculs!$DY$12="","",Calculs!EE12) | AW59: =IF(Calculs!$DY$12="","",Calculs!EF12) | BA59: =IF(Calculs!$DY$12="","",Calculs!EG12) | BE59: =IF(Calculs!$DY$12="","",Calculs!EH12)
B60: =IF(Calculs!$DY$13="","",Calculs!DX13) | D60: =IF(Calculs!$DY$13="","",Calculs!DZ13) | M60: =IF(Calculs!$DY$13="","",Calculs!EA13) | V60: =IF(Calculs!$DY$13="","",Calculs!EB13) | AE60: =IF(Calculs!$DY$13="","",Calculs!EC13) | AL60: =IF(Calculs!$DY$13="","",Calculs!ED13) | AQ60: =IF(Calculs!$DY$13="","",Calculs!EE13) | AW60: =IF(Calculs!$DY$13="","",Calculs!EF13) | BA60: =IF(Calculs!$DY$13="","",Calculs!EG13) | BE60: =IF(Calculs!$DY$13="","",Calculs!EH13)
B61: =IF(Calculs!$DY$14="","",Calculs!DX14) | D61: =IF(Calculs!$DY$14="","",Calculs!DZ14) | M61: =IF(Calculs!$DY$14="","",Calculs!EA14) | V61: =IF(Calculs!$DY$14="","",Calculs!EB14) | AE61: =IF(Calculs!$DY$14="","",Calculs!EC14) | AL61: =IF(Calculs!$DY$14="","",Calculs!ED14) | AQ61: =IF(Calculs!$DY$14="","",Calculs!EE14) | AW61: =IF(Calculs!$DY$14="","",Calculs!EF14) | BA61: =IF(Calculs!$DY$14="","",Calculs!EG14) | BE61: =IF(Calculs!$DY$14="","",Calculs!EH14)
B62: =IF(Calculs!$DY$15="","",Calculs!DX15) | D62: =IF(Calculs!$DY$15="","",Calculs!DZ15) | M62: =IF(Calculs!$DY$15="","",Calculs!EA15) | V62: =IF(Calculs!$DY$15="","",Calculs!EB15) | AE62: =IF(Calculs!$DY$15="","",Calculs!EC15) | AL62: =IF(Calculs!$DY$15="","",Calculs!ED15) | AQ62: =IF(Calculs!$DY$15="","",Calculs!EE15) | AW62: =IF(Calculs!$DY$15="","",Calculs!EF15) | BA62: =IF(Calculs!$DY$15="","",Calculs!EG15) | BE62: =IF(Calculs!$DY$15="","",Calculs!EH15)
B63: =IF(Calculs!$DY$16="","",Calculs!DX16) | D63: =IF(Calculs!$DY$16="","",Calculs!DZ16) | M63: =IF(Calculs!$DY$16="","",Calculs!EA16) | V63: =IF(Calculs!$DY$16="","",Calculs!EB16) | AE63: =IF(Calculs!$DY$16="","",Calculs!EC16) | AL63: =IF(Calculs!$DY$16="","",Calculs!ED16) | AQ63: =IF(Calculs!$DY$16="","",Calculs!EE16) | AW63: =IF(Calculs!$DY$16="","",Calculs!EF16) | BA63: =IF(Calculs!$DY$16="","",Calculs!EG16) | BE63: =IF(Calculs!$DY$16="","",Calculs!EH16)
B64: =IF(Calculs!$DY$17="","",Calculs!DX17) | D64: =IF(Calculs!$DY$17="","",Calculs!DZ17) | M64: =IF(Calculs!$DY$17="","",Calculs!EA17) | V64: =IF(Calculs!$DY$17="","",Calculs!EB17) | AE64: =IF(Calculs!$DY$17="","",Calculs!EC17) | AL64: =IF(Calculs!$DY$17="","",Calculs!ED17) | AQ64: =IF(Calculs!$DY$17="","",Calculs!EE17) | AW64: =IF(Calculs!$DY$17="","",Calculs!EF17) | BA64: =IF(Calculs!$DY$17="","",Calculs!EG17) | BE64: =IF(Calculs!$DY$17="","",Calculs!EH17)
B65: =IF(Calculs!$DY$18="","",Calculs!DX18) | D65: =IF(Calculs!$DY$18="","",Calculs!DZ18) | M65: =IF(Calculs!$DY$18="","",Calculs!EA18) | V65: =IF(Calculs!$DY$18="","",Calculs!EB18) | AE65: =IF(Calculs!$DY$18="","",Calculs!EC18) | AL65: =IF(Calculs!$DY$18="","",Calculs!ED18) | AQ65: =IF(Calculs!$DY$18="","",Calculs!EE18) | AW65: =IF(Calculs!$DY$18="","",Calculs!EF18) | BA65: =IF(Calculs!$DY$18="","",Calculs!EG18) | BE65: =IF(Calculs!$DY$18="","",Calculs!EH18)
B66: =IF(Calculs!$CD$28>15,"Seules les 15 plus grosses lignes sont listées sur "&Calculs!$CD$28&".",IF(AND(Calculs!$CD$4<>"",Calculs!$CD$28=0),"Aucune affaire affectée à cette ressource dans le périmètre.",""))
B68: OCCUPATION DE L'ÉQUIPE (charge fixe + projets, en % de la capacité)
C71: Vert : moins de 90 % · Orange : de 90 à 100 % · Rouge : au-delà de 100 % (surcharge) · les 16 premières ressources des listes Data (dessinateurs puis externes)
C72: Ressource | L72: =Calculs!CW3 -> 46266 | P72: =Calculs!CX3 -> 46296 | T72: =Calculs!CY3 -> 46327 | X72: =Calculs!CZ3 -> 46357 | AB72: =Calculs!DA3 -> 46388 | AF72: =Calculs!DB3 -> 46419 | AJ72: =Calculs!DC3 -> 46447 | AN72: =Calculs!DD3 -> 46478 | AR72: =Calculs!DE3 -> 46508 | AV72: =Calculs!DF3 -> 46539 | AZ72: =Calculs!DG3 -> 46569 | BD72: =Calculs!DH3 -> 46600
C73: =Calculs!CT4 -> Lucas Garnier | J73: =IF(Calculs!CT4="","",IF(Calculs!FB4="Externe","ext.","")) | L73: =Calculs!DI4 -> 0.4 | P73: =Calculs!DJ4 -> 0.56666667 | T73: =Calculs!DK4 -> 1.0166667 | X73: =Calculs!DL4 -> 0.7 | AB73: =Calculs!DM4 -> 0.65 | AF73: =Calculs!DN4 -> 0.63333333 | AJ73: =Calculs!DO4 -> 0.7 | AN73: =Calculs!DP4 -> 0.16666667 | AR73: =Calculs!DQ4 -> 0.16666667 | AV73: =Calculs!DR4 -> 0.16666667 | AZ73: =Calculs!DS4 -> 0.16666667 | BD73: =Calculs!DT4 -> 0.16666667
C74: =Calculs!CT5 -> Emma Faure | J74: =IF(Calculs!CT5="","",IF(Calculs!FB5="Externe","ext.","")) | L74: =Calculs!DI5 -> 0.16666667 | P74: =Calculs!DJ5 -> 0.16666667 | T74: =Calculs!DK5 -> 0.16666667 | X74: =Calculs!DL5 -> 0.65 | AB74: =Calculs!DM5 -> 0.93333333 | AF74: =Calculs!DN5 -> 1.0166667 | AJ74: =Calculs!DO5 -> 1.225 | AN74: =Calculs!DP5 -> 1.175 | AR74: =Calculs!DQ5 -> 1.0916667 | AV74: =Calculs!DR5 -> 0.425 | AZ74: =Calculs!DS5 -> 0.425 | BD74: =Calculs!DT5 -> 0.4
C75: =Calculs!CT6 -> Hugo Mercier | J75: =IF(Calculs!CT6="","",IF(Calculs!FB6="Externe","ext.","")) | L75: =Calculs!DI6 -> 0.16666667 | P75: =Calculs!DJ6 -> 0.54166667 | T75: =Calculs!DK6 -> 0.69166667 | X75: =Calculs!DL6 -> 0.51666667 | AB75: =Calculs!DM6 -> 0.16666667 | AF75: =Calculs!DN6 -> 0.26666667 | AJ75: =Calculs!DO6 -> 0.625 | AN75: =Calculs!DP6 -> 0.775 | AR75: =Calculs!DQ6 -> 0.74166667 | AV75: =Calculs!DR6 -> 0.775 | AZ75: =Calculs!DS6 -> 0.55 | BD75: =Calculs!DT6 -> 0.55
C76: =Calculs!CT7 -> Léa Chevalier | J76: =IF(Calculs!CT7="","",IF(Calculs!FB7="Externe","ext.","")) | L76: =Calculs!DI7 -> 0.20833333 | P76: =Calculs!DJ7 -> 0.96875 | T76: =Calculs!DK7 -> 1.40625 | X76: =Calculs!DL7 -> 1.40625 | AB76: =Calculs!DM7 -> 1.0104167 | AF76: =Calculs!DN7 -> 0.91666667 | AJ76: =Calculs!DO7 -> 1.0208333 | AN76: =Calculs!DP7 -> 0.97916667 | AR76: =Calculs!DQ7 -> 0.20833333 | AV76: =Calculs!DR7 -> 0.20833333 | AZ76: =Calculs!DS7 -> 0.20833333 | BD76: =Calculs!DT7 -> 0.20833333
C77: =Calculs!CT8 -> Antoine Blanc | J77: =IF(Calculs!CT8="","",IF(Calculs!FB8="Externe","ext.","")) | L77: =Calculs!DI8 -> 0.16666667 | P77: =Calculs!DJ8 -> 0.16666667 | T77: =Calculs!DK8 -> 0.275 | X77: =Calculs!DL8 -> 0.575 | AB77: =Calculs!DM8 -> 0.35833333 | AF77: =Calculs!DN8 -> 0.56666667 | AJ77: =Calculs!DO8 -> 0.94166667 | AN77: =Calculs!DP8 -> 0.61666667 | AR77: =Calculs!DQ8 -> 0.59166667 | AV77: =Calculs!DR8 -> 0.61666667 | AZ77: =Calculs!DS8 -> 0.16666667 | BD77: =Calculs!DT8 -> 0.16666667
C78: =Calculs!CT9 -> Paul Girard | J78: =IF(Calculs!CT9="","",IF(Calculs!FB9="Externe","ext.","")) -> ext. | L78: =Calculs!DI9 -> 0.16666667 | P78: =Calculs!DJ9 -> 0.16666667 | T78: =Calculs!DK9 -> 0.35833333 | X78: =Calculs!DL9 -> 0.61666667 | AB78: =Calculs!DM9 -> 0.58333333 | AF78: =Calculs!DN9 -> 0.55833333 | AJ78: =Calculs!DO9 -> 0.38333333 | AN78: =Calculs!DP9 -> 0.16666667 | AR78: =Calculs!DQ9 -> 0.16666667 | AV78: =Calculs!DR9 -> 0.16666667 | AZ78: =Calculs!DS9 -> 0.16666667 | BD78: =Calculs!DT9 -> 0.16666667
C79: =Calculs!CT10 -> Inès Morel | J79: =IF(Calculs!CT10="","",IF(Calculs!FB10="Externe","ext.","")) -> ext. | L79: =Calculs!DI10 -> 0.16666667 | P79: =Calculs!DJ10 -> 0.16666667 | T79: =Calculs!DK10 -> 0.16666667 | X79: =Calculs!DL10 -> 0.16666667 | AB79: =Calculs!DM10 -> 0.16666667 | AF79: =Calculs!DN10 -> 0.16666667 | AJ79: =Calculs!DO10 -> 0.16666667 | AN79: =Calculs!DP10 -> 0.51666667 | AR79: =Calculs!DQ10 -> 0.7 | AV79: =Calculs!DR10 -> 0.725 | AZ79: =Calculs!DS10 -> 0.725 | BD79: =Calculs!DT10 -> 0.325
C80: =Calculs!CT11 -> Karim Haddad | J80: =IF(Calculs!CT11="","",IF(Calculs!FB11="Externe","ext.","")) -> ext. | L80: =Calculs!DI11 -> 0.16666667 | P80: =Calculs!DJ11 -> 0.16666667 | T80: =Calculs!DK11 -> 0.16666667 | X80: =Calculs!DL11 -> 0.16666667 | AB80: =Calculs!DM11 -> 0.35 | AF80: =Calculs!DN11 -> 0.53333333 | AJ80: =Calculs!DO11 -> 0.5 | AN80: =Calculs!DP11 -> 0.4 | AR80: =Calculs!DQ11 -> 0.38333333 | AV80: =Calculs!DR11 -> 0.4 | AZ80: =Calculs!DS11 -> 0.4 | BD80: =Calculs!DT11 -> 0.4
C81: =Calculs!CT12 | J81: =IF(Calculs!CT12="","",IF(Calculs!FB12="Externe","ext.","")) | L81: =Calculs!DI12 | P81: =Calculs!DJ12 | T81: =Calculs!DK12 | X81: =Calculs!DL12 | AB81: =Calculs!DM12 | AF81: =Calculs!DN12 | AJ81: =Calculs!DO12 | AN81: =Calculs!DP12 | AR81: =Calculs!DQ12 | AV81: =Calculs!DR12 | AZ81: =Calculs!DS12 | BD81: =Calculs!DT12
C82: =Calculs!CT13 | J82: =IF(Calculs!CT13="","",IF(Calculs!FB13="Externe","ext.","")) | L82: =Calculs!DI13 | P82: =Calculs!DJ13 | T82: =Calculs!DK13 | X82: =Calculs!DL13 | AB82: =Calculs!DM13 | AF82: =Calculs!DN13 | AJ82: =Calculs!DO13 | AN82: =Calculs!DP13 | AR82: =Calculs!DQ13 | AV82: =Calculs!DR13 | AZ82: =Calculs!DS13 | BD82: =Calculs!DT13
C83: =Calculs!CT14 | J83: =IF(Calculs!CT14="","",IF(Calculs!FB14="Externe","ext.","")) | L83: =Calculs!DI14 | P83: =Calculs!DJ14 | T83: =Calculs!DK14 | X83: =Calculs!DL14 | AB83: =Calculs!DM14 | AF83: =Calculs!DN14 | AJ83: =Calculs!DO14 | AN83: =Calculs!DP14 | AR83: =Calculs!DQ14 | AV83: =Calculs!DR14 | AZ83: =Calculs!DS14 | BD83: =Calculs!DT14
C84: =Calculs!CT15 | J84: =IF(Calculs!CT15="","",IF(Calculs!FB15="Externe","ext.","")) | L84: =Calculs!DI15 | P84: =Calculs!DJ15 | T84: =Calculs!DK15 | X84: =Calculs!DL15 | AB84: =Calculs!DM15 | AF84: =Calculs!DN15 | AJ84: =Calculs!DO15 | AN84: =Calculs!DP15 | AR84: =Calculs!DQ15 | AV84: =Calculs!DR15 | AZ84: =Calculs!DS15 | BD84: =Calculs!DT15
... C88: =Calculs!CT19 | J88: =IF(Calculs!CT19="","",IF(Calculs!FB19="Externe","ext.","")) | L88: =Calculs!DI19 | P88: =Calculs!DJ19 | T88: =Calculs!DK19 | X88: =Calculs!DL19 | AB88: =Calculs!DM19 | AF88: =Calculs!DN19 | AJ88: =Calculs!DO19 | AN88: =Calculs!DP19 | AR88: =Calculs!DQ19 | AV88: =Calculs!DR19 | AZ88: =Calculs!DS19 | BD88: =Calculs!DT19
C89: Charge non affectée (h) | L89: =Calculs!CW20 -> 0 | P89: =Calculs!CX20 -> 0 | T89: =Calculs!CY20 -> 0 | X89: =Calculs!CZ20 -> 0 | AB89: =Calculs!DA20 -> 0 | AF89: =Calculs!DB20 -> 0 | AJ89: =Calculs!DC20 -> 25.555556 | AN89: =Calculs!DD20 -> 24.444444 | AR89: =Calculs!DE20 -> 0 | AV89: =Calculs!DF20 -> 0 | AZ89: =Calculs!DG20 -> 0 | BD89: =Calculs!DH20 -> 0
C90: Autres ressources (h) | L90: =Calculs!CW21 -> 0 | P90: =Calculs!CX21 -> 0 | T90: =Calculs!CY21 -> 0 | X90: =Calculs!CZ21 -> 0 | AB90: =Calculs!DA21 -> 0 | AF90: =Calculs!DB21 -> 0 | AJ90: =Calculs!DC21 -> 0 | AN90: =Calculs!DD21 -> 0 | AR90: =Calculs!DE21 -> 0 | AV90: =Calculs!DF21 -> 0 | AZ90: =Calculs!DG21 -> 0 | BD90: =Calculs!DH21 -> 0
B93: Charge d'une ressource = charge fixe hors projet + heures des lignes de l'onglet Charge où elle figure (colonne K pour un dessinateur, L pour une ressource externe), réparties par mois comme sur le Dashboard.
B94: Une ligne = une ressource : plusieurs personnes sur un même sous-projet = plusieurs lignes, chacune avec ses heures. Capacité et charge fixe : Data (F-G ou I-J), sinon valeurs par défaut du Dashboard.
B95: =IF(Calculs!$CD$27>0,"Attention : "&Calculs!$CD$27&" ligne(s) de l'onglet Charge ont à la fois un dessinateur (K) et une ressource externe (L) : seule la colonne K est comptée. Faire une ligne par ressource.","")
B96: =IF(Calculs!$CD$23+Calculs!$CD$26>16,"Attention : les listes Data contiennent "&(Calculs!$CD$23+Calculs!$CD$26)&" ressources, seules les 16 premières apparaissent dans le tableau d'occupation (le choix en haut de page fonctionne pour toutes).","")

Sheet Calculs
A1: CALCULS INTERMÉDIAIRES — alimentent le Dashboard, ne pas modifier
V2: Fin de mois → | W2: =EOMONTH(W3,0) -> 46295 | X2: =EOMONTH(X3,0) -> 46326 | Y2: =EOMONTH(Y3,0) -> 46356 | Z2: =EOMONTH(Z3,0) -> 46387 | AA2: =EOMONTH(AA3,0) -> 46418 | AB2: =EOMONTH(AB3,0) -> 46446 | AC2: =EOMONTH(AC3,0) -> 46477 | AD2: =EOMONTH(AD3,0) -> 46507 | ... AH2: =EOMONTH(AH3,0) -> 46630 | CW2: Heures projets par mois → | DI2: Occupation (charge fixe + projets) / capacité →
A3: Ligne (onglet Charge) | B3: Affaire valide (projet renseigné) | C3: Avancement (0-1) | D3: Incluse dans le périmètre | E3: Charge incluse (h) | F3: Chef de projet | G3: Projet | H3: Type | I3: Début planifié | J3: Fin de répartition | K3: Jours ouvrés de la période | L3: Rang affaire (charge décroissante) | M3: 1re occurrence chef | N3: Charge du chef | O3: Rang chef | P3: 1re occurrence projet | Q3: Charge du projet | R3: Rang projet | S3: 1re occurrence type | T3: Charge du type | U3: Rang type | V3: Groupe couleur (projet) | W3: =$AL$14 -> 46266 | X3: =EDATE(W3,1) -> 46296 | Y3: =EDATE(X3,1) -> 46327 | Z3: =EDATE(Y3,1) -> 46357 | AA3: =EDATE(Z3,1) -> 46388 | AB3: =EDATE(AA3,1) -> 46419 | AC3: =EDATE(AB3,1) -> 46447 | AD3: =EDATE(AC3,1) -> 46478 | AE3: =EDATE(AD3,1) -> 46508 | ... AH3: =EDATE(AG3,1) -> 46600 | AI3: Charge sur la période (h) | AK3: Indicateur | AL3: Valeur | AN3: N° mois | AO3: Mois | AP3: Charge (h) | AQ3: Affaires actives | AS3: Groupe | AT3: Projet | AU3: Charge (h) | AV3: Part | AW3: =W$3 -> 46266 | AX3: =X$3 -> 46296 | AY3: =Y$3 -> 46327 | AZ3: =Z$3 -> 46357 | BA3: =AA$3 -> 46388 | BB3: =AB$3 -> 46419 | BC3: =AC$3 -> 46447 | BD3: =AD$3 -> 46478 | ... BH3: =AH$3 -> 46600 | BK3: Rang | BL3: Chef de projet | BM3: Charge (h) | BO3: Rang | BP3: Projet | BQ3: Charge (h) | BS3: Rang | BT3: Type | BU3: Charge (h) | BW3: Rang | BX3: Position dans Charge | BZ3: Ressource de la ligne (K sinon L) | CA3: Rang affaire du dessinateur sélectionné | CC3: Dessinateur sélectionné | CD3: Valeur | CF3: N° mois | CG3: Mois | CH3: Charge fixe (h) | CI3: Charge projets (h) | CJ3: Charge totale (h) | CK3: Capacité (h) | CL3: Projets dans la capacité (h) | CM3: Dépassement (h) | CN3: Marge (+) / dépassement (-) (h, total arrondi) | CO3: Occupation (total arrondi) | CP3: Charge totale arrondie (h) | CQ3: N° mois si surcharge | CS3: N° | CT3: Ressource | CU3: Capacité (h) | CV3: Charge fixe (h) | CW3: =W$3 -> 46266 | CX3: =X$3 -> 46296 | CY3: =Y$3 -> 46327 | CZ3: =Z$3 -> 46357 | DA3: =AA$3 -> 46388 | DB3: =AB$3 -> 46419 | DC3: =AC$3 -> 46447 | DD3: =AD$3 -> 46478 | ... DH3: =AH$3 -> 46600 | DI3: =W$3 -> 46266 | DJ3: =X$3 -> 46296 | DK3: =Y$3 -> 46327 | DL3: =Z$3 -> 46357 | DM3: =AA$3 -> 46388 | DN3: =AB$3 -> 46419 | DO3: =AC$3 -> 46447 | DP3: =AD$3 -> 46478 | ... DT3: =AH$3 -> 46600 | DU3: Occupation maximale | DV3: Charge projets sur la période (h) | DX3: Rang | DY3: Position dans Charge | DZ3: Projet | EA3: Sous-projet | EB3: Produit | EC3: Chef de projet | ED3: Charge (h) | EE3: Heures sur la période | EF3: Début planifié | EG3: Date de besoin | EH3: Avancement | EJ3: Dessinateurs Data (nettoyés) | EK3: Ressources externes Data (nettoyées) | EM3: Type de ressource de la ligne | EN3: Clé affaire (projet | sous-projet | produit) | EO3: 1re ligne de l'affaire | EP3: Charge de l'affaire (h) | EQ3: Rang de l'affaire | ER3: Personnes internes (distinctes) | ES3: Personnes externes (distinctes) | ET3: Ressources (texte) | EU3: Avancement de l'affaire (pondéré par les heures) | EV3: Début de la ligne (31/12/9999 = vide) | EW3: Début de l'affaire (le plus tôt) | EX3: Besoin de la ligne (0 = vide) | EY3: Besoin de l'affaire (le plus tard) | FA3: Ressources : dessinateurs puis externes (liste déroulante) | FB3: Type | FD3: Ligne avec dessinateur ET externe (1 = à corriger) | FE3: 1re ligne de cette ressource sur l'affaire
A4: =ROW() -> 4 | B4: =IF(TRIM(INDEX(Charge!$B:$B,ROW()))<>"",1,0) -> 1 | C4: =IF(B4=1,MIN(1,MAX(0,N(INDEX(Charge!$O:$O,ROW())))),0) -> 0.15 | D4: =IF(B4=1,IF(OR(p_Perimetre="Tous les projets",C4<1),1,0),0) -> 1 | E4: =IF(D4=1,MAX(0,N(INDEX(Charge!$M:$M,ROW()))),0) -> 300 | F4: =IF(D4=1,IF(TRIM(INDEX(Charge!$A:$A,ROW()))="","(non renseigné)",TRIM(INDEX(Charge!$A:$A,ROW()))),"") -> Julie Martin | G4: =IF(D4=1,TRIM(INDEX(Charge!$B:$B,ROW())),"") -> ATLAS | H4: =IF(D4=1,IF(TRIM(INDEX(Charge!$E:$E,ROW()))="","(non renseigné)",TRIM(INDEX(Charge!$E:$E,ROW()))),"") -> Étude de conception | I4: =IF(AND(D4=1,ISNUMBER(INDEX(Charge!$N:$N,ROW()))),INDEX(Charge!$N:$N,ROW()),"") -> 46328 | J4: =IF(I4="","",IF(AND(p_Repartition="Lissée jusqu'à la date de besoin",ISNUMBER(INDEX(Charge!$F:$F,ROW()))),IF(INDEX(Charge!$F:$F,ROW())>=I4,INDEX(Charge!$F:$F,ROW()),I4),I4)) -> 46477 | K4: =IF(I4="","",NETWORKDAYS(I4,J4,Data!$K$4:$K$203)) -> 108 | L4: =IF(D4=1,COUNTIFS($D$4:$D$503,1,$E$4:$E$503,">"&E4)+COUNTIFS($D$4:$D4,1,$E$4:$E4,E4),"") -> 2 | M4: =IF(F4="",0,IF(COUNTIF($F$4:F4,F4)=1,1,0)) -> 1 | N4: =IF(M4=1,ROUND(SUMIF($F$4:$F$503,F4,$E$4:$E$503),2),"") -> 860 | O4: =IF(M4=1,COUNTIFS($M$4:$M$503,1,$N$4:$N$503,">"&N4)+COUNTIFS($M$4:M4,1,$N$4:N4,N4),"") -> 1 | P4: =IF(G4="",0,IF(COUNTIF($G$4:G4,G4)=1,1,0)) -> 1 | Q4: =IF(P4=1,ROUND(SUMIF($G$4:$G$503,G4,$E$4:$E$503),2),"") -> 860 | R4: =IF(P4=1,COUNTIFS($P$4:$P$503,1,$Q$4:$Q$503,">"&Q4)+COUNTIFS($P$4:P4,1,$Q$4:Q4,Q4),"") -> 1 | S4: =IF(H4="",0,IF(COUNTIF($H$4:H4,H4)=1,1,0)) -> 1 | T4: =IF(S4=1,ROUND(SUMIF($H$4:$H$503,H4,$E$4:$E$503),2),"") -> 2030 | U4: =IF(S4=1,COUNTIFS($S$4:$S$503,1,$T$4:$T$503,">"&T4)+COUNTIFS($S$4:S4,1,$T$4:T4,T4),"") -> 1 | V4: =IF(D4=1,MIN(INDEX($R$4:$R$503,MATCH(G4,$G$4:$G$503,0)),IF($AL$7>9,9,999)),"") -> 1 | W4: =IF(OR($I4="",$E4=0),0,IF(OR($J4<W$3,$I4>W$2),0,IF($K4=0,IF(AND($I4>=W$3,$I4<=W$2),$E4,0),$E4*NETWORKDAYS(MAX($I4,W$3),MIN($J4,W$2),Data!$K$4:$K$203)/$K4))) -> 0 | X4: =IF(OR($I4="",$E4=0),0,IF(OR($J4<X$3,$I4>X$2),0,IF($K4=0,IF(AND($I4>=X$3,$I4<=X$2),$E4,0),$E4*NETWORKDAYS(MAX($I4,X$3),MIN($J4,X$2),Data!$K$4:$K$203)/$K4))) -> 0 | Y4: =IF(OR($I4="",$E4=0),0,IF(OR($J4<Y$3,$I4>Y$2),0,IF($K4=0,IF(AND($I4>=Y$3,$I4<=Y$2),$E4,0),$E4*NETWORKDAYS(MAX($I4,Y$3),MIN($J4,Y$2),Data!$K$4:$K$203)/$K4))) -> 58.333333 | Z4: =IF(OR($I4="",$E4=0),0,IF(OR($J4<Z$3,$I4>Z$2),0,IF($K4=0,IF(AND($I4>=Z$3,$I4<=Z$2),$E4,0),$E4*NETWORKDAYS(MAX($I4,Z$3),MIN($J4,Z$2),Data!$K$4:$K$203)/$K4))) -> 63.888889 | AA4: =IF(OR($I4="",$E4=0),0,IF(OR($J4<AA$3,$I4>AA$2),0,IF($K4=0,IF(AND($I4>=AA$3,$I4<=AA$2),$E4,0),$E4*NETWORKDAYS(MAX($I4,AA$3),MIN($J4,AA$2),Data!$K$4:$K$203)/$K4))) -> 58.333333 | AB4: =IF(OR($I4="",$E4=0),0,IF(OR($J4<AB$3,$I4>AB$2),0,IF($K4=0,IF(AND($I4>=AB$3,$I4<=AB$2),$E4,0),$E4*NETWORKDAYS(MAX($I4,AB$3),MIN($J4,AB$2),Data!$K$4:$K$203)/$K4))) -> 55.555556 | AC4: =IF(OR($I4="",$E4=0),0,IF(OR($J4<AC$3,$I4>AC$2),0,IF($K4=0,IF(AND($I4>=AC$3,$I4<=AC$2),$E4,0),$E4*NETWORKDAYS(MAX($I4,AC$3),MIN($J4,AC$2),Data!$K$4:$K$203)/$K4))) -> 63.888889 | AD4: =IF(OR($I4="",$E4=0),0,IF(OR($J4<AD$3,$I4>AD$2),0,IF($K4=0,IF(AND($I4>=AD$3,$I4<=AD$2),$E4,0),$E4*NETWORKDAYS(MAX($I4,AD$3),MIN($J4,AD$2),Data!$K$4:$K$203)/$K4))) -> 0 | ... AH4: =IF(OR($I4="",$E4=0),0,IF(OR($J4<AH$3,$I4>AH$2),0,IF($K4=0,IF(AND($I4>=AH$3,$I4<=AH$2),$E4,0),$E4*NETWORKDAYS(MAX($I4,AH$3),MIN($J4,AH$2),Data!$K$4:$K$203)/$K4))) -> 0 | AI4: =SUM(W4:AH4) -> 300 | AK4: Charge totale identifiée (h) | AL4: =SUM(E4:E503) -> 3455 | AN4: 1 | AO4: =W$3 -> 46266 | AP4: =SUM(W4:W503) -> 28.363636 | AQ4: =SUMPRODUCT((W4:W503>0)/(COUNTIFS($EN$4:$EN$503,$EN$4:$EN$503,W4:W503,">0")+(W4:W503<=0))) -> 1 | AS4: 1 | AT4: =IF(AS4>$AL$7,"",INDEX($G$4:$G$503,MATCH(AS4,$R$4:$R$503,0))) -> ATLAS | AU4: =SUMIF($V$4:$V$503,AS4,$E$4:$E$503) -> 860 | AV4: =IF($AL$4=0,0,AU4/$AL$4) -> 0.24891462 | AW4: =SUMIF($V$4:$V$503,$AS4,W$4:W$503) -> 0 | AX4: =SUMIF($V$4:$V$503,$AS4,X$4:X$503) -> 0 | AY4: =SUMIF($V$4:$V$503,$AS4,Y$4:Y$503) -> 81.666667 | AZ4: =SUMIF($V$4:$V$503,$AS4,Z$4:Z$503) -> 89.444444 | BA4: =SUMIF($V$4:$V$503,$AS4,AA$4:AA$503) -> 120.66667 | BB4: =SUMIF($V$4:$V$503,$AS4,AB$4:AB$503) -> 129.77778 | BC4: =SUMIF($V$4:$V$503,$AS4,AC$4:AC$503) -> 149.24444 | BD4: =SUMIF($V$4:$V$503,$AS4,AD$4:AD$503) -> 99.552941 | ... BH4: =SUMIF($V$4:$V$503,$AS4,AH$4:AH$503) -> 0 | BK4: 1 | BL4: =IF(BK4>$AL$6,"",INDEX($F$4:$F$503,MATCH(BK4,$O$4:$O$503,0))) -> Julie Martin | BM4: =IF(BL4="","",INDEX($N$4:$N$503,MATCH(BK4,$O$4:$O$503,0))) -> 860 | BO4: 1 | BP4: =IF(BO4>$AL$7,"",INDEX($G$4:$G$503,MATCH(BO4,$R$4:$R$503,0))) -> ATLAS | BQ4: =IF(BP4="","",INDEX($Q$4:$Q$503,MATCH(BO4,$R$4:$R$503,0))) -> 860 | BS4: 1 | BT4: =IF(BS4>$AL$8,"",INDEX($H$4:$H$503,MATCH(BS4,$U$4:$U$503,0))) -> Étude de conception | BU4: =IF(BT4="","",INDEX($T$4:$T$503,MATCH(BS4,$U$4:$U$503,0))) -> 2030 | BW4: 1 | BX4: =IFERROR(MATCH(BW4,$EQ$4:$EQ$503,0),"") -> 17 | BZ4: =IF(D4=1,IF(TRIM(INDEX(Charge!$K:$K,ROW()))<>"",TRIM(INDEX(Charge!$K:$K,ROW())),IF(TRIM(INDEX(Charge!$L:$L,ROW()))<>"",TRIM(INDEX(Charge!$L:$L,ROW())),"(non affecté)")),"") -> Lucas Garnier | CA4: =IF(AND($CD$4<>"",BZ4=$CD$4),COUNTIFS($BZ$4:$BZ$503,$CD$4,$L$4:$L$503,"<"&L4)+1,"") -> 1 | CC4: Ressource sélectionnée | CD4: =TRIM(p_Dessinateur) -> Lucas Garnier | CF4: 1 | CG4: =W$3 -> 46266 | CH4: =IF($CD$4="",0,$CD$7) -> 20 | CI4: =IF($CD$4="",0,SUMIF($BZ$4:$BZ$503,$CD$4,W$4:W$503)) -> 28.363636 | CJ4: =CH4+CI4 -> 48.363636 | CK4: =IF($CD$4="",0,$CD$6) -> 120 | CL4: =IF(CN4<0,MAX(0,MIN(CI4,CK4-CH4)),CI4) -> 28.363636 | CM4: =CI4-CL4 -> 0 | CN4: =CK4-CP4 -> 72 | CO4: =IF(CK4<=0,IF(CP4>0,9.99,0),CP4/CK4) -> 0.4 | CP4: =ROUND(CJ4,0) -> 48 | CQ4: =IF(CN4<0,CF4,"") | CS4: 1 | CT4: =IF(OR(FA4="",FALSE),"",FA4) -> Lucas Garnier | CU4: =IF(CT4="","",IF(FB4="Interne",IF(ISNUMBER(INDEX(Data!$F:$F,4)),INDEX(Data!$F:$F,4),p_HeuresETP),IF(ISNUMBER(INDEX(Data!$I:$I,4-$CD$23)),INDEX(Data!$I:$I,4-$CD$23),p_HeuresETP))) -> 120 | CV4: =IF(CT4="","",IF(FB4="Interne",IF(ISNUMBER(INDEX(Data!$G:$G,4)),INDEX(Data!$G:$G,4),p_ChargeFixe),IF(ISNUMBER(INDEX(Data!$J:$J,4-$CD$23)),INDEX(Data!$J:$J,4-$CD$23),p_ChargeFixe))) -> 20 | CW4: =IF($CT4="","",SUMIF($BZ$4:$BZ$503,$CT4,W$4:W$503)) -> 28.363636 | CX4: =IF($CT4="","",SUMIF($BZ$4:$BZ$503,$CT4,X$4:X$503)) -> 48 | CY4: =IF($CT4="","",SUMIF($BZ$4:$BZ$503,$CT4,Y$4:Y$503)) -> 101.9697 | CZ4: =IF($CT4="","",SUMIF($BZ$4:$BZ$503,$CT4,Z$4:Z$503)) -> 63.888889 | DA4: =IF($CT4="","",SUMIF($BZ$4:$BZ$503,$CT4,AA$4:AA$503)) -> 58.333333 | DB4: =IF($CT4="","",SUMIF($BZ$4:$BZ$503,$CT4,AB$4:AB$503)) -> 55.555556 | DC4: =IF($CT4="","",SUMIF($BZ$4:$BZ$503,$CT4,AC$4:AC$503)) -> 63.888889 | DD4: =IF($CT4="","",SUMIF($BZ$4:$BZ$503,$CT4,AD$4:AD$503)) -> 0 | ... DH4: =IF($CT4="","",SUMIF($BZ$4:$BZ$503,$CT4,AH$4:AH$503)) -> 0 | DI4: =IF($CT4="","",IF($CU4<=0,IF(ROUND($CV4+CW4,0)>0,9.99,0),ROUND($CV4+CW4,0)/$CU4)) -> 0.4 | DJ4: =IF($CT4="","",IF($CU4<=0,IF(ROUND($CV4+CX4,0)>0,9.99,0),ROUND($CV4+CX4,0)/$CU4)) -> 0.56666667 | DK4: =IF($CT4="","",IF($CU4<=0,IF(ROUND($CV4+CY4,0)>0,9.99,0),ROUND($CV4+CY4,0)/$CU4)) -> 1.0166667 | DL4: =IF($CT4="","",IF($CU4<=0,IF(ROUND($CV4+CZ4,0)>0,9.99,0),ROUND($CV4+CZ4,0)/$CU4)) -> 0.7 | DM4: =IF($CT4="","",IF($CU4<=0,IF(ROUND($CV4+DA4,0)>0,9.99,0),ROUND($CV4+DA4,0)/$CU4)) -> 0.65 | DN4: =IF($CT4="","",IF($CU4<=0,IF(ROUND($CV4+DB4,0)>0,9.99,0),ROUND($CV4+DB4,0)/$CU4)) -> 0.63333333 | DO4: =IF($CT4="","",IF($CU4<=0,IF(ROUND($CV4+DC4,0)>0,9.99,0),ROUND($CV4+DC4,0)/$CU4)) -> 0.7 | DP4: =IF($CT4="","",IF($CU4<=0,IF(ROUND($CV4+DD4,0)>0,9.99,0),ROUND($CV4+DD4,0)/$CU4)) -> 0.16666667 | ... DT4: =IF($CT4="","",IF($CU4<=0,IF(ROUND($CV4+DH4,0)>0,9.99,0),ROUND($CV4+DH4,0)/$CU4)) -> 0.16666667 | DU4: =IF(CT4="","",MAX(DI4:DT4)) -> 1.0166667 | DV4: =IF(CT4="","",SUM(CW4:DH4)) -> 420 | DX4: 1 | DY4: =IFERROR(MATCH(DX4,$CA$4:$CA$503,0),"") -> 1 | DZ4: =IF(DY4="","",INDEX(Charge!$B:$B,DY4+3)&"") -> ATLAS | EA4: =IF(DY4="","",INDEX(Charge!$C:$C,DY4+3)&"") -> Lot 1 – Structure | EB4: =IF(DY4="","",INDEX(Charge!$D:$D,DY4+3)&"") -> Châssis principal | EC4: =IF(DY4="","",INDEX(Charge!$A:$A,DY4+3)&"") -> Julie Martin | ED4: =IF(DY4="","",INDEX($E$4:$E$503,DY4)) -> 300 | EE4: =IF(DY4="","",INDEX($AI$4:$AI$503,DY4)) -> 300 | EF4: =IF(DY4="","",IF(ISNUMBER(INDEX(Charge!$N:$N,DY4+3)),INDEX(Charge!$N:$N,DY4+3),"—")) -> 46328 | EG4: =IF(DY4="","",IF(ISNUMBER(INDEX(Charge!$F:$F,DY4+3)),INDEX(Charge!$F:$F,DY4+3),"—")) -> 46477 | EH4: =IF(DY4="","",INDEX($C$4:$C$503,DY4)) -> 0.15 | EJ4: =TRIM(INDEX(Data!$E:$E,ROW())) -> Lucas Garnier | EK4: =TRIM(INDEX(Data!$H:$H,ROW())) -> Paul Girard | EM4: =IF(D4=1,IF(TRIM(INDEX(Charge!$K:$K,ROW()))<>"","Interne",IF(TRIM(INDEX(Charge!$L:$L,ROW()))<>"","Externe","Non affecté")),"") -> Interne | EN4: =IF(D4=1,LEFT(SUBSTITUTE(SUBSTITUTE(SUBSTITUTE(TRIM(SUBSTITUTE(INDEX(Charge!$B:$B,ROW()),CHAR(160)," "))&" | "&TRIM(SUBSTITUTE(INDEX(Charge!$C:$C,ROW()),CHAR(160)," "))&" | "&TRIM(SUBSTITUTE(INDEX(Charge!$D:$D,ROW()),CHAR(160)," ")),"~","-"),"*","+"),"?","!"),240),"") -> ATLAS | Lot 1 – Structure | Châssis principal | EO4: =IF(EN4="",0,IF(COUNTIF($EN$4:EN4,EN4)=1,1,0)) -> 1 | EP4: =IF(EO4=1,ROUND(SUMIF($EN$4:$EN$503,EN4,$E$4:$E$503),2),"") -> 420 | EQ4: =IF(EO4=1,COUNTIFS($EO$4:$EO$503,1,$EP$4:$EP$503,">"&EP4)+COUNTIFS($EO$4:EO4,1,$EP$4:EP4,EP4),"") -> 2 | ER4: =IF(EO4=1,COUNTIFS($EN$4:$EN$503,EN4,$EM$4:$EM$503,"Interne",$FE$4:$FE$503,1),"") -> 1 | ES4: =IF(EO4=1,COUNTIFS($EN$4:$EN$503,EN4,$EM$4:$EM$503,"Externe",$FE$4:$FE$503,1),"") -> 1 | ET4: =IF(EO4=1,IF(ER4+ES4=0,"à affecter",IF(ER4=0,ES4&" ext.",(ER4+ES4)&IF(ES4>0," dont "&ES4&" ext.",""))&IF(COUNTIFS($EN$4:$EN$503,EN4,$EM$4:$EM$503,"Non affecté")>0," + à affecter","")),"") -> 2 dont 1 ext. | EU4: =IF(EO4=1,IF(EP4>0,SUMPRODUCT(($EN$4:$EN$503=EN4)*$E$4:$E$503*$C$4:$C$503)/EP4,AVERAGEIF($EN$4:$EN$503,EN4,$C$4:$C$503)),"") -> 0.10714286 | EV4: =IF(ISNUMBER(I4),I4,2958465) -> 46328 | EW4: =IF(EO4=1,SUMPRODUCT(MIN(($EN$4:$EN$503=EN4)*$EV$4:$EV$503+($EN$4:$EN$503<>EN4)*2958465)),"") -> 46328 | EX4: =IF(AND(D4=1,ISNUMBER(INDEX(Charge!$F:$F,ROW()))),INDEX(Charge!$F:$F,ROW()),0) -> 46477 | EY4: =IF(EO4=1,SUMPRODUCT(MAX(($EN$4:$EN$503=EN4)*$EX$4:$EX$503)),"") -> 46477 | FA4: =IF(1<=$CD$23,INDEX($EJ$4:$EJ$203,1),IF(1-$CD$23<=$CD$26,INDEX($EK$4:$EK$203,1-$CD$23),"")) -> Lucas Garnier | FB4: =IF(FA4="","",IF(1<=$CD$23,"Interne","Externe")) -> Interne | FD4: =IF(AND(B4=1,TRIM(INDEX(Charge!$K:$K,ROW()))<>"",TRIM(INDEX(Charge!$L:$L,ROW()))<>""),1,0) -> 0 | FE4: =IF(OR(EN4="",BZ4="(non affecté)"),0,IF(COUNTIFS($EN$4:EN4,EN4,$BZ$4:BZ4,BZ4)=1,1,0)) -> 1
A5: =ROW() -> 5 | B5: =IF(TRIM(INDEX(Charge!$B:$B,ROW()))<>"",1,0) -> 1 | C5: =IF(B5=1,MIN(1,MAX(0,N(INDEX(Charge!$O:$O,ROW())))),0) -> 0 | D5: =IF(B5=1,IF(OR(p_Perimetre="Tous les projets",C5<1),1,0),0) -> 1 | E5: =IF(D5=1,MAX(0,N(INDEX(Charge!$M:$M,ROW()))),0) -> 120 | F5: =IF(D5=1,IF(TRIM(INDEX(Charge!$A:$A,ROW()))="","(non renseigné)",TRIM(INDEX(Charge!$A:$A,ROW()))),"") -> Julie Martin | G5: =IF(D5=1,TRIM(INDEX(Charge!$B:$B,ROW())),"") -> ATLAS | H5: =IF(D5=1,IF(TRIM(INDEX(Charge!$E:$E,ROW()))="","(non renseigné)",TRIM(INDEX(Charge!$E:$E,ROW()))),"") -> Étude de conception | I5: =IF(AND(D5=1,ISNUMBER(INDEX(Charge!$N:$N,ROW()))),INDEX(Charge!$N:$N,ROW()),"") -> 46328 | J5: =IF(I5="","",IF(AND(p_Repartition="Lissée jusqu'à la date de besoin",ISNUMBER(INDEX(Charge!$F:$F,ROW()))),IF(INDEX(Charge!$F:$F,ROW())>=I5,INDEX(Charge!$F:$F,ROW()),I5),I5)) -> 46477 | K5: =IF(I5="","",NETWORKDAYS(I5,J5,Data!$K$4:$K$203)) -> 108 | L5: =IF(D5=1,COUNTIFS($D$4:$D$503,1,$E$4:$E$503,">"&E5)+COUNTIFS($D$4:$D5,1,$E$4:$E5,E5),"") -> 12 | M5: =IF(F5="",0,IF(COUNTIF($F$4:F5,F5)=1,1,0)) -> 0 | N5: =IF(M5=1,ROUND(SUMIF($F$4:$F$503,F5,$E$4:$E$503),2),"") | O5: =IF(M5=1,COUNTIFS($M$4:$M$503,1,$N$4:$N$503,">"&N5)+COUNTIFS($M$4:M5,1,$N$4:N5,N5),"") | P5: =IF(G5="",0,IF(COUNTIF($G$4:G5,G5)=1,1,0)) -> 0 | Q5: =IF(P5=1,ROUND(SUMIF($G$4:$G$503,G5,$E$4:$E$503),2),"") | R5: =IF(P5=1,COUNTIFS($P$4:$P$503,1,$Q$4:$Q$503,">"&Q5)+COUNTIFS($P$4:P5,1,$Q$4:Q5,Q5),"") | S5: =IF(H5="",0,IF(COUNTIF($H$4:H5,H5)=1,1,0)) -> 0 | T5: =IF(S5=1,ROUND(SUMIF($H$4:$H$503,H5,$E$4:$E$503),2),"") | U5: =IF(S5=1,COUNTIFS($S$4:$S$503,1,$T$4:$T$503,">"&T5)+COUNTIFS($S$4:S5,1,$T$4:T5,T5),"") | V5: =IF(D5=1,MIN(INDEX($R$4:$R$503,MATCH(G5,$G$4:$G$503,0)),IF($AL$7>9,9,999)),"") -> 1 | W5: =IF(OR($I5="",$E5=0),0,IF(OR($J5<W$3,$I5>W$2),0,IF($K5=0,IF(AND($I5>=W$3,$I5<=W$2),$E5,0),$E5*NETWORKDAYS(MAX($I5,W$3),MIN($J5,W$2),Data!$K$4:$K$203)/$K5))) -> 0 | X5: =IF(OR($I5="",$E5=0),0,IF(OR($J5<X$3,$I5>X$2),0,IF($K5=0,IF(AND($I5>=X$3,$I5<=X$2),$E5,0),$E5*NETWORKDAYS(MAX($I5,X$3),MIN($J5,X$2),Data!$K$4:$K$203)/$K5))) -> 0 | Y5: =IF(OR($I5="",$E5=0),0,IF(OR($J5<Y$3,$I5>Y$2),0,IF($K5=0,IF(AND($I5>=Y$3,$I5<=Y$2),$E5,0),$E5*NETWORKDAYS(MAX($I5,Y$3),MIN($J5,Y$2),Data!$K$4:$K$203)/$K5))) -> 23.333333 | Z5: =IF(OR($I5="",$E5=0),0,IF(OR($J5<Z$3,$I5>Z$2),0,IF($K5=0,IF(AND($I5>=Z$3,$I5<=Z$2),$E5,0),$E5*NETWORKDAYS(MAX($I5,Z$3),MIN($J5,Z$2),Data!$K$4:$K$203)/$K5))) -> 25.555556 | AA5: =IF(OR($I5="",$E5=0),0,IF(OR($J5<AA$3,$I5>AA$2),0,IF($K5=0,IF(AND($I5>=AA$3,$I5<=AA$2),$E5,0),$E5*NETWORKDAYS(MAX($I5,AA$3),MIN($J5,AA$2),Data!$K$4:$K$203)/$K5))) -> 23.333333 | AB5: =IF(OR($I5="",$E5=0),0,IF(OR($J5<AB$3,$I5>AB$2),0,IF($K5=0,IF(AND($I5>=AB$3,$I5<=AB$2),$E5,0),$E5*NETWORKDAYS(MAX($I5,AB$3),MIN($J5,AB$2),Data!$K$4:$K$203)/$K5))) -> 22.222222 | AC5: =IF(OR($I5="",$E5=0),0,IF(OR($J5<AC$3,$I5>AC$2),0,IF($K5=0,IF(AND($I5>=AC$3,$I5<=AC$2),$E5,0),$E5*NETWORKDAYS(MAX($I5,AC$3),MIN($J5,AC$2),Data!$K$4:$K$203)/$K5))) -> 25.555556 | AD5: =IF(OR($I5="",$E5=0),0,IF(OR($J5<AD$3,$I5>AD$2),0,IF($K5=0,IF(AND($I5>=AD$3,$I5<=AD$2),$E5,0),$E5*NETWORKDAYS(MAX($I5,AD$3),MIN($J5,AD$2),Data!$K$4:$K$203)/$K5))) -> 0 | ... AH5: =IF(OR($I5="",$E5=0),0,IF(OR($J5<AH$3,$I5>AH$2),0,IF($K5=0,IF(AND($I5>=AH$3,$I5<=AH$2),$E5,0),$E5*NETWORKDAYS(MAX($I5,AH$3),MIN($J5,AH$2),Data!$K$4:$K$203)/$K5))) -> 0 | AI5: =SUM(W5:AH5) -> 120 | AK5: Nombre d'affaires (sous-projets regroupés) | AL5: =SUM(EO4:EO503) -> 17 | AN5: 2 | AO5: =X$3 -> 46296 | AP5: =SUM(X4:X503) -> 165.94118 | AQ5: =SUMPRODUCT((X4:X503>0)/(COUNTIFS($EN$4:$EN$503,$EN$4:$EN$503,X4:X503,">0")+(X4:X503<=0))) -> 3 | AS5: 2 | AT5: =IF(AS5>$AL$7,"",INDEX($G$4:$G$503,MATCH(AS5,$R$4:$R$503,0))) -> BORÉAL | AU5: =SUMIF($V$4:$V$503,AS5,$E$4:$E$503) -> 620 | AV5: =IF($AL$4=0,0,AU5/$AL$4) -> 0.17945007 | AW5: =SUMIF($V$4:$V$503,$AS5,W$4:W$503) -> 0 | AX5: =SUMIF($V$4:$V$503,$AS5,X$4:X$503) -> 72.941176 | AY5: =SUMIF($V$4:$V$503,$AS5,Y$4:Y$503) -> 76.588235 | AZ5: =SUMIF($V$4:$V$503,$AS5,Z$4:Z$503) -> 83.882353 | BA5: =SUMIF($V$4:$V$503,$AS5,AA$4:AA$503) -> 98.539455 | BB5: =SUMIF($V$4:$V$503,$AS5,AB$4:AB$503) -> 111.59475 | BC5: =SUMIF($V$4:$V$503,$AS5,AC$4:AC$503) -> 101.9925 | BD5: =SUMIF($V$4:$V$503,$AS5,AD$4:AD$503) -> 74.461538 | ... BH5: =SUMIF($V$4:$V$503,$AS5,AH$4:AH$503) -> 0 | BK5: 2 | BL5: =IF(BK5>$AL$6,"",INDEX($F$4:$F$503,MATCH(BK5,$O$4:$O$503,0))) -> Thomas Bernard | BM5: =IF(BL5="","",INDEX($N$4:$N$503,MATCH(BK5,$O$4:$O$503,0))) -> 820 | BO5: 2 | BP5: =IF(BO5>$AL$7,"",INDEX($G$4:$G$503,MATCH(BO5,$R$4:$R$503,0))) -> BORÉAL | BQ5: =IF(BP5="","",INDEX($Q$4:$Q$503,MATCH(BO5,$R$4:$R$503,0))) -> 620 | BS5: 2 | BT5: =IF(BS5>$AL$8,"",INDEX($H$4:$H$503,MATCH(BS5,$U$4:$U$503,0))) -> Industrialisation | BU5: =IF(BT5="","",INDEX($T$4:$T$503,MATCH(BS5,$U$4:$U$503,0))) -> 540 | BW5: 2 | BX5: =IFERROR(MATCH(BW5,$EQ$4:$EQ$503,0),"") -> 1 | BZ5: =IF(D5=1,IF(TRIM(INDEX(Charge!$K:$K,ROW()))<>"",TRIM(INDEX(Charge!$K:$K,ROW())),IF(TRIM(INDEX(Charge!$L:$L,ROW()))<>"",TRIM(INDEX(Charge!$L:$L,ROW())),"(non affecté)")),"") -> Paul Girard | CA5: =IF(AND($CD$4<>"",BZ5=$CD$4),COUNTIFS($BZ$4:$BZ$503,$CD$4,$L$4:$L$503,"<"&L5)+1,"") | CC5: Position dans la liste des dessinateurs (0 = absent) | CD5: =IF(CD4="",0,IFERROR(MATCH(CD4,$EJ$4:$EJ$203,0),0)) -> 1 | CF5: 2 | CG5: =X$3 -> 46296 | CH5: =IF($CD$4="",0,$CD$7) -> 20 | CI5: =IF($CD$4="",0,SUMIF($BZ$4:$BZ$503,$CD$4,X$4:X$503)) -> 48 | CJ5: =CH5+CI5 -> 68 | CK5: =IF($CD$4="",0,$CD$6) -> 120 | CL5: =IF(CN5<0,MAX(0,MIN(CI5,CK5-CH5)),CI5) -> 48 | CM5: =CI5-CL5 -> 0 | CN5: =CK5-CP5 -> 52 | CO5: =IF(CK5<=0,IF(CP5>0,9.99,0),CP5/CK5) -> 0.56666667 | CP5: =ROUND(CJ5,0) -> 68 | CQ5: =IF(CN5<0,CF5,"") | CS5: 2 | CT5: =IF(OR(FA5="",COUNTIF($FA$4:FA4,FA5)>0),"",FA5) -> Emma Faure | CU5: =IF(CT5="","",IF(FB5="Interne",IF(ISNUMBER(INDEX(Data!$F:$F,5)),INDEX(Data!$F:$F,5),p_HeuresETP),IF(ISNUMBER(INDEX(Data!$I:$I,5-$CD$23)),INDEX(Data!$I:$I,5-$CD$23),p_HeuresETP))) -> 120 | CV5: =IF(CT5="","",IF(FB5="Interne",IF(ISNUMBER(INDEX(Data!$G:$G,5)),INDEX(Data!$G:$G,5),p_ChargeFixe),IF(ISNUMBER(INDEX(Data!$J:$J,5-$CD$23)),INDEX(Data!$J:$J,5-$CD$23),p_ChargeFixe))) -> 20 | CW5: =IF($CT5="","",SUMIF($BZ$4:$BZ$503,$CT5,W$4:W$503)) -> 0 | CX5: =IF($CT5="","",SUMIF($BZ$4:$BZ$503,$CT5,X$4:X$503)) -> 0 | CY5: =IF($CT5="","",SUMIF($BZ$4:$BZ$503,$CT5,Y$4:Y$503)) -> 0 | CZ5: =IF($CT5="","",SUMIF($BZ$4:$BZ$503,$CT5,Z$4:Z$503)) -> 57.5 | DA5: =IF($CT5="","",SUMIF($BZ$4:$BZ$503,$CT5,AA$4:AA$503)) -> 91.5 | DB5: =IF($CT5="","",SUMIF($BZ$4:$BZ$503,$CT5,AB$4:AB$503)) -> 102 | DC5: =IF($CT5="","",SUMIF($BZ$4:$BZ$503,$CT5,AC$4:AC$503)) -> 126.70909 | DD5: =IF($CT5="","",SUMIF($BZ$4:$BZ$503,$CT5,AD$4:AD$503)) -> 121.2 | ... DH5: =IF($CT5="","",SUMIF($BZ$4:$BZ$503,$CT5,AH$4:AH$503)) -> 28.235294 | DI5: =IF($CT5="","",IF($CU5<=0,IF(ROUND($CV5+CW5,0)>0,9.99,0),ROUND($CV5+CW5,0)/$CU5)) -> 0.16666667 | DJ5: =IF($CT5="","",IF($CU5<=0,IF(ROUND($CV5+CX5,0)>0,9.99,0),ROUND($CV5+CX5,0)/$CU5)) -> 0.16666667 | DK5: =IF($CT5="","",IF($CU5<=0,IF(ROUND($CV5+CY5,0)>0,9.99,0),ROUND($CV5+CY5,0)/$CU5)) -> 0.16666667 | DL5: =IF($CT5="","",IF($CU5<=0,IF(ROUND($CV5+CZ5,0)>0,9.99,0),ROUND($CV5+CZ5,0)/$CU5)) -> 0.65 | DM5: =IF($CT5="","",IF($CU5<=0,IF(ROUND($CV5+DA5,0)>0,9.99,0),ROUND($CV5+DA5,0)/$CU5)) -> 0.93333333 | DN5: =IF($CT5="","",IF($CU5<=0,IF(ROUND($CV5+DB5,0)>0,9.99,0),ROUND($CV5+DB5,0)/$CU5)) -> 1.0166667 | DO5: =IF($CT5="","",IF($CU5<=0,IF(ROUND($CV5+DC5,0)>0,9.99,0),ROUND($CV5+DC5,0)/$CU5)) -> 1.225 | DP5: =IF($CT5="","",IF($CU5<=0,IF(ROUND($CV5+DD5,0)>0,9.99,0),ROUND($CV5+DD5,0)/$CU5)) -> 1.175 | ... DT5: =IF($CT5="","",IF($CU5<=0,IF(ROUND($CV5+DH5,0)>0,9.99,0),ROUND($CV5+DH5,0)/$CU5)) -> 0.4 | DU5: =IF(CT5="","",MAX(DI5:DT5)) -> 1.225 | DV5: =IF(CT5="","",SUM(CW5:DH5)) -> 700 | DX5: 2 | DY5: =IFERROR(MATCH(DX5,$CA$4:$CA$503,0),"") -> 13 | DZ5: =IF(DY5="","",INDEX(Charge!$B:$B,DY5+3)&"") -> ORION | EA5: =IF(DY5="","",INDEX(Charge!$C:$C,DY5+3)&"") -> Tranche 1 | EB5: =IF(DY5="","",INDEX(Charge!$D:$D,DY5+3)&"") -> Support moteur | EC5: =IF(DY5="","",INDEX(Charge!$A:$A,DY5+3)&"") -> Nicolas Moreau | ED5: =IF(DY5="","",INDEX($E$4:$E$503,DY5)) -> 120 | EE5: =IF(DY5="","",INDEX($AI$4:$AI$503,DY5)) -> 120 | EF5: =IF(DY5="","",IF(ISNUMBER(INDEX(Charge!$N:$N,DY5+3)),INDEX(Charge!$N:$N,DY5+3),"—")) -> 46279 | EG5: =IF(DY5="","",IF(ISNUMBER(INDEX(Charge!$F:$F,DY5+3)),INDEX(Charge!$F:$F,DY5+3),"—")) -> 46353 | EH5: =IF(DY5="","",INDEX($C$4:$C$503,DY5)) -> 0.8 | EJ5: =TRIM(INDEX(Data!$E:$E,ROW())) -> Emma Faure | EK5: =TRIM(INDEX(Data!$H:$H,ROW())) -> Inès Morel | EM5: =IF(D5=1,IF(TRIM(INDEX(Charge!$K:$K,ROW()))<>"","Interne",IF(TRIM(INDEX(Charge!$L:$L,ROW()))<>"","Externe","Non affecté")),"") -> Externe | EN5: =IF(D5=1,LEFT(SUBSTITUTE(SUBSTITUTE(SUBSTITUTE(TRIM(SUBSTITUTE(INDEX(Charge!$B:$B,ROW()),CHAR(160)," "))&" | "&TRIM(SUBSTITUTE(INDEX(Charge!$C:$C,ROW()),CHAR(160)," "))&" | "&TRIM(SUBSTITUTE(INDEX(Charge!$D:$D,ROW()),CHAR(160)," ")),"~","-"),"*","+"),"?","!"),240),"") -> ATLAS | Lot 1 – Structure | Châssis principal | EO5: =IF(EN5="",0,IF(COUNTIF($EN$4:EN5,EN5)=1,1,0)) -> 0 | EP5: =IF(EO5=1,ROUND(SUMIF($EN$4:$EN$503,EN5,$E$4:$E$503),2),"") | EQ5: =IF(EO5=1,COUNTIFS($EO$4:$EO$503,1,$EP$4:$EP$503,">"&EP5)+COUNTIFS($EO$4:EO5,1,$EP$4:EP5,EP5),"") | ER5: =IF(EO5=1,COUNTIFS($EN$4:$EN$503,EN5,$EM$4:$EM$503,"Interne",$FE$4:$FE$503,1),"") | ES5: =IF(EO5=1,COUNTIFS($EN$4:$EN$503,EN5,$EM$4:$EM$503,"Externe",$FE$4:$FE$503,1),"") | ET5: =IF(EO5=1,IF(ER5+ES5=0,"à affecter",IF(ER5=0,ES5&" ext.",(ER5+ES5)&IF(ES5>0," dont "&ES5&" ext.",""))&IF(COUNTIFS($EN$4:$EN$503,EN5,$EM$4:$EM$503,"Non affecté")>0," + à affecter","")),"") | EU5: =IF(EO5=1,IF(EP5>0,SUMPRODUCT(($EN$4:$EN$503=EN5)*$E$4:$E$503*$C$4:$C$503)/EP5,AVERAGEIF($EN$4:$EN$503,EN5,$C$4:$C$503)),"") | EV5: =IF(ISNUMBER(I5),I5,2958465) -> 46328 | EW5: =IF(EO5=1,SUMPRODUCT(MIN(($EN$4:$EN$503=EN5)*$EV$4:$EV$503+($EN$4:$EN$503<>EN5)*2958465)),"") | EX5: =IF(AND(D5=1,ISNUMBER(INDEX(Charge!$F:$F,ROW()))),INDEX(Charge!$F:$F,ROW()),0) -> 46477 | EY5: =IF(EO5=1,SUMPRODUCT(MAX(($EN$4:$EN$503=EN5)*$EX$4:$EX$503)),"") | FA5: =IF(2<=$CD$23,INDEX($EJ$4:$EJ$203,2),IF(2-$CD$23<=$CD$26,INDEX($EK$4:$EK$203,2-$CD$23),"")) -> Emma Faure | FB5: =IF(FA5="","",IF(2<=$CD$23,"Interne","Externe")) -> Interne | FD5: =IF(AND(B5=1,TRIM(INDEX(Charge!$K:$K,ROW()))<>"",TRIM(INDEX(Charge!$L:$L,ROW()))<>""),1,0) -> 0 | FE5: =IF(OR(EN5="",BZ5="(non affecté)"),0,IF(COUNTIFS($EN$4:EN5,EN5,$BZ$4:BZ5,BZ5)=1,1,0)) -> 1
A6: =ROW() -> 6 | B6: =IF(TRIM(INDEX(Charge!$B:$B,ROW()))<>"",1,0) -> 1 | C6: =IF(B6=1,MIN(1,MAX(0,N(INDEX(Charge!$O:$O,ROW())))),0) -> 0 | D6: =IF(B6=1,IF(OR(p_Perimetre="Tous les projets",C6<1),1,0),0) -> 1 | E6: =IF(D6=1,MAX(0,N(INDEX(Charge!$M:$M,ROW()))),0) -> 260 | F6: =IF(D6=1,IF(TRIM(INDEX(Charge!$A:$A,ROW()))="","(non renseigné)",TRIM(INDEX(Charge!$A:$A,ROW()))),"") -> Julie Martin | G6: =IF(D6=1,TRIM(INDEX(Charge!$B:$B,ROW())),"") -> ATLAS | H6: =IF(D6=1,IF(TRIM(INDEX(Charge!$E:$E,ROW()))="","(non renseigné)",TRIM(INDEX(Charge!$E:$E,ROW()))),"") -> Étude de conception | I6: =IF(AND(D6=1,ISNUMBER(INDEX(Charge!$N:$N,ROW()))),INDEX(Charge!$N:$N,ROW()),"") -> 46398 | J6: =IF(I6="","",IF(AND(p_Repartition="Lissée jusqu'à la date de besoin",ISNUMBER(INDEX(Charge!$F:$F,ROW()))),IF(INDEX(Charge!$F:$F,ROW())>=I6,INDEX(Charge!$F:$F,ROW()),I6),I6)) -> 46535 | K6: =IF(I6="","",NETWORKDAYS(I6,J6,Data!$K$4:$K$203)) -> 100 | L6: =IF(D6=1,COUNTIFS($D$4:$D$503,1,$E$4:$E$503,">"&E6)+COUNTIFS($D$4:$D6,1,$E$4:$E6,E6),"") -> 4 | M6: =IF(F6="",0,IF(COUNTIF($F$4:F6,F6)=1,1,0)) -> 0 | N6: =IF(M6=1,ROUND(SUMIF($F$4:$F$503,F6,$E$4:$E$503),2),"") | O6: =IF(M6=1,COUNTIFS($M$4:$M$503,1,$N$4:$N$503,">"&N6)+COUNTIFS($M$4:M6,1,$N$4:N6,N6),"") | P6: =IF(G6="",0,IF(COUNTIF($G$4:G6,G6)=1,1,0)) -> 0 | Q6: =IF(P6=1,ROUND(SUMIF($G$4:$G$503,G6,$E$4:$E$503),2),"") | R6: =IF(P6=1,COUNTIFS($P$4:$P$503,1,$Q$4:$Q$503,">"&Q6)+COUNTIFS($P$4:P6,1,$Q$4:Q6,Q6),"") | S6: =IF(H6="",0,IF(COUNTIF($H$4:H6,H6)=1,1,0)) -> 0 | T6: =IF(S6=1,ROUND(SUMIF($H$4:$H$503,H6,$E$4:$E$503),2),"") | U6: =IF(S6=1,COUNTIFS($S$4:$S$503,1,$T$4:$T$503,">"&T6)+COUNTIFS($S$4:S6,1,$T$4:T6,T6),"") | V6: =IF(D6=1,MIN(INDEX($R$4:$R$503,MATCH(G6,$G$4:$G$503,0)),IF($AL$7>9,9,999)),"") -> 1 | W6: =IF(OR($I6="",$E6=0),0,IF(OR($J6<W$3,$I6>W$2),0,IF($K6=0,IF(AND($I6>=W$3,$I6<=W$2),$E6,0),$E6*NETWORKDAYS(MAX($I6,W$3),MIN($J6,W$2),Data!$K$4:$K$203)/$K6))) -> 0 | X6: =IF(OR($I6="",$E6=0),0,IF(OR($J6<X$3,$I6>X$2),0,IF($K6=0,IF(AND($I6>=X$3,$I6<=X$2),$E6,0),$E6*NETWORKDAYS(MAX($I6,X$3),MIN($J6,X$2),Data!$K$4:$K$203)/$K6))) -> 0 | Y6: =IF(OR($I6="",$E6=0),0,IF(OR($J6<Y$3,$I6>Y$2),0,IF($K6=0,IF(AND($I6>=Y$3,$I6<=Y$2),$E6,0),$E6*NETWORKDAYS(MAX($I6,Y$3),MIN($J6,Y$2),Data!$K$4:$K$203)/$K6))) -> 0 | Z6: =IF(OR($I6="",$E6=0),0,IF(OR($J6<Z$3,$I6>Z$2),0,IF($K6=0,IF(AND($I6>=Z$3,$I6<=Z$2),$E6,0),$E6*NETWORKDAYS(MAX($I6,Z$3),MIN($J6,Z$2),Data!$K$4:$K$203)/$K6))) -> 0 | AA6: =IF(OR($I6="",$E6=0),0,IF(OR($J6<AA$3,$I6>AA$2),0,IF($K6=0,IF(AND($I6>=AA$3,$I6<=AA$2),$E6,0),$E6*NETWORKDAYS(MAX($I6,AA$3),MIN($J6,AA$2),Data!$K$4:$K$203)/$K6))) -> 39 | AB6: =IF(OR($I6="",$E6=0),0,IF(OR($J6<AB$3,$I6>AB$2),0,IF($K6=0,IF(AND($I6>=AB$3,$I6<=AB$2),$E6,0),$E6*NETWORKDAYS(MAX($I6,AB$3),MIN($J6,AB$2),Data!$K$4:$K$203)/$K6))) -> 52 | AC6: =IF(OR($I6="",$E6=0),0,IF(OR($J6<AC$3,$I6>AC$2),0,IF($K6=0,IF(AND($I6>=AC$3,$I6<=AC$2),$E6,0),$E6*NETWORKDAYS(MAX($I6,AC$3),MIN($J6,AC$2),Data!$K$4:$K$203)/$K6))) -> 59.8 | AD6: =IF(OR($I6="",$E6=0),0,IF(OR($J6<AD$3,$I6>AD$2),0,IF($K6=0,IF(AND($I6>=AD$3,$I6<=AD$2),$E6,0),$E6*NETWORKDAYS(MAX($I6,AD$3),MIN($J6,AD$2),Data!$K$4:$K$203)/$K6))) -> 57.2 | ... AH6: =IF(OR($I6="",$E6=0),0,IF(OR($J6<AH$3,$I6>AH$2),0,IF($K6=0,IF(AND($I6>=AH$3,$I6<=AH$2),$E6,0),$E6*NETWORKDAYS(MAX($I6,AH$3),MIN($J6,AH$2),Data!$K$4:$K$203)/$K6))) -> 0 | AI6: =SUM(W6:AH6) -> 260 | AK6: Nombre de chefs de projet | AL6: =SUM(M4:M503) -> 5 | AN6: 3 | AO6: =Y$3 -> 46327 | AP6: =SUM(Y4:Y503) -> 316.14127 | AQ6: =SUMPRODUCT((Y4:Y503>0)/(COUNTIFS($EN$4:$EN$503,$EN$4:$EN$503,Y4:Y503,">0")+(Y4:Y503<=0))) -> 6 | AS6: 3 | AT6: =IF(AS6>$AL$7,"",INDEX($G$4:$G$503,MATCH(AS6,$R$4:$R$503,0))) -> DELTA | AU6: =SUMIF($V$4:$V$503,AS6,$E$4:$E$503) -> 560 | AV6: =IF($AL$4=0,0,AU6/$AL$4) -> 0.16208394 | AW6: =SUMIF($V$4:$V$503,$AS6,W$4:W$503) -> 0 | AX6: =SUMIF($V$4:$V$503,$AS6,X$4:X$503) -> 0 | AY6: =SUMIF($V$4:$V$503,$AS6,Y$4:Y$503) -> 0 | AZ6: =SUMIF($V$4:$V$503,$AS6,Z$4:Z$503) -> 0 | BA6: =SUMIF($V$4:$V$503,$AS6,AA$4:AA$503) -> 0 | BB6: =SUMIF($V$4:$V$503,$AS6,AB$4:AB$503) -> 36.734694 | BC6: =SUMIF($V$4:$V$503,$AS6,AC$4:AC$503) -> 84.489796 | BD6: =SUMIF($V$4:$V$503,$AS6,AD$4:AD$503) -> 80.816327 | ... BH6: =SUMIF($V$4:$V$503,$AS6,AH$4:AH$503) -> 47.058824 | BK6: 3 | BL6: =IF(BK6>$AL$6,"",INDEX($F$4:$F$503,MATCH(BK6,$O$4:$O$503,0))) -> Sophie Lefèvre | BM6: =IF(BL6="","",INDEX($N$4:$N$503,MATCH(BK6,$O$4:$O$503,0))) -> 750 | BO6: 3 | BP6: =IF(BO6>$AL$7,"",INDEX($G$4:$G$503,MATCH(BO6,$R$4:$R$503,0))) -> DELTA | BQ6: =IF(BP6="","",INDEX($Q$4:$Q$503,MATCH(BO6,$R$4:$R$503,0))) -> 560 | BS6: 3 | BT6: =IF(BS6>$AL$8,"",INDEX($H$4:$H$503,MATCH(BS6,$U$4:$U$503,0))) -> Modification | BU6: =IF(BT6="","",INDEX($T$4:$T$503,MATCH(BS6,$U$4:$U$503,0))) -> 535 | BW6: 3 | BX6: =IFERROR(MATCH(BW6,$EQ$4:$EQ$503,0),"") -> 11 | BZ6: =IF(D6=1,IF(TRIM(INDEX(Charge!$K:$K,ROW()))<>"",TRIM(INDEX(Charge!$K:$K,ROW())),IF(TRIM(INDEX(Charge!$L:$L,ROW()))<>"",TRIM(INDEX(Charge!$L:$L,ROW())),"(non affecté)")),"") -> Emma Faure | CA6: =IF(AND($CD$4<>"",BZ6=$CD$4),COUNTIFS($BZ$4:$BZ$503,$CD$4,$L$4:$L$503,"<"&L6)+1,"") | CC6: Capacité mensuelle (h) | CD6: =IF(CD4="",0,IF(CD5>0,IF(ISNUMBER(INDEX(Data!$F:$F,CD5+3)),INDEX(Data!$F:$F,CD5+3),p_HeuresETP),IF(CD24>0,IF(ISNUMBER(INDEX(Data!$I:$I,CD24+3)),INDEX(Data!$I:$I,CD24+3),p_HeuresETP),p_HeuresETP))) -> 120 | CF6: 3 | CG6: =Y$3 -> 46327 | CH6: =IF($CD$4="",0,$CD$7) -> 20 | CI6: =IF($CD$4="",0,SUMIF($BZ$4:$BZ$503,$CD$4,Y$4:Y$503)) -> 101.9697 | CJ6: =CH6+CI6 -> 121.9697 | CK6: =IF($CD$4="",0,$CD$6) -> 120 | CL6: =IF(CN6<0,MAX(0,MIN(CI6,CK6-CH6)),CI6) -> 100 | CM6: =CI6-CL6 -> 1.969697 | CN6: =CK6-CP6 -> -2 | CO6: =IF(CK6<=0,IF(CP6>0,9.99,0),CP6/CK6) -> 1.0166667 | CP6: =ROUND(CJ6,0) -> 122 | CQ6: =IF(CN6<0,CF6,"") -> 3 | CS6: 3 | CT6: =IF(OR(FA6="",COUNTIF($FA$4:FA5,FA6)>0),"",FA6) -> Hugo Mercier | CU6: =IF(CT6="","",IF(FB6="Interne",IF(ISNUMBER(INDEX(Data!$F:$F,6)),INDEX(Data!$F:$F,6),p_HeuresETP),IF(ISNUMBER(INDEX(Data!$I:$I,6-$CD$23)),INDEX(Data!$I:$I,6-$CD$23),p_HeuresETP))) -> 120 | CV6: =IF(CT6="","",IF(FB6="Interne",IF(ISNUMBER(INDEX(Data!$G:$G,6)),INDEX(Data!$G:$G,6),p_ChargeFixe),IF(ISNUMBER(INDEX(Data!$J:$J,6-$CD$23)),INDEX(Data!$J:$J,6-$CD$23),p_ChargeFixe))) -> 20 | CW6: =IF($CT6="","",SUMIF($BZ$4:$BZ$503,$CT6,W$4:W$503)) -> 0 | CX6: =IF($CT6="","",SUMIF($BZ$4:$BZ$503,$CT6,X$4:X$503)) -> 45 | CY6: =IF($CT6="","",SUMIF($BZ$4:$BZ$503,$CT6,Y$4:Y$503)) -> 63 | CZ6: =IF($CT6="","",SUMIF($BZ$4:$BZ$503,$CT6,Z$4:Z$503)) -> 42 | DA6: =IF($CT6="","",SUMIF($BZ$4:$BZ$503,$CT6,AA$4:AA$503)) -> 0 | DB6: =IF($CT6="","",SUMIF($BZ$4:$BZ$503,$CT6,AB$4:AB$503)) -> 12.244898 | DC6: =IF($CT6="","",SUMIF($BZ$4:$BZ$503,$CT6,AC$4:AC$503)) -> 55.246599 | DD6: =IF($CT6="","",SUMIF($BZ$4:$BZ$503,$CT6,AD$4:AD$503)) -> 72.772109 | ... DH6: =IF($CT6="","",SUMIF($BZ$4:$BZ$503,$CT6,AH$4:AH$503)) -> 45.833333 | DI6: =IF($CT6="","",IF($CU6<=0,IF(ROUND($CV6+CW6,0)>0,9.99,0),ROUND($CV6+CW6,0)/$CU6)) -> 0.16666667 | DJ6: =IF($CT6="","",IF($CU6<=0,IF(ROUND($CV6+CX6,0)>0,9.99,0),ROUND($CV6+CX6,0)/$CU6)) -> 0.54166667 | DK6: =IF($CT6="","",IF($CU6<=0,IF(ROUND($CV6+CY6,0)>0,9.99,0),ROUND($CV6+CY6,0)/$CU6)) -> 0.69166667 | DL6: =IF($CT6="","",IF($CU6<=0,IF(ROUND($CV6+CZ6,0)>0,9.99,0),ROUND($CV6+CZ6,0)/$CU6)) -> 0.51666667 | DM6: =IF($CT6="","",IF($CU6<=0,IF(ROUND($CV6+DA6,0)>0,9.99,0),ROUND($CV6+DA6,0)/$CU6)) -> 0.16666667 | DN6: =IF($CT6="","",IF($CU6<=0,IF(ROUND($CV6+DB6,0)>0,9.99,0),ROUND($CV6+DB6,0)/$CU6)) -> 0.26666667 | DO6: =IF($CT6="","",IF($CU6<=0,IF(ROUND($CV6+DC6,0)>0,9.99,0),ROUND($CV6+DC6,0)/$CU6)) -> 0.625 | DP6: =IF($CT6="","",IF($CU6<=0,IF(ROUND($CV6+DD6,0)>0,9.99,0),ROUND($CV6+DD6,0)/$CU6)) -> 0.775 | ... DT6: =IF($CT6="","",IF($CU6<=0,IF(ROUND($CV6+DH6,0)>0,9.99,0),ROUND($CV6+DH6,0)/$CU6)) -> 0.55 | DU6: =IF(CT6="","",MAX(DI6:DT6)) -> 0.775 | DV6: =IF(CT6="","",SUM(CW6:DH6)) -> 524.16667 | DX6: 3 | DY6: =IFERROR(MATCH(DX6,$CA$4:$CA$503,0),"") | DZ6: =IF(DY6="","",INDEX(Charge!$B:$B,DY6+3)&"") | EA6: =IF(DY6="","",INDEX(Charge!$C:$C,DY6+3)&"") | EB6: =IF(DY6="","",INDEX(Charge!$D:$D,DY6+3)&"") | EC6: =IF(DY6="","",INDEX(Charge!$A:$A,DY6+3)&"") | ED6: =IF(DY6="","",INDEX($E$4:$E$503,DY6)) | EE6: =IF(DY6="","",INDEX($AI$4:$AI$503,DY6)) | EF6: =IF(DY6="","",IF(ISNUMBER(INDEX(Charge!$N:$N,DY6+3)),INDEX(Charge!$N:$N,DY6+3),"—")) | EG6: =IF(DY6="","",IF(ISNUMBER(INDEX(Charge!$F:$F,DY6+3)),INDEX(Charge!$F:$F,DY6+3),"—")) | EH6: =IF(DY6="","",INDEX($C$4:$C$503,DY6)) | EJ6: =TRIM(INDEX(Data!$E:$E,ROW())) -> Hugo Mercier | EK6: =TRIM(INDEX(Data!$H:$H,ROW())) -> Karim Haddad | EM6: =IF(D6=1,IF(TRIM(INDEX(Charge!$K:$K,ROW()))<>"","Interne",IF(TRIM(INDEX(Charge!$L:$L,ROW()))<>"","Externe","Non affecté")),"") -> Interne | EN6: =IF(D6=1,LEFT(SUBSTITUTE(SUBSTITUTE(SUBSTITUTE(TRIM(SUBSTITUTE(INDEX(Charge!$B:$B,ROW()),CHAR(160)," "))&" | "&TRIM(SUBSTITUTE(INDEX(Charge!$C:$C,ROW()),CHAR(160)," "))&" | "&TRIM(SUBSTITUTE(INDEX(Charge!$D:$D,ROW()),CHAR(160)," ")),"~","-"),"*","+"),"?","!"),240),"") -> ATLAS | Lot 2 – Carénage | Capots latéraux | EO6: =IF(EN6="",0,IF(COUNTIF($EN$4:EN6,EN6)=1,1,0)) -> 1 | EP6: =IF(EO6=1,ROUND(SUMIF($EN$4:$EN$503,EN6,$E$4:$E$503),2),"") -> 260 | EQ6: =IF(EO6=1,COUNTIFS($EO$4:$EO$503,1,$EP$4:$EP$503,">"&EP6)+COUNTIFS($EO$4:EO6,1,$EP$4:EP6,EP6),"") -> 5 | ER6: =IF(EO6=1,COUNTIFS($EN$4:$EN$503,EN6,$EM$4:$EM$503,"Interne",$FE$4:$FE$503,1),"") -> 1 | ES6: =IF(EO6=1,COUNTIFS($EN$4:$EN$503,EN6,$EM$4:$EM$503,"Externe",$FE$4:$FE$503,1),"") -> 0 | ET6: =IF(EO6=1,IF(ER6+ES6=0,"à affecter",IF(ER6=0,ES6&" ext.",(ER6+ES6)&IF(ES6>0," dont "&ES6&" ext.",""))&IF(COUNTIFS($EN$4:$EN$503,EN6,$EM$4:$EM$503,"Non affecté")>0," + à affecter","")),"") -> 1 | EU6: =IF(EO6=1,IF(EP6>0,SUMPRODUCT(($EN$4:$EN$503=EN6)*$E$4:$E$503*$C$4:$C$503)/EP6,AVERAGEIF($EN$4:$EN$503,EN6,$C$4:$C$503)),"") -> 0 | EV6: =IF(ISNUMBER(I6),I6,2958465) -> 46398 | EW6: =IF(EO6=1,SUMPRODUCT(MIN(($EN$4:$EN$503=EN6)*$EV$4:$EV$503+($EN$4:$EN$503<>EN6)*2958465)),"") -> 46398 | EX6: =IF(AND(D6=1,ISNUMBER(INDEX(Charge!$F:$F,ROW()))),INDEX(Charge!$F:$F,ROW()),0) -> 46535 | EY6: =IF(EO6=1,SUMPRODUCT(MAX(($EN$4:$EN$503=EN6)*$EX$4:$EX$503)),"") -> 46535 | FA6: =IF(3<=$CD$23,INDEX($EJ$4:$EJ$203,3),IF(3-$CD$23<=$CD$26,INDEX($EK$4:$EK$203,3-$CD$23),"")) -> Hugo Mercier | FB6: =IF(FA6="","",IF(3<=$CD$23,"Interne","Externe")) -> Interne | FD6: =IF(AND(B6=1,TRIM(INDEX(Charge!$K:$K,ROW()))<>"",TRIM(INDEX(Charge!$L:$L,ROW()))<>""),1,0) -> 0 | FE6: =IF(OR(EN6="",BZ6="(non affecté)"),0,IF(COUNTIFS($EN$4:EN6,EN6,$BZ$4:BZ6,BZ6)=1,1,0)) -> 1
A7: =ROW() -> 7 | B7: =IF(TRIM(INDEX(Charge!$B:$B,ROW()))<>"",1,0) -> 1 | C7: =IF(B7=1,MIN(1,MAX(0,N(INDEX(Charge!$O:$O,ROW())))),0) -> 0 | D7: =IF(B7=1,IF(OR(p_Perimetre="Tous les projets",C7<1),1,0),0) -> 1 | E7: =IF(D7=1,MAX(0,N(INDEX(Charge!$M:$M,ROW()))),0) -> 180 | F7: =IF(D7=1,IF(TRIM(INDEX(Charge!$A:$A,ROW()))="","(non renseigné)",TRIM(INDEX(Charge!$A:$A,ROW()))),"") -> Julie Martin | G7: =IF(D7=1,TRIM(INDEX(Charge!$B:$B,ROW())),"") -> ATLAS | H7: =IF(D7=1,IF(TRIM(INDEX(Charge!$E:$E,ROW()))="","(non renseigné)",TRIM(INDEX(Charge!$E:$E,ROW()))),"") -> Industrialisation | I7: =IF(AND(D7=1,ISNUMBER(INDEX(Charge!$N:$N,ROW()))),INDEX(Charge!$N:$N,ROW()),"") -> 46482 | J7: =IF(I7="","",IF(AND(p_Repartition="Lissée jusqu'à la date de besoin",ISNUMBER(INDEX(Charge!$F:$F,ROW()))),IF(INDEX(Charge!$F:$F,ROW())>=I7,INDEX(Charge!$F:$F,ROW()),I7),I7)) -> 46598 | K7: =IF(I7="","",NETWORKDAYS(I7,J7,Data!$K$4:$K$203)) -> 85 | L7: =IF(D7=1,COUNTIFS($D$4:$D$503,1,$E$4:$E$503,">"&E7)+COUNTIFS($D$4:$D7,1,$E$4:$E7,E7),"") -> 7 | M7: =IF(F7="",0,IF(COUNTIF($F$4:F7,F7)=1,1,0)) -> 0 | N7: =IF(M7=1,ROUND(SUMIF($F$4:$F$503,F7,$E$4:$E$503),2),"") | O7: =IF(M7=1,COUNTIFS($M$4:$M$503,1,$N$4:$N$503,">"&N7)+COUNTIFS($M$4:M7,1,$N$4:N7,N7),"") | P7: =IF(G7="",0,IF(COUNTIF($G$4:G7,G7)=1,1,0)) -> 0 | Q7: =IF(P7=1,ROUND(SUMIF($G$4:$G$503,G7,$E$4:$E$503),2),"") | R7: =IF(P7=1,COUNTIFS($P$4:$P$503,1,$Q$4:$Q$503,">"&Q7)+COUNTIFS($P$4:P7,1,$Q$4:Q7,Q7),"") | S7: =IF(H7="",0,IF(COUNTIF($H$4:H7,H7)=1,1,0)) -> 1 | T7: =IF(S7=1,ROUND(SUMIF($H$4:$H$503,H7,$E$4:$E$503),2),"") -> 540 | U7: =IF(S7=1,COUNTIFS($S$4:$S$503,1,$T$4:$T$503,">"&T7)+COUNTIFS($S$4:S7,1,$T$4:T7,T7),"") -> 2 | V7: =IF(D7=1,MIN(INDEX($R$4:$R$503,MATCH(G7,$G$4:$G$503,0)),IF($AL$7>9,9,999)),"") -> 1 | W7: =IF(OR($I7="",$E7=0),0,IF(OR($J7<W$3,$I7>W$2),0,IF($K7=0,IF(AND($I7>=W$3,$I7<=W$2),$E7,0),$E7*NETWORKDAYS(MAX($I7,W$3),MIN($J7,W$2),Data!$K$4:$K$203)/$K7))) -> 0 | X7: =IF(OR($I7="",$E7=0),0,IF(OR($J7<X$3,$I7>X$2),0,IF($K7=0,IF(AND($I7>=X$3,$I7<=X$2),$E7,0),$E7*NETWORKDAYS(MAX($I7,X$3),MIN($J7,X$2),Data!$K$4:$K$203)/$K7))) -> 0 | Y7: =IF(OR($I7="",$E7=0),0,IF(OR($J7<Y$3,$I7>Y$2),0,IF($K7=0,IF(AND($I7>=Y$3,$I7<=Y$2),$E7,0),$E7*NETWORKDAYS(MAX($I7,Y$3),MIN($J7,Y$2),Data!$K$4:$K$203)/$K7))) -> 0 | Z7: =IF(OR($I7="",$E7=0),0,IF(OR($J7<Z$3,$I7>Z$2),0,IF($K7=0,IF(AND($I7>=Z$3,$I7<=Z$2),$E7,0),$E7*NETWORKDAYS(MAX($I7,Z$3),MIN($J7,Z$2),Data!$K$4:$K$203)/$K7))) -> 0 | AA7: =IF(OR($I7="",$E7=0),0,IF(OR($J7<AA$3,$I7>AA$2),0,IF($K7=0,IF(AND($I7>=AA$3,$I7<=AA$2),$E7,0),$E7*NETWORKDAYS(MAX($I7,AA$3),MIN($J7,AA$2),Data!$K$4:$K$203)/$K7))) -> 0 | AB7: =IF(OR($I7="",$E7=0),0,IF(OR($J7<AB$3,$I7>AB$2),0,IF($K7=0,IF(AND($I7>=AB$3,$I7<=AB$2),$E7,0),$E7*NETWORKDAYS(MAX($I7,AB$3),MIN($J7,AB$2),Data!$K$4:$K$203)/$K7))) -> 0 | AC7: =IF(OR($I7="",$E7=0),0,IF(OR($J7<AC$3,$I7>AC$2),0,IF($K7=0,IF(AND($I7>=AC$3,$I7<=AC$2),$E7,0),$E7*NETWORKDAYS(MAX($I7,AC$3),MIN($J7,AC$2),Data!$K$4:$K$203)/$K7))) -> 0 | AD7: =IF(OR($I7="",$E7=0),0,IF(OR($J7<AD$3,$I7>AD$2),0,IF($K7=0,IF(AND($I7>=AD$3,$I7<=AD$2),$E7,0),$E7*NETWORKDAYS(MAX($I7,AD$3),MIN($J7,AD$2),Data!$K$4:$K$203)/$K7))) -> 42.352941 | ... AH7: =IF(OR($I7="",$E7=0),0,IF(OR($J7<AH$3,$I7>AH$2),0,IF($K7=0,IF(AND($I7>=AH$3,$I7<=AH$2),$E7,0),$E7*NETWORKDAYS(MAX($I7,AH$3),MIN($J7,AH$2),Data!$K$4:$K$203)/$K7))) -> 0 | AI7: =SUM(W7:AH7) -> 180 | AK7: Nombre de projets | AL7: =SUM(P4:P503) -> 7 | AN7: 4 | AO7: =Z$3 -> 46357 | AP7: =SUM(Z4:Z503) -> 381.9518 | AQ7: =SUMPRODUCT((Z4:Z503>0)/(COUNTIFS($EN$4:$EN$503,$EN$4:$EN$503,Z4:Z503,">0")+(Z4:Z503<=0))) -> 6 | AS7: 4 | AT7: =IF(AS7>$AL$7,"",INDEX($G$4:$G$503,MATCH(AS7,$R$4:$R$503,0))) -> PÉGASE | AU7: =SUMIF($V$4:$V$503,AS7,$E$4:$E$503) -> 550 | AV7: =IF($AL$4=0,0,AU7/$AL$4) -> 0.15918958 | AW7: =SUMIF($V$4:$V$503,$AS7,W$4:W$503) -> 0 | AX7: =SUMIF($V$4:$V$503,$AS7,X$4:X$503) -> 0 | AY7: =SUMIF($V$4:$V$503,$AS7,Y$4:Y$503) -> 38.5 | AZ7: =SUMIF($V$4:$V$503,$AS7,Z$4:Z$503) -> 31.5 | BA7: =SUMIF($V$4:$V$503,$AS7,AA$4:AA$503) -> 0 | BB7: =SUMIF($V$4:$V$503,$AS7,AB$4:AB$503) -> 0 | BC7: =SUMIF($V$4:$V$503,$AS7,AC$4:AC$503) -> 43.333333 | BD7: =SUMIF($V$4:$V$503,$AS7,AD$4:AD$503) -> 73.333333 | ... BH7: =SUMIF($V$4:$V$503,$AS7,AH$4:AH$503) -> 73.333333 | BK7: 4 | BL7: =IF(BK7>$AL$6,"",INDEX($F$4:$F$503,MATCH(BK7,$O$4:$O$503,0))) -> Camille Laurent | BM7: =IF(BL7="","",INDEX($N$4:$N$503,MATCH(BK7,$O$4:$O$503,0))) -> 675 | BO7: 4 | BP7: =IF(BO7>$AL$7,"",INDEX($G$4:$G$503,MATCH(BO7,$R$4:$R$503,0))) -> PÉGASE | BQ7: =IF(BP7="","",INDEX($Q$4:$Q$503,MATCH(BO7,$R$4:$R$503,0))) -> 550 | BS7: 4 | BT7: =IF(BS7>$AL$8,"",IF($AL$8>4,"+ "&($AL$8-3)&" autres types",INDEX($H$4:$H$503,MATCH(BS7,$U$4:$U$503,0)))) -> + 2 autres types | BU7: =IF(BT7="","",IF($AL$8>4,$AL$4-SUM(BU4:BU6),INDEX($T$4:$T$503,MATCH(BS7,$U$4:$U$503,0)))) -> 350 | BW7: 4 | BX7: =IFERROR(MATCH(BW7,$EQ$4:$EQ$503,0),"") -> 5 | BZ7: =IF(D7=1,IF(TRIM(INDEX(Charge!$K:$K,ROW()))<>"",TRIM(INDEX(Charge!$K:$K,ROW())),IF(TRIM(INDEX(Charge!$L:$L,ROW()))<>"",TRIM(INDEX(Charge!$L:$L,ROW())),"(non affecté)")),"") -> Inès Morel | CA7: =IF(AND($CD$4<>"",BZ7=$CD$4),COUNTIFS($BZ$4:$BZ$503,$CD$4,$L$4:$L$503,"<"&L7)+1,"") | CC7: Charge fixe hors projet (h/mois) | CD7: =IF(CD4="",0,IF(CD5>0,IF(ISNUMBER(INDEX(Data!$G:$G,CD5+3)),INDEX(Data!$G:$G,CD5+3),p_ChargeFixe),IF(CD24>0,IF(ISNUMBER(INDEX(Data!$J:$J,CD24+3)),INDEX(Data!$J:$J,CD24+3),p_ChargeFixe),p_ChargeFixe))) -> 20 | CF7: 4 | CG7: =Z$3 -> 46357 | CH7: =IF($CD$4="",0,$CD$7) -> 20 | CI7: =IF($CD$4="",0,SUMIF($BZ$4:$BZ$503,$CD$4,Z$4:Z$503)) -> 63.888889 | CJ7: =CH7+CI7 -> 83.888889 | CK7: =IF($CD$4="",0,$CD$6) -> 120 | CL7: =IF(CN7<0,MAX(0,MIN(CI7,CK7-CH7)),CI7) -> 63.888889 | CM7: =CI7-CL7 -> 0 | CN7: =CK7-CP7 -> 36 | CO7: =IF(CK7<=0,IF(CP7>0,9.99,0),CP7/CK7) -> 0.7 | CP7: =ROUND(CJ7,0) -> 84 | CQ7: =IF(CN7<0,CF7,"") | CS7: 4 | CT7: =IF(OR(FA7="",COUNTIF($FA$4:FA6,FA7)>0),"",FA7) -> Léa Chevalier | CU7: =IF(CT7="","",IF(FB7="Interne",IF(ISNUMBER(INDEX(Data!$F:$F,7)),INDEX(Data!$F:$F,7),p_HeuresETP),IF(ISNUMBER(INDEX(Data!$I:$I,7-$CD$23)),INDEX(Data!$I:$I,7-$CD$23),p_HeuresETP))) -> 96 | CV7: =IF(CT7="","",IF(FB7="Interne",IF(ISNUMBER(INDEX(Data!$G:$G,7)),INDEX(Data!$G:$G,7),p_ChargeFixe),IF(ISNUMBER(INDEX(Data!$J:$J,7-$CD$23)),INDEX(Data!$J:$J,7-$CD$23),p_ChargeFixe))) -> 20 | CW7: =IF($CT7="","",SUMIF($BZ$4:$BZ$503,$CT7,W$4:W$503)) -> 0 | CX7: =IF($CT7="","",SUMIF($BZ$4:$BZ$503,$CT7,X$4:X$503)) -> 72.941176 | CY7: =IF($CT7="","",SUMIF($BZ$4:$BZ$503,$CT7,Y$4:Y$503)) -> 115.08824 | CZ7: =IF($CT7="","",SUMIF($BZ$4:$BZ$503,$CT7,Z$4:Z$503)) -> 115.38235 | DA7: =IF($CT7="","",SUMIF($BZ$4:$BZ$503,$CT7,AA$4:AA$503)) -> 76.588235 | DB7: =IF($CT7="","",SUMIF($BZ$4:$BZ$503,$CT7,AB$4:AB$503)) -> 67.692308 | DC7: =IF($CT7="","",SUMIF($BZ$4:$BZ$503,$CT7,AC$4:AC$503)) -> 77.846154 | DD7: =IF($CT7="","",SUMIF($BZ$4:$BZ$503,$CT7,AD$4:AD$503)) -> 74.461538 | ... DH7: =IF($CT7="","",SUMIF($BZ$4:$BZ$503,$CT7,AH$4:AH$503)) -> 0 | DI7: =IF($CT7="","",IF($CU7<=0,IF(ROUND($CV7+CW7,0)>0,9.99,0),ROUND($CV7+CW7,0)/$CU7)) -> 0.20833333 | DJ7: =IF($CT7="","",IF($CU7<=0,IF(ROUND($CV7+CX7,0)>0,9.99,0),ROUND($CV7+CX7,0)/$CU7)) -> 0.96875 | DK7: =IF($CT7="","",IF($CU7<=0,IF(ROUND($CV7+CY7,0)>0,9.99,0),ROUND($CV7+CY7,0)/$CU7)) -> 1.40625 | DL7: =IF($CT7="","",IF($CU7<=0,IF(ROUND($CV7+CZ7,0)>0,9.99,0),ROUND($CV7+CZ7,0)/$CU7)) -> 1.40625 | DM7: =IF($CT7="","",IF($CU7<=0,IF(ROUND($CV7+DA7,0)>0,9.99,0),ROUND($CV7+DA7,0)/$CU7)) -> 1.0104167 | DN7: =IF($CT7="","",IF($CU7<=0,IF(ROUND($CV7+DB7,0)>0,9.99,0),ROUND($CV7+DB7,0)/$CU7)) -> 0.91666667 | DO7: =IF($CT7="","",IF($CU7<=0,IF(ROUND($CV7+DC7,0)>0,9.99,0),ROUND($CV7+DC7,0)/$CU7)) -> 1.0208333 | DP7: =IF($CT7="","",IF($CU7<=0,IF(ROUND($CV7+DD7,0)>0,9.99,0),ROUND($CV7+DD7,0)/$CU7)) -> 0.97916667 | ... DT7: =IF($CT7="","",IF($CU7<=0,IF(ROUND($CV7+DH7,0)>0,9.99,0),ROUND($CV7+DH7,0)/$CU7)) -> 0.20833333 | DU7: =IF(CT7="","",MAX(DI7:DT7)) -> 1.40625 | DV7: =IF(CT7="","",SUM(CW7:DH7)) -> 600 | DX7: 4 | DY7: =IFERROR(MATCH(DX7,$CA$4:$CA$503,0),"") | DZ7: =IF(DY7="","",INDEX(Charge!$B:$B,DY7+3)&"") | EA7: =IF(DY7="","",INDEX(Charge!$C:$C,DY7+3)&"") | EB7: =IF(DY7="","",INDEX(Charge!$D:$D,DY7+3)&"") | EC7: =IF(DY7="","",INDEX(Charge!$A:$A,DY7+3)&"") | ED7: =IF(DY7="","",INDEX($E$4:$E$503,DY7)) | EE7: =IF(DY7="","",INDEX($AI$4:$AI$503,DY7)) | EF7: =IF(DY7="","",IF(ISNUMBER(INDEX(Charge!$N:$N,DY7+3)),INDEX(Charge!$N:$N,DY7+3),"—")) | EG7: =IF(DY7="","",IF(ISNUMBER(INDEX(Charge!$F:$F,DY7+3)),INDEX(Charge!$F:$F,DY7+3),"—")) | EH7: =IF(DY7="","",INDEX($C$4:$C$503,DY7)) | EJ7: =TRIM(INDEX(Data!$E:$E,ROW())) -> Léa Chevalier | EK7: =TRIM(INDEX(Data!$H:$H,ROW())) | EM7: =IF(D7=1,IF(TRIM(INDEX(Charge!$K:$K,ROW()))<>"","Interne",IF(TRIM(INDEX(Charge!$L:$L,ROW()))<>"","Externe","Non affecté")),"") -> Externe | EN7: =IF(D7=1,LEFT(SUBSTITUTE(SUBSTITUTE(SUBSTITUTE(TRIM(SUBSTITUTE(INDEX(Charge!$B:$B,ROW()),CHAR(160)," "))&" | "&TRIM(SUBSTITUTE(INDEX(Charge!$C:$C,ROW()),CHAR(160)," "))&" | "&TRIM(SUBSTITUTE(INDEX(Charge!$D:$D,ROW()),CHAR(160)," ")),"~","-"),"*","+"),"?","!"),240),"") -> ATLAS | Lot 3 – Intégration | Faisceau électrique | EO7: =IF(EN7="",0,IF(COUNTIF($EN$4:EN7,EN7)=1,1,0)) -> 1 | EP7: =IF(EO7=1,ROUND(SUMIF($EN$4:$EN$503,EN7,$E$4:$E$503),2),"") -> 180 | EQ7: =IF(EO7=1,COUNTIFS($EO$4:$EO$503,1,$EP$4:$EP$503,">"&EP7)+COUNTIFS($EO$4:EO7,1,$EP$4:EP7,EP7),"") -> 9 | ER7: =IF(EO7=1,COUNTIFS($EN$4:$EN$503,EN7,$EM$4:$EM$503,"Interne",$FE$4:$FE$503,1),"") -> 0 | ES7: =IF(EO7=1,COUNTIFS($EN$4:$EN$503,EN7,$EM$4:$EM$503,"Externe",$FE$4:$FE$503,1),"") -> 1 | ET7: =IF(EO7=1,IF(ER7+ES7=0,"à affecter",IF(ER7=0,ES7&" ext.",(ER7+ES7)&IF(ES7>0," dont "&ES7&" ext.",""))&IF(COUNTIFS($EN$4:$EN$503,EN7,$EM$4:$EM$503,"Non affecté")>0," + à affecter","")),"") -> 1 ext. | EU7: =IF(EO7=1,IF(EP7>0,SUMPRODUCT(($EN$4:$EN$503=EN7)*$E$4:$E$503*$C$4:$C$503)/EP7,AVERAGEIF($EN$4:$EN$503,EN7,$C$4:$C$503)),"") -> 0 | EV7: =IF(ISNUMBER(I7),I7,2958465) -> 46482 | EW7: =IF(EO7=1,SUMPRODUCT(MIN(($EN$4:$EN$503=EN7)*$EV$4:$EV$503+($EN$4:$EN$503<>EN7)*2958465)),"") -> 46482 | EX7: =IF(AND(D7=1,ISNUMBER(INDEX(Charge!$F:$F,ROW()))),INDEX(Charge!$F:$F,ROW()),0) -> 46598 | EY7: =IF(EO7=1,SUMPRODUCT(MAX(($EN$4:$EN$503=EN7)*$EX$4:$EX$503)),"") -> 46598 | FA7: =IF(4<=$CD$23,INDEX($EJ$4:$EJ$203,4),IF(4-$CD$23<=$CD$26,INDEX($EK$4:$EK$203,4-$CD$23),"")) -> Léa Chevalier | FB7: =IF(FA7="","",IF(4<=$CD$23,"Interne","Externe")) -> Interne | FD7: =IF(AND(B7=1,TRIM(INDEX(Charge!$K:$K,ROW()))<>"",TRIM(INDEX(Charge!$L:$L,ROW()))<>""),1,0) -> 0 | FE7: =IF(OR(EN7="",BZ7="(non affecté)"),0,IF(COUNTIFS($EN$4:EN7,EN7,$BZ$4:BZ7,BZ7)=1,1,0)) -> 1
A8: =ROW() -> 8 | B8: =IF(TRIM(INDEX(Charge!$B:$B,ROW()))<>"",1,0) -> 1 | C8: =IF(B8=1,MIN(1,MAX(0,N(INDEX(Charge!$O:$O,ROW())))),0) -> 0.35 | D8: =IF(B8=1,IF(OR(p_Perimetre="Tous les projets",C8<1),1,0),0) -> 1 | E8: =IF(D8=1,MAX(0,N(INDEX(Charge!$M:$M,ROW()))),0) -> 310 | F8: =IF(D8=1,IF(TRIM(INDEX(Charge!$A:$A,ROW()))="","(non renseigné)",TRIM(INDEX(Charge!$A:$A,ROW()))),"") -> Thomas Bernard | G8: =IF(D8=1,TRIM(INDEX(Charge!$B:$B,ROW())),"") -> BORÉAL | H8: =IF(D8=1,IF(TRIM(INDEX(Charge!$E:$E,ROW()))="","(non renseigné)",TRIM(INDEX(Charge!$E:$E,ROW()))),"") -> Étude de conception | I8: =IF(AND(D8=1,ISNUMBER(INDEX(Charge!$N:$N,ROW()))),INDEX(Charge!$N:$N,ROW()),"") -> 46300 | J8: =IF(I8="","",IF(AND(p_Repartition="Lissée jusqu'à la date de besoin",ISNUMBER(INDEX(Charge!$F:$F,ROW()))),IF(INDEX(Charge!$F:$F,ROW())>=I8,INDEX(Charge!$F:$F,ROW()),I8),I8)) -> 46416 | K8: =IF(I8="","",NETWORKDAYS(I8,J8,Data!$K$4:$K$203)) -> 85 | L8: =IF(D8=1,COUNTIFS($D$4:$D$503,1,$E$4:$E$503,">"&E8)+COUNTIFS($D$4:$D8,1,$E$4:$E8,E8),"") -> 1 | M8: =IF(F8="",0,IF(COUNTIF($F$4:F8,F8)=1,1,0)) -> 1 | N8: =IF(M8=1,ROUND(SUMIF($F$4:$F$503,F8,$E$4:$E$503),2),"") -> 820 | O8: =IF(M8=1,COUNTIFS($M$4:$M$503,1,$N$4:$N$503,">"&N8)+COUNTIFS($M$4:M8,1,$N$4:N8,N8),"") -> 2 | P8: =IF(G8="",0,IF(COUNTIF($G$4:G8,G8)=1,1,0)) -> 1 | Q8: =IF(P8=1,ROUND(SUMIF($G$4:$G$503,G8,$E$4:$E$503),2),"") -> 620 | R8: =IF(P8=1,COUNTIFS($P$4:$P$503,1,$Q$4:$Q$503,">"&Q8)+COUNTIFS($P$4:P8,1,$Q$4:Q8,Q8),"") -> 2 | S8: =IF(H8="",0,IF(COUNTIF($H$4:H8,H8)=1,1,0)) -> 0 | T8: =IF(S8=1,ROUND(SUMIF($H$4:$H$503,H8,$E$4:$E$503),2),"") | U8: =IF(S8=1,COUNTIFS($S$4:$S$503,1,$T$4:$T$503,">"&T8)+COUNTIFS($S$4:S8,1,$T$4:T8,T8),"") | V8: =IF(D8=1,MIN(INDEX($R$4:$R$503,MATCH(G8,$G$4:$G$503,0)),IF($AL$7>9,9,999)),"") -> 2 | W8: =IF(OR($I8="",$E8=0),0,IF(OR($J8<W$3,$I8>W$2),0,IF($K8=0,IF(AND($I8>=W$3,$I8<=W$2),$E8,0),$E8*NETWORKDAYS(MAX($I8,W$3),MIN($J8,W$2),Data!$K$4:$K$203)/$K8))) -> 0 | X8: =IF(OR($I8="",$E8=0),0,IF(OR($J8<X$3,$I8>X$2),0,IF($K8=0,IF(AND($I8>=X$3,$I8<=X$2),$E8,0),$E8*NETWORKDAYS(MAX($I8,X$3),MIN($J8,X$2),Data!$K$4:$K$203)/$K8))) -> 72.941176 | Y8: =IF(OR($I8="",$E8=0),0,IF(OR($J8<Y$3,$I8>Y$2),0,IF($K8=0,IF(AND($I8>=Y$3,$I8<=Y$2),$E8,0),$E8*NETWORKDAYS(MAX($I8,Y$3),MIN($J8,Y$2),Data!$K$4:$K$203)/$K8))) -> 76.588235 | Z8: =IF(OR($I8="",$E8=0),0,IF(OR($J8<Z$3,$I8>Z$2),0,IF($K8=0,IF(AND($I8>=Z$3,$I8<=Z$2),$E8,0),$E8*NETWORKDAYS(MAX($I8,Z$3),MIN($J8,Z$2),Data!$K$4:$K$203)/$K8))) -> 83.882353 | AA8: =IF(OR($I8="",$E8=0),0,IF(OR($J8<AA$3,$I8>AA$2),0,IF($K8=0,IF(AND($I8>=AA$3,$I8<=AA$2),$E8,0),$E8*NETWORKDAYS(MAX($I8,AA$3),MIN($J8,AA$2),Data!$K$4:$K$203)/$K8))) -> 76.588235 | AB8: =IF(OR($I8="",$E8=0),0,IF(OR($J8<AB$3,$I8>AB$2),0,IF($K8=0,IF(AND($I8>=AB$3,$I8<=AB$2),$E8,0),$E8*NETWORKDAYS(MAX($I8,AB$3),MIN($J8,AB$2),Data!$K$4:$K$203)/$K8))) -> 0 | AC8: =IF(OR($I8="",$E8=0),0,IF(OR($J8<AC$3,$I8>AC$2),0,IF($K8=0,IF(AND($I8>=AC$3,$I8<=AC$2),$E8,0),$E8*NETWORKDAYS(MAX($I8,AC$3),MIN($J8,AC$2),Data!$K$4:$K$203)/$K8))) -> 0 | AD8: =IF(OR($I8="",$E8=0),0,IF(OR($J8<AD$3,$I8>AD$2),0,IF($K8=0,IF(AND($I8>=AD$3,$I8<=AD$2),$E8,0),$E8*NETWORKDAYS(MAX($I8,AD$3),MIN($J8,AD$2),Data!$K$4:$K$203)/$K8))) -> 0 | ... AH8: =IF(OR($I8="",$E8=0),0,IF(OR($J8<AH$3,$I8>AH$2),0,IF($K8=0,IF(AND($I8>=AH$3,$I8<=AH$2),$E8,0),$E8*NETWORKDAYS(MAX($I8,AH$3),MIN($J8,AH$2),Data!$K$4:$K$203)/$K8))) -> 0 | AI8: =SUM(W8:AH8) -> 310 | AK8: Nombre de types | AL8: =SUM(S4:S503) -> 5 | AN8: 5 | AO8: =AA$3 -> 46388 | AP8: =SUM(AA4:AA503) -> 321.33112 | AQ8: =SUMPRODUCT((AA4:AA503>0)/(COUNTIFS($EN$4:$EN$503,$EN$4:$EN$503,AA4:AA503,">0")+(AA4:AA503<=0))) -> 6 | AS8: 5 | AT8: =IF(AS8>$AL$7,"",INDEX($G$4:$G$503,MATCH(AS8,$R$4:$R$503,0))) -> CASSIOPÉE | AU8: =SUMIF($V$4:$V$503,AS8,$E$4:$E$503) -> 390 | AV8: =IF($AL$4=0,0,AU8/$AL$4) -> 0.11287988 | AW8: =SUMIF($V$4:$V$503,$AS8,W$4:W$503) -> 0 | AX8: =SUMIF($V$4:$V$503,$AS8,X$4:X$503) -> 45 | AY8: =SUMIF($V$4:$V$503,$AS8,Y$4:Y$503) -> 63 | AZ8: =SUMIF($V$4:$V$503,$AS8,Z$4:Z$503) -> 128.25 | BA8: =SUMIF($V$4:$V$503,$AS8,AA$4:AA$503) -> 78.75 | BB8: =SUMIF($V$4:$V$503,$AS8,AB$4:AB$503) -> 75 | BC8: =SUMIF($V$4:$V$503,$AS8,AC$4:AC$503) -> 0 | BD8: =SUMIF($V$4:$V$503,$AS8,AD$4:AD$503) -> 0 | ... BH8: =SUMIF($V$4:$V$503,$AS8,AH$4:AH$503) -> 0 | BK8: 5 | BL8: =IF(BK8>$AL$6,"",INDEX($F$4:$F$503,MATCH(BK8,$O$4:$O$503,0))) -> Nicolas Moreau | BM8: =IF(BL8="","",INDEX($N$4:$N$503,MATCH(BK8,$O$4:$O$503,0))) -> 350 | BO8: 5 | BP8: =IF(BO8>$AL$7,"",INDEX($G$4:$G$503,MATCH(BO8,$R$4:$R$503,0))) -> CASSIOPÉE | BQ8: =IF(BP8="","",INDEX($Q$4:$Q$503,MATCH(BO8,$R$4:$R$503,0))) -> 390 | BW8: 5 | BX8: =IFERROR(MATCH(BW8,$EQ$4:$EQ$503,0),"") -> 3 | BZ8: =IF(D8=1,IF(TRIM(INDEX(Charge!$K:$K,ROW()))<>"",TRIM(INDEX(Charge!$K:$K,ROW())),IF(TRIM(INDEX(Charge!$L:$L,ROW()))<>"",TRIM(INDEX(Charge!$L:$L,ROW())),"(non affecté)")),"") -> Léa Chevalier | CA8: =IF(AND($CD$4<>"",BZ8=$CD$4),COUNTIFS($BZ$4:$BZ$503,$CD$4,$L$4:$L$503,"<"&L8)+1,"") | CC8: Capacité disponible pour les projets (h/mois) | CD8: =MAX(0,CD6-CD7) -> 100 | CF8: 5 | CG8: =AA$3 -> 46388 | CH8: =IF($CD$4="",0,$CD$7) -> 20 | CI8: =IF($CD$4="",0,SUMIF($BZ$4:$BZ$503,$CD$4,AA$4:AA$503)) -> 58.333333 | CJ8: =CH8+CI8 -> 78.333333 | CK8: =IF($CD$4="",0,$CD$6) -> 120 | CL8: =IF(CN8<0,MAX(0,MIN(CI8,CK8-CH8)),CI8) -> 58.333333 | CM8: =CI8-CL8 -> 0 | CN8: =CK8-CP8 -> 42 | CO8: =IF(CK8<=0,IF(CP8>0,9.99,0),CP8/CK8) -> 0.65 | CP8: =ROUND(CJ8,0) -> 78 | CQ8: =IF(CN8<0,CF8,"") | CS8: 5 | CT8: =IF(OR(FA8="",COUNTIF($FA$4:FA7,FA8)>0),"",FA8) -> Antoine Blanc | CU8: =IF(CT8="","",IF(FB8="Interne",IF(ISNUMBER(INDEX(Data!$F:$F,8)),INDEX(Data!$F:$F,8),p_HeuresETP),IF(ISNUMBER(INDEX(Data!$I:$I,8-$CD$23)),INDEX(Data!$I:$I,8-$CD$23),p_HeuresETP))) -> 120 | CV8: =IF(CT8="","",IF(FB8="Interne",IF(ISNUMBER(INDEX(Data!$G:$G,8)),INDEX(Data!$G:$G,8),p_ChargeFixe),IF(ISNUMBER(INDEX(Data!$J:$J,8-$CD$23)),INDEX(Data!$J:$J,8-$CD$23),p_ChargeFixe))) -> 20 | CW8: =IF($CT8="","",SUMIF($BZ$4:$BZ$503,$CT8,W$4:W$503)) -> 0 | CX8: =IF($CT8="","",SUMIF($BZ$4:$BZ$503,$CT8,X$4:X$503)) -> 0 | CY8: =IF($CT8="","",SUMIF($BZ$4:$BZ$503,$CT8,Y$4:Y$503)) -> 12.75 | CZ8: =IF($CT8="","",SUMIF($BZ$4:$BZ$503,$CT8,Z$4:Z$503)) -> 48.875 | DA8: =IF($CT8="","",SUMIF($BZ$4:$BZ$503,$CT8,AA$4:AA$503)) -> 23.375 | DB8: =IF($CT8="","",SUMIF($BZ$4:$BZ$503,$CT8,AB$4:AB$503)) -> 48.174006 | DC8: =IF($CT8="","",SUMIF($BZ$4:$BZ$503,$CT8,AC$4:AC$503)) -> 92.64232 | DD8: =IF($CT8="","",SUMIF($BZ$4:$BZ$503,$CT8,AD$4:AD$503)) -> 53.877551 | ... DH8: =IF($CT8="","",SUMIF($BZ$4:$BZ$503,$CT8,AH$4:AH$503)) -> 0 | DI8: =IF($CT8="","",IF($CU8<=0,IF(ROUND($CV8+CW8,0)>0,9.99,0),ROUND($CV8+CW8,0)/$CU8)) -> 0.16666667 | DJ8: =IF($CT8="","",IF($CU8<=0,IF(ROUND($CV8+CX8,0)>0,9.99,0),ROUND($CV8+CX8,0)/$CU8)) -> 0.16666667 | DK8: =IF($CT8="","",IF($CU8<=0,IF(ROUND($CV8+CY8,0)>0,9.99,0),ROUND($CV8+CY8,0)/$CU8)) -> 0.275 | DL8: =IF($CT8="","",IF($CU8<=0,IF(ROUND($CV8+CZ8,0)>0,9.99,0),ROUND($CV8+CZ8,0)/$CU8)) -> 0.575 | DM8: =IF($CT8="","",IF($CU8<=0,IF(ROUND($CV8+DA8,0)>0,9.99,0),ROUND($CV8+DA8,0)/$CU8)) -> 0.35833333 | DN8: =IF($CT8="","",IF($CU8<=0,IF(ROUND($CV8+DB8,0)>0,9.99,0),ROUND($CV8+DB8,0)/$CU8)) -> 0.56666667 | DO8: =IF($CT8="","",IF($CU8<=0,IF(ROUND($CV8+DC8,0)>0,9.99,0),ROUND($CV8+DC8,0)/$CU8)) -> 0.94166667 | DP8: =IF($CT8="","",IF($CU8<=0,IF(ROUND($CV8+DD8,0)>0,9.99,0),ROUND($CV8+DD8,0)/$CU8)) -> 0.61666667 | ... DT8: =IF($CT8="","",IF($CU8<=0,IF(ROUND($CV8+DH8,0)>0,9.99,0),ROUND($CV8+DH8,0)/$CU8)) -> 0.16666667 | DU8: =IF(CT8="","",MAX(DI8:DT8)) -> 0.94166667 | DV8: =IF(CT8="","",SUM(CW8:DH8)) -> 385 | DX8: 5 | DY8: =IFERROR(MATCH(DX8,$CA$4:$CA$503,0),"") | DZ8: =IF(DY8="","",INDEX(Charge!$B:$B,DY8+3)&"") | EA8: =IF(DY8="","",INDEX(Charge!$C:$C,DY8+3)&"") | EB8: =IF(DY8="","",INDEX(Charge!$D:$D,DY8+3)&"") | EC8: =IF(DY8="","",INDEX(Charge!$A:$A,DY8+3)&"") | ED8: =IF(DY8="","",INDEX($E$4:$E$503,DY8)) | EE8: =IF(DY8="","",INDEX($AI$4:$AI$503,DY8)) | EF8: =IF(DY8="","",IF(ISNUMBER(INDEX(Charge!$N:$N,DY8+3)),INDEX(Charge!$N:$N,DY8+3),"—")) | EG8: =IF(DY8="","",IF(ISNUMBER(INDEX(Charge!$F:$F,DY8+3)),INDEX(Charge!$F:$F,DY8+3),"—")) | EH8: =IF(DY8="","",INDEX($C$4:$C$503,DY8)) | EJ8: =TRIM(INDEX(Data!$E:$E,ROW())) -> Antoine Blanc | EK8: =TRIM(INDEX(Data!$H:$H,ROW())) | EM8: =IF(D8=1,IF(TRIM(INDEX(Charge!$K:$K,ROW()))<>"","Interne",IF(TRIM(INDEX(Charge!$L:$L,ROW()))<>"","Externe","Non affecté")),"") -> Interne | EN8: =IF(D8=1,LEFT(SUBSTITUTE(SUBSTITUTE(SUBSTITUTE(TRIM(SUBSTITUTE(INDEX(Charge!$B:$B,ROW()),CHAR(160)," "))&" | "&TRIM(SUBSTITUTE(INDEX(Charge!$C:$C,ROW()),CHAR(160)," "))&" | "&TRIM(SUBSTITUTE(INDEX(Charge!$D:$D,ROW()),CHAR(160)," ")),"~","-"),"*","+"),"?","!"),240),"") -> BORÉAL | Phase APD | Groupe froid | EO8: =IF(EN8="",0,IF(COUNTIF($EN$4:EN8,EN8)=1,1,0)) -> 1 | EP8: =IF(EO8=1,ROUND(SUMIF($EN$4:$EN$503,EN8,$E$4:$E$503),2),"") -> 310 | EQ8: =IF(EO8=1,COUNTIFS($EO$4:$EO$503,1,$EP$4:$EP$503,">"&EP8)+COUNTIFS($EO$4:EO8,1,$EP$4:EP8,EP8),"") -> 4 | ER8: =IF(EO8=1,COUNTIFS($EN$4:$EN$503,EN8,$EM$4:$EM$503,"Interne",$FE$4:$FE$503,1),"") -> 1 | ES8: =IF(EO8=1,COUNTIFS($EN$4:$EN$503,EN8,$EM$4:$EM$503,"Externe",$FE$4:$FE$503,1),"") -> 0 | ET8: =IF(EO8=1,IF(ER8+ES8=0,"à affecter",IF(ER8=0,ES8&" ext.",(ER8+ES8)&IF(ES8>0," dont "&ES8&" ext.",""))&IF(COUNTIFS($EN$4:$EN$503,EN8,$EM$4:$EM$503,"Non affecté")>0," + à affecter","")),"") -> 1 | EU8: =IF(EO8=1,IF(EP8>0,SUMPRODUCT(($EN$4:$EN$503=EN8)*$E$4:$E$503*$C$4:$C$503)/EP8,AVERAGEIF($EN$4:$EN$503,EN8,$C$4:$C$503)),"") -> 0.35 | EV8: =IF(ISNUMBER(I8),I8,2958465) -> 46300 | EW8: =IF(EO8=1,SUMPRODUCT(MIN(($EN$4:$EN$503=EN8)*$EV$4:$EV$503+($EN$4:$EN$503<>EN8)*2958465)),"") -> 46300 | EX8: =IF(AND(D8=1,ISNUMBER(INDEX(Charge!$F:$F,ROW()))),INDEX(Charge!$F:$F,ROW()),0) -> 46416 | EY8: =IF(EO8=1,SUMPRODUCT(MAX(($EN$4:$EN$503=EN8)*$EX$4:$EX$503)),"") -> 46416 | FA8: =IF(5<=$CD$23,INDEX($EJ$4:$EJ$203,5),IF(5-$CD$23<=$CD$26,INDEX($EK$4:$EK$203,5-$CD$23),"")) -> Antoine Blanc | FB8: =IF(FA8="","",IF(5<=$CD$23,"Interne","Externe")) -> Interne | FD8: =IF(AND(B8=1,TRIM(INDEX(Charge!$K:$K,ROW()))<>"",TRIM(INDEX(Charge!$L:$L,ROW()))<>""),1,0) -> 0 | FE8: =IF(OR(EN8="",BZ8="(non affecté)"),0,IF(COUNTIFS($EN$4:EN8,EN8,$BZ$4:BZ8,BZ8)=1,1,0)) -> 1
A9: =ROW() -> 9 | B9: =IF(TRIM(INDEX(Charge!$B:$B,ROW()))<>"",1,0) -> 1 | C9: =IF(B9=1,MIN(1,MAX(0,N(INDEX(Charge!$O:$O,ROW())))),0) -> 0 | D9: =IF(B9=1,IF(OR(p_Perimetre="Tous les projets",C9<1),1,0),0) -> 1 | E9: =IF(D9=1,MAX(0,N(INDEX(Charge!$M:$M,ROW()))),0) -> 220 | F9: =IF(D9=1,IF(TRIM(INDEX(Charge!$A:$A,ROW()))="","(non renseigné)",TRIM(INDEX(Charge!$A:$A,ROW()))),"") -> Thomas Bernard | G9: =IF(D9=1,TRIM(INDEX(Charge!$B:$B,ROW())),"") -> BORÉAL | H9: =IF(D9=1,IF(TRIM(INDEX(Charge!$E:$E,ROW()))="","(non renseigné)",TRIM(INDEX(Charge!$E:$E,ROW()))),"") -> Mise à jour de plans | I9: =IF(AND(D9=1,ISNUMBER(INDEX(Charge!$N:$N,ROW()))),INDEX(Charge!$N:$N,ROW()),"") -> 46419 | J9: =IF(I9="","",IF(AND(p_Repartition="Lissée jusqu'à la date de besoin",ISNUMBER(INDEX(Charge!$F:$F,ROW()))),IF(INDEX(Charge!$F:$F,ROW())>=I9,INDEX(Charge!$F:$F,ROW()),I9),I9)) -> 46507 | K9: =IF(I9="","",NETWORKDAYS(I9,J9,Data!$K$4:$K$203)) -> 65 | L9: =IF(D9=1,COUNTIFS($D$4:$D$503,1,$E$4:$E$503,">"&E9)+COUNTIFS($D$4:$D9,1,$E$4:$E9,E9),"") -> 6 | M9: =IF(F9="",0,IF(COUNTIF($F$4:F9,F9)=1,1,0)) -> 0 | N9: =IF(M9=1,ROUND(SUMIF($F$4:$F$503,F9,$E$4:$E$503),2),"") | O9: =IF(M9=1,COUNTIFS($M$4:$M$503,1,$N$4:$N$503,">"&N9)+COUNTIFS($M$4:M9,1,$N$4:N9,N9),"") | P9: =IF(G9="",0,IF(COUNTIF($G$4:G9,G9)=1,1,0)) -> 0 | Q9: =IF(P9=1,ROUND(SUMIF($G$4:$G$503,G9,$E$4:$E$503),2),"") | R9: =IF(P9=1,COUNTIFS($P$4:$P$503,1,$Q$4:$Q$503,">"&Q9)+COUNTIFS($P$4:P9,1,$Q$4:Q9,Q9),"") | S9: =IF(H9="",0,IF(COUNTIF($H$4:H9,H9)=1,1,0)) -> 1 | T9: =IF(S9=1,ROUND(SUMIF($H$4:$H$503,H9,$E$4:$E$503),2),"") -> 280 | U9: =IF(S9=1,COUNTIFS($S$4:$S$503,1,$T$4:$T$503,">"&T9)+COUNTIFS($S$4:S9,1,$T$4:T9,T9),"") -> 4 | V9: =IF(D9=1,MIN(INDEX($R$4:$R$503,MATCH(G9,$G$4:$G$503,0)),IF($AL$7>9,9,999)),"") -> 2 | W9: =IF(OR($I9="",$E9=0),0,IF(OR($J9<W$3,$I9>W$2),0,IF($K9=0,IF(AND($I9>=W$3,$I9<=W$2),$E9,0),$E9*NETWORKDAYS(MAX($I9,W$3),MIN($J9,W$2),Data!$K$4:$K$203)/$K9))) -> 0 | X9: =IF(OR($I9="",$E9=0),0,IF(OR($J9<X$3,$I9>X$2),0,IF($K9=0,IF(AND($I9>=X$3,$I9<=X$2),$E9,0),$E9*NETWORKDAYS(MAX($I9,X$3),MIN($J9,X$2),Data!$K$4:$K$203)/$K9))) -> 0 | Y9: =IF(OR($I9="",$E9=0),0,IF(OR($J9<Y$3,$I9>Y$2),0,IF($K9=0,IF(AND($I9>=Y$3,$I9<=Y$2),$E9,0),$E9*NETWORKDAYS(MAX($I9,Y$3),MIN($J9,Y$2),Data!$K$4:$K$203)/$K9))) -> 0 | Z9: =IF(OR($I9="",$E9=0),0,IF(OR($J9<Z$3,$I9>Z$2),0,IF($K9=0,IF(AND($I9>=Z$3,$I9<=Z$2),$E9,0),$E9*NETWORKDAYS(MAX($I9,Z$3),MIN($J9,Z$2),Data!$K$4:$K$203)/$K9))) -> 0 | AA9: =IF(OR($I9="",$E9=0),0,IF(OR($J9<AA$3,$I9>AA$2),0,IF($K9=0,IF(AND($I9>=AA$3,$I9<=AA$2),$E9,0),$E9*NETWORKDAYS(MAX($I9,AA$3),MIN($J9,AA$2),Data!$K$4:$K$203)/$K9))) -> 0 | AB9: =IF(OR($I9="",$E9=0),0,IF(OR($J9<AB$3,$I9>AB$2),0,IF($K9=0,IF(AND($I9>=AB$3,$I9<=AB$2),$E9,0),$E9*NETWORKDAYS(MAX($I9,AB$3),MIN($J9,AB$2),Data!$K$4:$K$203)/$K9))) -> 67.692308 | AC9: =IF(OR($I9="",$E9=0),0,IF(OR($J9<AC$3,$I9>AC$2),0,IF($K9=0,IF(AND($I9>=AC$3,$I9<=AC$2),$E9,0),$E9*NETWORKDAYS(MAX($I9,AC$3),MIN($J9,AC$2),Data!$K$4:$K$203)/$K9))) -> 77.846154 | AD9: =IF(OR($I9="",$E9=0),0,IF(OR($J9<AD$3,$I9>AD$2),0,IF($K9=0,IF(AND($I9>=AD$3,$I9<=AD$2),$E9,0),$E9*NETWORKDAYS(MAX($I9,AD$3),MIN($J9,AD$2),Data!$K$4:$K$203)/$K9))) -> 74.461538 | ... AH9: =IF(OR($I9="",$E9=0),0,IF(OR($J9<AH$3,$I9>AH$2),0,IF($K9=0,IF(AND($I9>=AH$3,$I9<=AH$2),$E9,0),$E9*NETWORKDAYS(MAX($I9,AH$3),MIN($J9,AH$2),Data!$K$4:$K$203)/$K9))) -> 0 | AI9: =SUM(W9:AH9) -> 220 | AK9: Charge réalisée (selon avancement) | AL9: =SUMPRODUCT(E4:E503,C4:C503) -> 339.5 | AN9: 6 | AO9: =AB$3 -> 46419 | AP9: =SUM(AB4:AB503) -> 376.79143 | AQ9: =SUMPRODUCT((AB4:AB503>0)/(COUNTIFS($EN$4:$EN$503,$EN$4:$EN$503,AB4:AB503,">0")+(AB4:AB503<=0))) -> 7 | AS9: 6 | AT9: =IF(AS9>$AL$7,"",INDEX($G$4:$G$503,MATCH(AS9,$R$4:$R$503,0))) -> ORION | AU9: =SUMIF($V$4:$V$503,AS9,$E$4:$E$503) -> 280 | AV9: =IF($AL$4=0,0,AU9/$AL$4) -> 0.081041968 | AW9: =SUMIF($V$4:$V$503,$AS9,W$4:W$503) -> 28.363636 | AX9: =SUMIF($V$4:$V$503,$AS9,X$4:X$503) -> 48 | AY9: =SUMIF($V$4:$V$503,$AS9,Y$4:Y$503) -> 43.636364 | AZ9: =SUMIF($V$4:$V$503,$AS9,Z$4:Z$503) -> 0 | BA9: =SUMIF($V$4:$V$503,$AS9,AA$4:AA$503) -> 0 | BB9: =SUMIF($V$4:$V$503,$AS9,AB$4:AB$503) -> 0 | BC9: =SUMIF($V$4:$V$503,$AS9,AC$4:AC$503) -> 66.909091 | BD9: =SUMIF($V$4:$V$503,$AS9,AD$4:AD$503) -> 64 | ... BH9: =SUMIF($V$4:$V$503,$AS9,AH$4:AH$503) -> 0 | BK9: 6 | BL9: =IF(BK9>$AL$6,"",INDEX($F$4:$F$503,MATCH(BK9,$O$4:$O$503,0))) | BM9: =IF(BL9="","",INDEX($N$4:$N$503,MATCH(BK9,$O$4:$O$503,0))) | BO9: 6 | BP9: =IF(BO9>$AL$7,"",INDEX($G$4:$G$503,MATCH(BO9,$R$4:$R$503,0))) -> ORION | BQ9: =IF(BP9="","",INDEX($Q$4:$Q$503,MATCH(BO9,$R$4:$R$503,0))) -> 280 | BW9: 6 | BX9: =IFERROR(MATCH(BW9,$EQ$4:$EQ$503,0),"") -> 9 | BZ9: =IF(D9=1,IF(TRIM(INDEX(Charge!$K:$K,ROW()))<>"",TRIM(INDEX(Charge!$K:$K,ROW())),IF(TRIM(INDEX(Charge!$L:$L,ROW()))<>"",TRIM(INDEX(Charge!$L:$L,ROW())),"(non affecté)")),"") -> Léa Chevalier | CA9: =IF(AND($CD$4<>"",BZ9=$CD$4),COUNTIFS($BZ$4:$BZ$503,$CD$4,$L$4:$L$503,"<"&L9)+1,"") | CC9: Charge projets affectée, toutes périodes (h) | CD9: =IF(CD4="",0,SUMIF($BZ$4:$BZ$503,CD4,$E$4:$E$503)) -> 420 | CF9: 6 | CG9: =AB$3 -> 46419 | CH9: =IF($CD$4="",0,$CD$7) -> 20 | CI9: =IF($CD$4="",0,SUMIF($BZ$4:$BZ$503,$CD$4,AB$4:AB$503)) -> 55.555556 | CJ9: =CH9+CI9 -> 75.555556 | CK9: =IF($CD$4="",0,$CD$6) -> 120 | CL9: =IF(CN9<0,MAX(0,MIN(CI9,CK9-CH9)),CI9) -> 55.555556 | CM9: =CI9-CL9 -> 0 | CN9: =CK9-CP9 -> 44 | CO9: =IF(CK9<=0,IF(CP9>0,9.99,0),CP9/CK9) -> 0.63333333 | CP9: =ROUND(CJ9,0) -> 76 | CQ9: =IF(CN9<0,CF9,"") | CS9: 6 | CT9: =IF(OR(FA9="",COUNTIF($FA$4:FA8,FA9)>0),"",FA9) -> Paul Girard | CU9: =IF(CT9="","",IF(FB9="Interne",IF(ISNUMBER(INDEX(Data!$F:$F,9)),INDEX(Data!$F:$F,9),p_HeuresETP),IF(ISNUMBER(INDEX(Data!$I:$I,9-$CD$23)),INDEX(Data!$I:$I,9-$CD$23),p_HeuresETP))) -> 120 | CV9: =IF(CT9="","",IF(FB9="Interne",IF(ISNUMBER(INDEX(Data!$G:$G,9)),INDEX(Data!$G:$G,9),p_ChargeFixe),IF(ISNUMBER(INDEX(Data!$J:$J,9-$CD$23)),INDEX(Data!$J:$J,9-$CD$23),p_ChargeFixe))) -> 20 | CW9: =IF($CT9="","",SUMIF($BZ$4:$BZ$503,$CT9,W$4:W$503)) -> 0 | CX9: =IF($CT9="","",SUMIF($BZ$4:$BZ$503,$CT9,X$4:X$503)) -> 0 | CY9: =IF($CT9="","",SUMIF($BZ$4:$BZ$503,$CT9,Y$4:Y$503)) -> 23.333333 | CZ9: =IF($CT9="","",SUMIF($BZ$4:$BZ$503,$CT9,Z$4:Z$503)) -> 54.305556 | DA9: =IF($CT9="","",SUMIF($BZ$4:$BZ$503,$CT9,AA$4:AA$503)) -> 49.583333 | DB9: =IF($CT9="","",SUMIF($BZ$4:$BZ$503,$CT9,AB$4:AB$503)) -> 47.222222 | DC9: =IF($CT9="","",SUMIF($BZ$4:$BZ$503,$CT9,AC$4:AC$503)) -> 25.555556 | DD9: =IF($CT9="","",SUMIF($BZ$4:$BZ$503,$CT9,AD$4:AD$503)) -> 0 | ... DH9: =IF($CT9="","",SUMIF($BZ$4:$BZ$503,$CT9,AH$4:AH$503)) -> 0 | DI9: =IF($CT9="","",IF($CU9<=0,IF(ROUND($CV9+CW9,0)>0,9.99,0),ROUND($CV9+CW9,0)/$CU9)) -> 0.16666667 | DJ9: =IF($CT9="","",IF($CU9<=0,IF(ROUND($CV9+CX9,0)>0,9.99,0),ROUND($CV9+CX9,0)/$CU9)) -> 0.16666667 | DK9: =IF($CT9="","",IF($CU9<=0,IF(ROUND($CV9+CY9,0)>0,9.99,0),ROUND($CV9+CY9,0)/$CU9)) -> 0.35833333 | DL9: =IF($CT9="","",IF($CU9<=0,IF(ROUND($CV9+CZ9,0)>0,9.99,0),ROUND($CV9+CZ9,0)/$CU9)) -> 0.61666667 | DM9: =IF($CT9="","",IF($CU9<=0,IF(ROUND($CV9+DA9,0)>0,9.99,0),ROUND($CV9+DA9,0)/$CU9)) -> 0.58333333 | DN9: =IF($CT9="","",IF($CU9<=0,IF(ROUND($CV9+DB9,0)>0,9.99,0),ROUND($CV9+DB9,0)/$CU9)) -> 0.55833333 | DO9: =IF($CT9="","",IF($CU9<=0,IF(ROUND($CV9+DC9,0)>0,9.99,0),ROUND($CV9+DC9,0)/$CU9)) -> 0.38333333 | DP9: =IF($CT9="","",IF($CU9<=0,IF(ROUND($CV9+DD9,0)>0,9.99,0),ROUND($CV9+DD9,0)/$CU9)) -> 0.16666667 | ... DT9: =IF($CT9="","",IF($CU9<=0,IF(ROUND($CV9+DH9,0)>0,9.99,0),ROUND($CV9+DH9,0)/$CU9)) -> 0.16666667 | DU9: =IF(CT9="","",MAX(DI9:DT9)) -> 0.61666667 | DV9: =IF(CT9="","",SUM(CW9:DH9)) -> 200 | DX9: 6 | DY9: =IFERROR(MATCH(DX9,$CA$4:$CA$503,0),"") | DZ9: =IF(DY9="","",INDEX(Charge!$B:$B,DY9+3)&"") | EA9: =IF(DY9="","",INDEX(Charge!$C:$C,DY9+3)&"") | EB9: =IF(DY9="","",INDEX(Charge!$D:$D,DY9+3)&"") | EC9: =IF(DY9="","",INDEX(Charge!$A:$A,DY9+3)&"") | ED9: =IF(DY9="","",INDEX($E$4:$E$503,DY9)) | EE9: =IF(DY9="","",INDEX($AI$4:$AI$503,DY9)) | EF9: =IF(DY9="","",IF(ISNUMBER(INDEX(Charge!$N:$N,DY9+3)),INDEX(Charge!$N:$N,DY9+3),"—")) | EG9: =IF(DY9="","",IF(ISNUMBER(INDEX(Charge!$F:$F,DY9+3)),INDEX(Charge!$F:$F,DY9+3),"—")) | EH9: =IF(DY9="","",INDEX($C$4:$C$503,DY9)) | EJ9: =TRIM(INDEX(Data!$E:$E,ROW())) | EK9: =TRIM(INDEX(Data!$H:$H,ROW())) | EM9: =IF(D9=1,IF(TRIM(INDEX(Charge!$K:$K,ROW()))<>"","Interne",IF(TRIM(INDEX(Charge!$L:$L,ROW()))<>"","Externe","Non affecté")),"") -> Interne | EN9: =IF(D9=1,LEFT(SUBSTITUTE(SUBSTITUTE(SUBSTITUTE(TRIM(SUBSTITUTE(INDEX(Charge!$B:$B,ROW()),CHAR(160)," "))&" | "&TRIM(SUBSTITUTE(INDEX(Charge!$C:$C,ROW()),CHAR(160)," "))&" | "&TRIM(SUBSTITUTE(INDEX(Charge!$D:$D,ROW()),CHAR(160)," ")),"~","-"),"*","+"),"?","!"),240),"") -> BORÉAL | Phase EXE | Groupe froid | EO9: =IF(EN9="",0,IF(COUNTIF($EN$4:EN9,EN9)=1,1,0)) -> 1 | EP9: =IF(EO9=1,ROUND(SUMIF($EN$4:$EN$503,EN9,$E$4:$E$503),2),"") -> 220 | EQ9: =IF(EO9=1,COUNTIFS($EO$4:$EO$503,1,$EP$4:$EP$503,">"&EP9)+COUNTIFS($EO$4:EO9,1,$EP$4:EP9,EP9),"") -> 7 | ER9: =IF(EO9=1,COUNTIFS($EN$4:$EN$503,EN9,$EM$4:$EM$503,"Interne",$FE$4:$FE$503,1),"") -> 1 | ES9: =IF(EO9=1,COUNTIFS($EN$4:$EN$503,EN9,$EM$4:$EM$503,"Externe",$FE$4:$FE$503,1),"") -> 0 | ET9: =IF(EO9=1,IF(ER9+ES9=0,"à affecter",IF(ER9=0,ES9&" ext.",(ER9+ES9)&IF(ES9>0," dont "&ES9&" ext.",""))&IF(COUNTIFS($EN$4:$EN$503,EN9,$EM$4:$EM$503,"Non affecté")>0," + à affecter","")),"") -> 1 | EU9: =IF(EO9=1,IF(EP9>0,SUMPRODUCT(($EN$4:$EN$503=EN9)*$E$4:$E$503*$C$4:$C$503)/EP9,AVERAGEIF($EN$4:$EN$503,EN9,$C$4:$C$503)),"") -> 0 | EV9: =IF(ISNUMBER(I9),I9,2958465) -> 46419 | EW9: =IF(EO9=1,SUMPRODUCT(MIN(($EN$4:$EN$503=EN9)*$EV$4:$EV$503+($EN$4:$EN$503<>EN9)*2958465)),"") -> 46419 | EX9: =IF(AND(D9=1,ISNUMBER(INDEX(Charge!$F:$F,ROW()))),INDEX(Charge!$F:$F,ROW()),0) -> 46507 | EY9: =IF(EO9=1,SUMPRODUCT(MAX(($EN$4:$EN$503=EN9)*$EX$4:$EX$503)),"") -> 46507 | FA9: =IF(6<=$CD$23,INDEX($EJ$4:$EJ$203,6),IF(6-$CD$23<=$CD$26,INDEX($EK$4:$EK$203,6-$CD$23),"")) -> Paul Girard | FB9: =IF(FA9="","",IF(6<=$CD$23,"Interne","Externe")) -> Externe | FD9: =IF(AND(B9=1,TRIM(INDEX(Charge!$K:$K,ROW()))<>"",TRIM(INDEX(Charge!$L:$L,ROW()))<>""),1,0) -> 0 | FE9: =IF(OR(EN9="",BZ9="(non affecté)"),0,IF(COUNTIFS($EN$4:EN9,EN9,$BZ$4:BZ9,BZ9)=1,1,0)) -> 1
A10: =ROW() -> 10 | B10: =IF(TRIM(INDEX(Charge!$B:$B,ROW()))<>"",1,0) -> 1 | C10: =IF(B10=1,MIN(1,MAX(0,N(INDEX(Charge!$O:$O,ROW())))),0) -> 0 | D10: =IF(B10=1,IF(OR(p_Perimetre="Tous les projets",C10<1),1,0),0) -> 1 | E10: =IF(D10=1,MAX(0,N(INDEX(Charge!$M:$M,ROW()))),0) -> 90 | F10: =IF(D10=1,IF(TRIM(INDEX(Charge!$A:$A,ROW()))="","(non renseigné)",TRIM(INDEX(Charge!$A:$A,ROW()))),"") -> Thomas Bernard | G10: =IF(D10=1,TRIM(INDEX(Charge!$B:$B,ROW())),"") -> BORÉAL | H10: =IF(D10=1,IF(TRIM(INDEX(Charge!$E:$E,ROW()))="","(non renseigné)",TRIM(INDEX(Charge!$E:$E,ROW()))),"") -> Modification | I10: =IF(AND(D10=1,ISNUMBER(INDEX(Charge!$N:$N,ROW()))),INDEX(Charge!$N:$N,ROW()),"") -> 46405 | J10: =IF(I10="","",IF(AND(p_Repartition="Lissée jusqu'à la date de besoin",ISNUMBER(INDEX(Charge!$F:$F,ROW()))),IF(INDEX(Charge!$F:$F,ROW())>=I10,INDEX(Charge!$F:$F,ROW()),I10),I10)) -> 46461 | K10: =IF(I10="","",NETWORKDAYS(I10,J10,Data!$K$4:$K$203)) -> 41 | L10: =IF(D10=1,COUNTIFS($D$4:$D$503,1,$E$4:$E$503,">"&E10)+COUNTIFS($D$4:$D10,1,$E$4:$E10,E10),"") -> 16 | M10: =IF(F10="",0,IF(COUNTIF($F$4:F10,F10)=1,1,0)) -> 0 | N10: =IF(M10=1,ROUND(SUMIF($F$4:$F$503,F10,$E$4:$E$503),2),"") | O10: =IF(M10=1,COUNTIFS($M$4:$M$503,1,$N$4:$N$503,">"&N10)+COUNTIFS($M$4:M10,1,$N$4:N10,N10),"") | P10: =IF(G10="",0,IF(COUNTIF($G$4:G10,G10)=1,1,0)) -> 0 | Q10: =IF(P10=1,ROUND(SUMIF($G$4:$G$503,G10,$E$4:$E$503),2),"") | R10: =IF(P10=1,COUNTIFS($P$4:$P$503,1,$Q$4:$Q$503,">"&Q10)+COUNTIFS($P$4:P10,1,$Q$4:Q10,Q10),"") | S10: =IF(H10="",0,IF(COUNTIF($H$4:H10,H10)=1,1,0)) -> 1 | T10: =IF(S10=1,ROUND(SUMIF($H$4:$H$503,H10,$E$4:$E$503),2),"") -> 535 | U10: =IF(S10=1,COUNTIFS($S$4:$S$503,1,$T$4:$T$503,">"&T10)+COUNTIFS($S$4:S10,1,$T$4:T10,T10),"") -> 3 | V10: =IF(D10=1,MIN(INDEX($R$4:$R$503,MATCH(G10,$G$4:$G$503,0)),IF($AL$7>9,9,999)),"") -> 2 | W10: =IF(OR($I10="",$E10=0),0,IF(OR($J10<W$3,$I10>W$2),0,IF($K10=0,IF(AND($I10>=W$3,$I10<=W$2),$E10,0),$E10*NETWORKDAYS(MAX($I10,W$3),MIN($J10,W$2),Data!$K$4:$K$203)/$K10))) -> 0 | X10: =IF(OR($I10="",$E10=0),0,IF(OR($J10<X$3,$I10>X$2),0,IF($K10=0,IF(AND($I10>=X$3,$I10<=X$2),$E10,0),$E10*NETWORKDAYS(MAX($I10,X$3),MIN($J10,X$2),Data!$K$4:$K$203)/$K10))) -> 0 | Y10: =IF(OR($I10="",$E10=0),0,IF(OR($J10<Y$3,$I10>Y$2),0,IF($K10=0,IF(AND($I10>=Y$3,$I10<=Y$2),$E10,0),$E10*NETWORKDAYS(MAX($I10,Y$3),MIN($J10,Y$2),Data!$K$4:$K$203)/$K10))) -> 0 | Z10: =IF(OR($I10="",$E10=0),0,IF(OR($J10<Z$3,$I10>Z$2),0,IF($K10=0,IF(AND($I10>=Z$3,$I10<=Z$2),$E10,0),$E10*NETWORKDAYS(MAX($I10,Z$3),MIN($J10,Z$2),Data!$K$4:$K$203)/$K10))) -> 0 | AA10: =IF(OR($I10="",$E10=0),0,IF(OR($J10<AA$3,$I10>AA$2),0,IF($K10=0,IF(AND($I10>=AA$3,$I10<=AA$2),$E10,0),$E10*NETWORKDAYS(MAX($I10,AA$3),MIN($J10,AA$2),Data!$K$4:$K$203)/$K10))) -> 21.95122 | AB10: =IF(OR($I10="",$E10=0),0,IF(OR($J10<AB$3,$I10>AB$2),0,IF($K10=0,IF(AND($I10>=AB$3,$I10<=AB$2),$E10,0),$E10*NETWORKDAYS(MAX($I10,AB$3),MIN($J10,AB$2),Data!$K$4:$K$203)/$K10))) -> 43.902439 | AC10: =IF(OR($I10="",$E10=0),0,IF(OR($J10<AC$3,$I10>AC$2),0,IF($K10=0,IF(AND($I10>=AC$3,$I10<=AC$2),$E10,0),$E10*NETWORKDAYS(MAX($I10,AC$3),MIN($J10,AC$2),Data!$K$4:$K$203)/$K10))) -> 24.146341 | AD10: =IF(OR($I10="",$E10=0),0,IF(OR($J10<AD$3,$I10>AD$2),0,IF($K10=0,IF(AND($I10>=AD$3,$I10<=AD$2),$E10,0),$E10*NETWORKDAYS(MAX($I10,AD$3),MIN($J10,AD$2),Data!$K$4:$K$203)/$K10))) -> 0 | ... AH10: =IF(OR($I10="",$E10=0),0,IF(OR($J10<AH$3,$I10>AH$2),0,IF($K10=0,IF(AND($I10>=AH$3,$I10<=AH$2),$E10,0),$E10*NETWORKDAYS(MAX($I10,AH$3),MIN($J10,AH$2),Data!$K$4:$K$203)/$K10))) -> 0 | AI10: =SUM(W10:AH10) -> 90 | AK10: Reste à faire (h) | AL10: =AL4-AL9 -> 3115.5 | AN10: 7 | AO10: =AC$3 -> 46447 | AP10: =SUM(AC4:AC503) -> 507.8405 | AQ10: =SUMPRODUCT((AC4:AC503>0)/(COUNTIFS($EN$4:$EN$503,$EN$4:$EN$503,AC4:AC503,">0")+(AC4:AC503<=0))) -> 9 | AS10: 7 | AT10: =IF(AS10>$AL$7,"",INDEX($G$4:$G$503,MATCH(AS10,$R$4:$R$503,0))) -> VEGA | AU10: =SUMIF($V$4:$V$503,AS10,$E$4:$E$503) -> 195 | AV10: =IF($AL$4=0,0,AU10/$AL$4) -> 0.056439942 | AW10: =SUMIF($V$4:$V$503,$AS10,W$4:W$503) -> 0 | AX10: =SUMIF($V$4:$V$503,$AS10,X$4:X$503) -> 0 | AY10: =SUMIF($V$4:$V$503,$AS10,Y$4:Y$503) -> 12.75 | AZ10: =SUMIF($V$4:$V$503,$AS10,Z$4:Z$503) -> 48.875 | BA10: =SUMIF($V$4:$V$503,$AS10,AA$4:AA$503) -> 23.375 | BB10: =SUMIF($V$4:$V$503,$AS10,AB$4:AB$503) -> 23.684211 | BC10: =SUMIF($V$4:$V$503,$AS10,AC$4:AC$503) -> 61.871345 | BD10: =SUMIF($V$4:$V$503,$AS10,AD$4:AD$503) -> 24.444444 | ... BH10: =SUMIF($V$4:$V$503,$AS10,AH$4:AH$503) -> 0 | BK10: 7 | BL10: =IF(BK10>$AL$6,"",INDEX($F$4:$F$503,MATCH(BK10,$O$4:$O$503,0))) | BM10: =IF(BL10="","",INDEX($N$4:$N$503,MATCH(BK10,$O$4:$O$503,0))) | BO10: 7 | BP10: =IF(BO10>$AL$7,"",INDEX($G$4:$G$503,MATCH(BO10,$R$4:$R$503,0))) -> VEGA | BQ10: =IF(BP10="","",INDEX($Q$4:$Q$503,MATCH(BO10,$R$4:$R$503,0))) -> 195 | BW10: 7 | BX10: =IFERROR(MATCH(BW10,$EQ$4:$EQ$503,0),"") -> 6 | BZ10: =IF(D10=1,IF(TRIM(INDEX(Charge!$K:$K,ROW()))<>"",TRIM(INDEX(Charge!$K:$K,ROW())),IF(TRIM(INDEX(Charge!$L:$L,ROW()))<>"",TRIM(INDEX(Charge!$L:$L,ROW())),"(non affecté)")),"") -> Karim Haddad | CA10: =IF(AND($CD$4<>"",BZ10=$CD$4),COUNTIFS($BZ$4:$BZ$503,$CD$4,$L$4:$L$503,"<"&L10)+1,"") | CC10: Nombre d'affaires (sous-projets) de la ressource | CD10: =IF(CD4="",0,COUNTIFS($BZ$4:$BZ$503,CD4,$FE$4:$FE$503,1)) -> 2 | CF10: 7 | CG10: =AC$3 -> 46447 | CH10: =IF($CD$4="",0,$CD$7) -> 20 | CI10: =IF($CD$4="",0,SUMIF($BZ$4:$BZ$503,$CD$4,AC$4:AC$503)) -> 63.888889 | CJ10: =CH10+CI10 -> 83.888889 | CK10: =IF($CD$4="",0,$CD$6) -> 120 | CL10: =IF(CN10<0,MAX(0,MIN(CI10,CK10-CH10)),CI10) -> 63.888889 | CM10: =CI10-CL10 -> 0 | CN10: =CK10-CP10 -> 36 | CO10: =IF(CK10<=0,IF(CP10>0,9.99,0),CP10/CK10) -> 0.7 | CP10: =ROUND(CJ10,0) -> 84 | CQ10: =IF(CN10<0,CF10,"") | CS10: 7 | CT10: =IF(OR(FA10="",COUNTIF($FA$4:FA9,FA10)>0),"",FA10) -> Inès Morel | CU10: =IF(CT10="","",IF(FB10="Interne",IF(ISNUMBER(INDEX(Data!$F:$F,10)),INDEX(Data!$F:$F,10),p_HeuresETP),IF(ISNUMBER(INDEX(Data!$I:$I,10-$CD$23)),INDEX(Data!$I:$I,10-$CD$23),p_HeuresETP))) -> 120 | CV10: =IF(CT10="","",IF(FB10="Interne",IF(ISNUMBER(INDEX(Data!$G:$G,10)),INDEX(Data!$G:$G,10),p_ChargeFixe),IF(ISNUMBER(INDEX(Data!$J:$J,10-$CD$23)),INDEX(Data!$J:$J,10-$CD$23),p_ChargeFixe))) -> 20 | CW10: =IF($CT10="","",SUMIF($BZ$4:$BZ$503,$CT10,W$4:W$503)) -> 0 | CX10: =IF($CT10="","",SUMIF($BZ$4:$BZ$503,$CT10,X$4:X$503)) -> 0 | CY10: =IF($CT10="","",SUMIF($BZ$4:$BZ$503,$CT10,Y$4:Y$503)) -> 0 | CZ10: =IF($CT10="","",SUMIF($BZ$4:$BZ$503,$CT10,Z$4:Z$503)) -> 0 | DA10: =IF($CT10="","",SUMIF($BZ$4:$BZ$503,$CT10,AA$4:AA$503)) -> 0 | DB10: =IF($CT10="","",SUMIF($BZ$4:$BZ$503,$CT10,AB$4:AB$503)) -> 0 | DC10: =IF($CT10="","",SUMIF($BZ$4:$BZ$503,$CT10,AC$4:AC$503)) -> 0 | DD10: =IF($CT10="","",SUMIF($BZ$4:$BZ$503,$CT10,AD$4:AD$503)) -> 42.352941 | ... DH10: =IF($CT10="","",SUMIF($BZ$4:$BZ$503,$CT10,AH$4:AH$503)) -> 18.823529 | DI10: =IF($CT10="","",IF($CU10<=0,IF(ROUND($CV10+CW10,0)>0,9.99,0),ROUND($CV10+CW10,0)/$CU10)) -> 0.16666667 | DJ10: =IF($CT10="","",IF($CU10<=0,IF(ROUND($CV10+CX10,0)>0,9.99,0),ROUND($CV10+CX10,0)/$CU10)) -> 0.16666667 | DK10: =IF($CT10="","",IF($CU10<=0,IF(ROUND($CV10+CY10,0)>0,9.99,0),ROUND($CV10+CY10,0)/$CU10)) -> 0.16666667 | DL10: =IF($CT10="","",IF($CU10<=0,IF(ROUND($CV10+CZ10,0)>0,9.99,0),ROUND($CV10+CZ10,0)/$CU10)) -> 0.16666667 | DM10: =IF($CT10="","",IF($CU10<=0,IF(ROUND($CV10+DA10,0)>0,9.99,0),ROUND($CV10+DA10,0)/$CU10)) -> 0.16666667 | DN10: =IF($CT10="","",IF($CU10<=0,IF(ROUND($CV10+DB10,0)>0,9.99,0),ROUND($CV10+DB10,0)/$CU10)) -> 0.16666667 | DO10: =IF($CT10="","",IF($CU10<=0,IF(ROUND($CV10+DC10,0)>0,9.99,0),ROUND($CV10+DC10,0)/$CU10)) -> 0.16666667 | DP10: =IF($CT10="","",IF($CU10<=0,IF(ROUND($CV10+DD10,0)>0,9.99,0),ROUND($CV10+DD10,0)/$CU10)) -> 0.51666667 | ... DT10: =IF($CT10="","",IF($CU10<=0,IF(ROUND($CV10+DH10,0)>0,9.99,0),ROUND($CV10+DH10,0)/$CU10)) -> 0.325 | DU10: =IF(CT10="","",MAX(DI10:DT10)) -> 0.725 | DV10: =IF(CT10="","",SUM(CW10:DH10)) -> 260 | DX10: 7 | DY10: =IFERROR(MATCH(DX10,$CA$4:$CA$503,0),"") | DZ10: =IF(DY10="","",INDEX(Charge!$B:$B,DY10+3)&"") | EA10: =IF(DY10="","",INDEX(Charge!$C:$C,DY10+3)&"") | EB10: =IF(DY10="","",INDEX(Charge!$D:$D,DY10+3)&"") | EC10: =IF(DY10="","",INDEX(Charge!$A:$A,DY10+3)&"") | ED10: =IF(DY10="","",INDEX($E$4:$E$503,DY10)) | EE10: =IF(DY10="","",INDEX($AI$4:$AI$503,DY10)) | EF10: =IF(DY10="","",IF(ISNUMBER(INDEX(Charge!$N:$N,DY10+3)),INDEX(Charge!$N:$N,DY10+3),"—")) | EG10: =IF(DY10="","",IF(ISNUMBER(INDEX(Charge!$F:$F,DY10+3)),INDEX(Charge!$F:$F,DY10+3),"—")) | EH10: =IF(DY10="","",INDEX($C$4:$C$503,DY10)) | EJ10: =TRIM(INDEX(Data!$E:$E,ROW())) | EK10: =TRIM(INDEX(Data!$H:$H,ROW())) | EM10: =IF(D10=1,IF(TRIM(INDEX(Charge!$K:$K,ROW()))<>"","Interne",IF(TRIM(INDEX(Charge!$L:$L,ROW()))<>"","Externe","Non affecté")),"") -> Externe | EN10: =IF(D10=1,LEFT(SUBSTITUTE(SUBSTITUTE(SUBSTITUTE(TRIM(SUBSTITUTE(INDEX(Charge!$B:$B,ROW()),CHAR(160)," "))&" | "&TRIM(SUBSTITUTE(INDEX(Charge!$C:$C,ROW()),CHAR(160)," "))&" | "&TRIM(SUBSTITUTE(INDEX(Charge!$D:$D,ROW()),CHAR(160)," ")),"~","-"),"*","+"),"?","!"),240),"") -> BORÉAL | Phase EXE | Armoire de commande | EO10: =IF(EN10="",0,IF(COUNTIF($EN$4:EN10,EN10)=1,1,0)) -> 1 | EP10: =IF(EO10=1,ROUND(SUMIF($EN$4:$EN$503,EN10,$E$4:$E$503),2),"") -> 90 | EQ10: =IF(EO10=1,COUNTIFS($EO$4:$EO$503,1,$EP$4:$EP$503,">"&EP10)+COUNTIFS($EO$4:EO10,1,$EP$4:EP10,EP10),"") -> 13 | ER10: =IF(EO10=1,COUNTIFS($EN$4:$EN$503,EN10,$EM$4:$EM$503,"Interne",$FE$4:$FE$503,1),"") -> 0 | ES10: =IF(EO10=1,COUNTIFS($EN$4:$EN$503,EN10,$EM$4:$EM$503,"Externe",$FE$4:$FE$503,1),"") -> 1 | ET10: =IF(EO10=1,IF(ER10+ES10=0,"à affecter",IF(ER10=0,ES10&" ext.",(ER10+ES10)&IF(ES10>0," dont "&ES10&" ext.",""))&IF(COUNTIFS($EN$4:$EN$503,EN10,$EM$4:$EM$503,"Non affecté")>0," + à affecter","")),"") -> 1 ext. | EU10: =IF(EO10=1,IF(EP10>0,SUMPRODUCT(($EN$4:$EN$503=EN10)*$E$4:$E$503*$C$4:$C$503)/EP10,AVERAGEIF($EN$4:$EN$503,EN10,$C$4:$C$503)),"") -> 0 | EV10: =IF(ISNUMBER(I10),I10,2958465) -> 46405 | EW10: =IF(EO10=1,SUMPRODUCT(MIN(($EN$4:$EN$503=EN10)*$EV$4:$EV$503+($EN$4:$EN$503<>EN10)*2958465)),"") -> 46405 | EX10: =IF(AND(D10=1,ISNUMBER(INDEX(Charge!$F:$F,ROW()))),INDEX(Charge!$F:$F,ROW()),0) -> 46461 | EY10: =IF(EO10=1,SUMPRODUCT(MAX(($EN$4:$EN$503=EN10)*$EX$4:$EX$503)),"") -> 46461 | FA10: =IF(7<=$CD$23,INDEX($EJ$4:$EJ$203,7),IF(7-$CD$23<=$CD$26,INDEX($EK$4:$EK$203,7-$CD$23),"")) -> Inès Morel | FB10: =IF(FA10="","",IF(7<=$CD$23,"Interne","Externe")) -> Externe | FD10: =IF(AND(B10=1,TRIM(INDEX(Charge!$K:$K,ROW()))<>"",TRIM(INDEX(Charge!$L:$L,ROW()))<>""),1,0) -> 0 | FE10: =IF(OR(EN10="",BZ10="(non affecté)"),0,IF(COUNTIFS($EN$4:EN10,EN10,$BZ$4:BZ10,BZ10)=1,1,0)) -> 1
A11: =ROW() -> 11 | B11: =IF(TRIM(INDEX(Charge!$B:$B,ROW()))<>"",1,0) -> 1 | C11: =IF(B11=1,MIN(1,MAX(0,N(INDEX(Charge!$O:$O,ROW())))),0) -> 0.5 | D11: =IF(B11=1,IF(OR(p_Perimetre="Tous les projets",C11<1),1,0),0) -> 1 | E11: =IF(D11=1,MAX(0,N(INDEX(Charge!$M:$M,ROW()))),0) -> 150 | F11: =IF(D11=1,IF(TRIM(INDEX(Charge!$A:$A,ROW()))="","(non renseigné)",TRIM(INDEX(Charge!$A:$A,ROW()))),"") -> Sophie Lefèvre | G11: =IF(D11=1,TRIM(INDEX(Charge!$B:$B,ROW())),"") -> CASSIOPÉE | H11: =IF(D11=1,IF(TRIM(INDEX(Charge!$E:$E,ROW()))="","(non renseigné)",TRIM(INDEX(Charge!$E:$E,ROW()))),"") -> Modification | I11: =IF(AND(D11=1,ISNUMBER(INDEX(Charge!$N:$N,ROW()))),INDEX(Charge!$N:$N,ROW()),"") -> 46307 | J11: =IF(I11="","",IF(AND(p_Repartition="Lissée jusqu'à la date de besoin",ISNUMBER(INDEX(Charge!$F:$F,ROW()))),IF(INDEX(Charge!$F:$F,ROW())>=I11,INDEX(Charge!$F:$F,ROW()),I11),I11)) -> 46374 | K11: =IF(I11="","",NETWORKDAYS(I11,J11,Data!$K$4:$K$203)) -> 50 | L11: =IF(D11=1,COUNTIFS($D$4:$D$503,1,$E$4:$E$503,">"&E11)+COUNTIFS($D$4:$D11,1,$E$4:$E11,E11),"") -> 11 | M11: =IF(F11="",0,IF(COUNTIF($F$4:F11,F11)=1,1,0)) -> 1 | N11: =IF(M11=1,ROUND(SUMIF($F$4:$F$503,F11,$E$4:$E$503),2),"") -> 750 | O11: =IF(M11=1,COUNTIFS($M$4:$M$503,1,$N$4:$N$503,">"&N11)+COUNTIFS($M$4:M11,1,$N$4:N11,N11),"") -> 3 | P11: =IF(G11="",0,IF(COUNTIF($G$4:G11,G11)=1,1,0)) -> 1 | Q11: =IF(P11=1,ROUND(SUMIF($G$4:$G$503,G11,$E$4:$E$503),2),"") -> 390 | R11: =IF(P11=1,COUNTIFS($P$4:$P$503,1,$Q$4:$Q$503,">"&Q11)+COUNTIFS($P$4:P11,1,$Q$4:Q11,Q11),"") -> 5 | S11: =IF(H11="",0,IF(COUNTIF($H$4:H11,H11)=1,1,0)) -> 0 | T11: =IF(S11=1,ROUND(SUMIF($H$4:$H$503,H11,$E$4:$E$503),2),"") | U11: =IF(S11=1,COUNTIFS($S$4:$S$503,1,$T$4:$T$503,">"&T11)+COUNTIFS($S$4:S11,1,$T$4:T11,T11),"") | V11: =IF(D11=1,MIN(INDEX($R$4:$R$503,MATCH(G11,$G$4:$G$503,0)),IF($AL$7>9,9,999)),"") -> 5 | W11: =IF(OR($I11="",$E11=0),0,IF(OR($J11<W$3,$I11>W$2),0,IF($K11=0,IF(AND($I11>=W$3,$I11<=W$2),$E11,0),$E11*NETWORKDAYS(MAX($I11,W$3),MIN($J11,W$2),Data!$K$4:$K$203)/$K11))) -> 0 | X11: =IF(OR($I11="",$E11=0),0,IF(OR($J11<X$3,$I11>X$2),0,IF($K11=0,IF(AND($I11>=X$3,$I11<=X$2),$E11,0),$E11*NETWORKDAYS(MAX($I11,X$3),MIN($J11,X$2),Data!$K$4:$K$203)/$K11))) -> 45 | Y11: =IF(OR($I11="",$E11=0),0,IF(OR($J11<Y$3,$I11>Y$2),0,IF($K11=0,IF(AND($I11>=Y$3,$I11<=Y$2),$E11,0),$E11*NETWORKDAYS(MAX($I11,Y$3),MIN($J11,Y$2),Data!$K$4:$K$203)/$K11))) -> 63 | Z11: =IF(OR($I11="",$E11=0),0,IF(OR($J11<Z$3,$I11>Z$2),0,IF($K11=0,IF(AND($I11>=Z$3,$I11<=Z$2),$E11,0),$E11*NETWORKDAYS(MAX($I11,Z$3),MIN($J11,Z$2),Data!$K$4:$K$203)/$K11))) -> 42 | AA11: =IF(OR($I11="",$E11=0),0,IF(OR($J11<AA$3,$I11>AA$2),0,IF($K11=0,IF(AND($I11>=AA$3,$I11<=AA$2),$E11,0),$E11*NETWORKDAYS(MAX($I11,AA$3),MIN($J11,AA$2),Data!$K$4:$K$203)/$K11))) -> 0 | AB11: =IF(OR($I11="",$E11=0),0,IF(OR($J11<AB$3,$I11>AB$2),0,IF($K11=0,IF(AND($I11>=AB$3,$I11<=AB$2),$E11,0),$E11*NETWORKDAYS(MAX($I11,AB$3),MIN($J11,AB$2),Data!$K$4:$K$203)/$K11))) -> 0 | AC11: =IF(OR($I11="",$E11=0),0,IF(OR($J11<AC$3,$I11>AC$2),0,IF($K11=0,IF(AND($I11>=AC$3,$I11<=AC$2),$E11,0),$E11*NETWORKDAYS(MAX($I11,AC$3),MIN($J11,AC$2),Data!$K$4:$K$203)/$K11))) -> 0 | AD11: =IF(OR($I11="",$E11=0),0,IF(OR($J11<AD$3,$I11>AD$2),0,IF($K11=0,IF(AND($I11>=AD$3,$I11<=AD$2),$E11,0),$E11*NETWORKDAYS(MAX($I11,AD$3),MIN($J11,AD$2),Data!$K$4:$K$203)/$K11))) -> 0 | ... AH11: =IF(OR($I11="",$E11=0),0,IF(OR($J11<AH$3,$I11>AH$2),0,IF($K11=0,IF(AND($I11>=AH$3,$I11<=AH$2),$E11,0),$E11*NETWORKDAYS(MAX($I11,AH$3),MIN($J11,AH$2),Data!$K$4:$K$203)/$K11))) -> 0 | AI11: =SUM(W11:AH11) -> 150 | AK11: Avancement moyen (moyenne simple des affaires) | AL11: =IF(AL5=0,0,SUM(EU4:EU503)/AL5) -> 0.11120448 | AN11: 8 | AO11: =AD$3 -> 46478 | AP11: =SUM(AD4:AD503) -> 416.60858 | AQ11: =SUMPRODUCT((AD4:AD503>0)/(COUNTIFS($EN$4:$EN$503,$EN$4:$EN$503,AD4:AD503,">0")+(AD4:AD503<=0))) -> 7 | AS11: 8 | AT11: =IF(AS11>$AL$7,"",INDEX($G$4:$G$503,MATCH(AS11,$R$4:$R$503,0))) | AU11: =SUMIF($V$4:$V$503,AS11,$E$4:$E$503) -> 0 | AV11: =IF($AL$4=0,0,AU11/$AL$4) -> 0 | AW11: =SUMIF($V$4:$V$503,$AS11,W$4:W$503) -> 0 | AX11: =SUMIF($V$4:$V$503,$AS11,X$4:X$503) -> 0 | AY11: =SUMIF($V$4:$V$503,$AS11,Y$4:Y$503) -> 0 | AZ11: =SUMIF($V$4:$V$503,$AS11,Z$4:Z$503) -> 0 | BA11: =SUMIF($V$4:$V$503,$AS11,AA$4:AA$503) -> 0 | BB11: =SUMIF($V$4:$V$503,$AS11,AB$4:AB$503) -> 0 | BC11: =SUMIF($V$4:$V$503,$AS11,AC$4:AC$503) -> 0 | BD11: =SUMIF($V$4:$V$503,$AS11,AD$4:AD$503) -> 0 | ... BH11: =SUMIF($V$4:$V$503,$AS11,AH$4:AH$503) -> 0 | BK11: 8 | BL11: =IF(BK11>$AL$6,"",IF($AL$6>8,"+ "&($AL$6-7)&" autres",INDEX($F$4:$F$503,MATCH(BK11,$O$4:$O$503,0)))) | BM11: =IF(BL11="","",IF($AL$6>8,$AL$4-SUM(BM4:BM10),INDEX($N$4:$N$503,MATCH(BK11,$O$4:$O$503,0)))) | BO11: 8 | BP11: =IF(BO11>$AL$7,"",IF($AL$7>8,"+ "&($AL$7-7)&" autres projets",INDEX($G$4:$G$503,MATCH(BO11,$R$4:$R$503,0)))) | BQ11: =IF(BP11="","",IF($AL$7>8,$AL$4-SUM(BQ4:BQ10),INDEX($Q$4:$Q$503,MATCH(BO11,$R$4:$R$503,0)))) | BW11: 8 | BX11: =IFERROR(MATCH(BW11,$EQ$4:$EQ$503,0),"") -> 23 | BZ11: =IF(D11=1,IF(TRIM(INDEX(Charge!$K:$K,ROW()))<>"",TRIM(INDEX(Charge!$K:$K,ROW())),IF(TRIM(INDEX(Charge!$L:$L,ROW()))<>"",TRIM(INDEX(Charge!$L:$L,ROW())),"(non affecté)")),"") -> Hugo Mercier | CA11: =IF(AND($CD$4<>"",BZ11=$CD$4),COUNTIFS($BZ$4:$BZ$503,$CD$4,$L$4:$L$503,"<"&L11)+1,"") | CC11: Charge projets sur la période affichée (h) | CD11: =SUM(CI4:CI15) -> 420 | CF11: 8 | CG11: =AD$3 -> 46478 | CH11: =IF($CD$4="",0,$CD$7) -> 20 | CI11: =IF($CD$4="",0,SUMIF($BZ$4:$BZ$503,$CD$4,AD$4:AD$503)) -> 0 | CJ11: =CH11+CI11 -> 20 | CK11: =IF($CD$4="",0,$CD$6) -> 120 | CL11: =IF(CN11<0,MAX(0,MIN(CI11,CK11-CH11)),CI11) -> 0 | CM11: =CI11-CL11 -> 0 | CN11: =CK11-CP11 -> 100 | CO11: =IF(CK11<=0,IF(CP11>0,9.99,0),CP11/CK11) -> 0.16666667 | CP11: =ROUND(CJ11,0) -> 20 | CQ11: =IF(CN11<0,CF11,"") | CS11: 8 | CT11: =IF(OR(FA11="",COUNTIF($FA$4:FA10,FA11)>0),"",FA11) -> Karim Haddad | CU11: =IF(CT11="","",IF(FB11="Interne",IF(ISNUMBER(INDEX(Data!$F:$F,11)),INDEX(Data!$F:$F,11),p_HeuresETP),IF(ISNUMBER(INDEX(Data!$I:$I,11-$CD$23)),INDEX(Data!$I:$I,11-$CD$23),p_HeuresETP))) -> 120 | CV11: =IF(CT11="","",IF(FB11="Interne",IF(ISNUMBER(INDEX(Data!$G:$G,11)),INDEX(Data!$G:$G,11),p_ChargeFixe),IF(ISNUMBER(INDEX(Data!$J:$J,11-$CD$23)),INDEX(Data!$J:$J,11-$CD$23),p_ChargeFixe))) -> 20 | CW11: =IF($CT11="","",SUMIF($BZ$4:$BZ$503,$CT11,W$4:W$503)) -> 0 | CX11: =IF($CT11="","",SUMIF($BZ$4:$BZ$503,$CT11,X$4:X$503)) -> 0 | CY11: =IF($CT11="","",SUMIF($BZ$4:$BZ$503,$CT11,Y$4:Y$503)) -> 0 | CZ11: =IF($CT11="","",SUMIF($BZ$4:$BZ$503,$CT11,Z$4:Z$503)) -> 0 | DA11: =IF($CT11="","",SUMIF($BZ$4:$BZ$503,$CT11,AA$4:AA$503)) -> 21.95122 | DB11: =IF($CT11="","",SUMIF($BZ$4:$BZ$503,$CT11,AB$4:AB$503)) -> 43.902439 | DC11: =IF($CT11="","",SUMIF($BZ$4:$BZ$503,$CT11,AC$4:AC$503)) -> 40.396341 | DD11: =IF($CT11="","",SUMIF($BZ$4:$BZ$503,$CT11,AD$4:AD$503)) -> 27.5 | ... DH11: =IF($CT11="","",SUMIF($BZ$4:$BZ$503,$CT11,AH$4:AH$503)) -> 27.5 | DI11: =IF($CT11="","",IF($CU11<=0,IF(ROUND($CV11+CW11,0)>0,9.99,0),ROUND($CV11+CW11,0)/$CU11)) -> 0.16666667 | DJ11: =IF($CT11="","",IF($CU11<=0,IF(ROUND($CV11+CX11,0)>0,9.99,0),ROUND($CV11+CX11,0)/$CU11)) -> 0.16666667 | DK11: =IF($CT11="","",IF($CU11<=0,IF(ROUND($CV11+CY11,0)>0,9.99,0),ROUND($CV11+CY11,0)/$CU11)) -> 0.16666667 | DL11: =IF($CT11="","",IF($CU11<=0,IF(ROUND($CV11+CZ11,0)>0,9.99,0),ROUND($CV11+CZ11,0)/$CU11)) -> 0.16666667 | DM11: =IF($CT11="","",IF($CU11<=0,IF(ROUND($CV11+DA11,0)>0,9.99,0),ROUND($CV11+DA11,0)/$CU11)) -> 0.35 | DN11: =IF($CT11="","",IF($CU11<=0,IF(ROUND($CV11+DB11,0)>0,9.99,0),ROUND($CV11+DB11,0)/$CU11)) -> 0.53333333 | DO11: =IF($CT11="","",IF($CU11<=0,IF(ROUND($CV11+DC11,0)>0,9.99,0),ROUND($CV11+DC11,0)/$CU11)) -> 0.5 | DP11: =IF($CT11="","",IF($CU11<=0,IF(ROUND($CV11+DD11,0)>0,9.99,0),ROUND($CV11+DD11,0)/$CU11)) -> 0.4 | ... DT11: =IF($CT11="","",IF($CU11<=0,IF(ROUND($CV11+DH11,0)>0,9.99,0),ROUND($CV11+DH11,0)/$CU11)) -> 0.4 | DU11: =IF(CT11="","",MAX(DI11:DT11)) -> 0.53333333 | DV11: =IF(CT11="","",SUM(CW11:DH11)) -> 242.5 | DX11: 8 | DY11: =IFERROR(MATCH(DX11,$CA$4:$CA$503,0),"") | DZ11: =IF(DY11="","",INDEX(Charge!$B:$B,DY11+3)&"") | EA11: =IF(DY11="","",INDEX(Charge!$C:$C,DY11+3)&"") | EB11: =IF(DY11="","",INDEX(Charge!$D:$D,DY11+3)&"") | EC11: =IF(DY11="","",INDEX(Charge!$A:$A,DY11+3)&"") | ED11: =IF(DY11="","",INDEX($E$4:$E$503,DY11)) | EE11: =IF(DY11="","",INDEX($AI$4:$AI$503,DY11)) | EF11: =IF(DY11="","",IF(ISNUMBER(INDEX(Charge!$N:$N,DY11+3)),INDEX(Charge!$N:$N,DY11+3),"—")) | EG11: =IF(DY11="","",IF(ISNUMBER(INDEX(Charge!$F:$F,DY11+3)),INDEX(Charge!$F:$F,DY11+3),"—")) | EH11: =IF(DY11="","",INDEX($C$4:$C$503,DY11)) | EJ11: =TRIM(INDEX(Data!$E:$E,ROW())) | EK11: =TRIM(INDEX(Data!$H:$H,ROW())) | EM11: =IF(D11=1,IF(TRIM(INDEX(Charge!$K:$K,ROW()))<>"","Interne",IF(TRIM(INDEX(Charge!$L:$L,ROW()))<>"","Externe","Non affecté")),"") -> Interne | EN11: =IF(D11=1,LEFT(SUBSTITUTE(SUBSTITUTE(SUBSTITUTE(TRIM(SUBSTITUTE(INDEX(Charge!$B:$B,ROW()),CHAR(160)," "))&" | "&TRIM(SUBSTITUTE(INDEX(Charge!$C:$C,ROW()),CHAR(160)," "))&" | "&TRIM(SUBSTITUTE(INDEX(Charge!$D:$D,ROW()),CHAR(160)," ")),"~","-"),"*","+"),"?","!"),240),"") -> CASSIOPÉE | Rétrofit ligne 2 | Convoyeur | EO11: =IF(EN11="",0,IF(COUNTIF($EN$4:EN11,EN11)=1,1,0)) -> 1 | EP11: =IF(EO11=1,ROUND(SUMIF($EN$4:$EN$503,EN11,$E$4:$E$503),2),"") -> 150 | EQ11: =IF(EO11=1,COUNTIFS($EO$4:$EO$503,1,$EP$4:$EP$503,">"&EP11)+COUNTIFS($EO$4:EO11,1,$EP$4:EP11,EP11),"") -> 11 | ER11: =IF(EO11=1,COUNTIFS($EN$4:$EN$503,EN11,$EM$4:$EM$503,"Interne",$FE$4:$FE$503,1),"") -> 1 | ES11: =IF(EO11=1,COUNTIFS($EN$4:$EN$503,EN11,$EM$4:$EM$503,"Externe",$FE$4:$FE$503,1),"") -> 0 | ET11: =IF(EO11=1,IF(ER11+ES11=0,"à affecter",IF(ER11=0,ES11&" ext.",(ER11+ES11)&IF(ES11>0," dont "&ES11&" ext.",""))&IF(COUNTIFS($EN$4:$EN$503,EN11,$EM$4:$EM$503,"Non affecté")>0," + à affecter","")),"") -> 1 | EU11: =IF(EO11=1,IF(EP11>0,SUMPRODUCT(($EN$4:$EN$503=EN11)*$E$4:$E$503*$C$4:$C$503)/EP11,AVERAGEIF($EN$4:$EN$503,EN11,$C$4:$C$503)),"") -> 0.5 | EV11: =IF(ISNUMBER(I11),I11,2958465) -> 46307 | EW11: =IF(EO11=1,SUMPRODUCT(MIN(($EN$4:$EN$503=EN11)*$EV$4:$EV$503+($EN$4:$EN$503<>EN11)*2958465)),"") -> 46307 | EX11: =IF(AND(D11=1,ISNUMBER(INDEX(Charge!$F:$F,ROW()))),INDEX(Charge!$F:$F,ROW()),0) -> 46374 | EY11: =IF(EO11=1,SUMPRODUCT(MAX(($EN$4:$EN$503=EN11)*$EX$4:$EX$503)),"") -> 46374 | FA11: =IF(8<=$CD$23,INDEX($EJ$4:$EJ$203,8),IF(8-$CD$23<=$CD$26,INDEX($EK$4:$EK$203,8-$CD$23),"")) -> Karim Haddad | FB11: =IF(FA11="","",IF(8<=$CD$23,"Interne","Externe")) -> Externe | FD11: =IF(AND(B11=1,TRIM(INDEX(Charge!$K:$K,ROW()))<>"",TRIM(INDEX(Charge!$L:$L,ROW()))<>""),1,0) -> 0 | FE11: =IF(OR(EN11="",BZ11="(non affecté)"),0,IF(COUNTIFS($EN$4:EN11,EN11,$BZ$4:BZ11,BZ11)=1,1,0)) -> 1
A12: =ROW() -> 12 | B12: =IF(TRIM(INDEX(Charge!$B:$B,ROW()))<>"",1,0) -> 1 | C12: =IF(B12=1,MIN(1,MAX(0,N(INDEX(Charge!$O:$O,ROW())))),0) -> 0.05 | D12: =IF(B12=1,IF(OR(p_Perimetre="Tous les projets",C12<1),1,0),0) -> 1 | E12: =IF(D12=1,MAX(0,N(INDEX(Charge!$M:$M,ROW()))),0) -> 160 | F12: =IF(D12=1,IF(TRIM(INDEX(Charge!$A:$A,ROW()))="","(non renseigné)",TRIM(INDEX(Charge!$A:$A,ROW()))),"") -> Sophie Lefèvre | G12: =IF(D12=1,TRIM(INDEX(Charge!$B:$B,ROW())),"") -> CASSIOPÉE | H12: =IF(D12=1,IF(TRIM(INDEX(Charge!$E:$E,ROW()))="","(non renseigné)",TRIM(INDEX(Charge!$E:$E,ROW()))),"") -> Étude de conception | I12: =IF(AND(D12=1,ISNUMBER(INDEX(Charge!$N:$N,ROW()))),INDEX(Charge!$N:$N,ROW()),"") -> 46357 | J12: =IF(I12="","",IF(AND(p_Repartition="Lissée jusqu'à la date de besoin",ISNUMBER(INDEX(Charge!$F:$F,ROW()))),IF(INDEX(Charge!$F:$F,ROW())>=I12,INDEX(Charge!$F:$F,ROW()),I12),I12)) -> 46444 | K12: =IF(I12="","",NETWORKDAYS(I12,J12,Data!$K$4:$K$203)) -> 64 | L12: =IF(D12=1,COUNTIFS($D$4:$D$503,1,$E$4:$E$503,">"&E12)+COUNTIFS($D$4:$D12,1,$E$4:$E12,E12),"") -> 9 | M12: =IF(F12="",0,IF(COUNTIF($F$4:F12,F12)=1,1,0)) -> 0 | N12: =IF(M12=1,ROUND(SUMIF($F$4:$F$503,F12,$E$4:$E$503),2),"") | O12: =IF(M12=1,COUNTIFS($M$4:$M$503,1,$N$4:$N$503,">"&N12)+COUNTIFS($M$4:M12,1,$N$4:N12,N12),"") | P12: =IF(G12="",0,IF(COUNTIF($G$4:G12,G12)=1,1,0)) -> 0 | Q12: =IF(P12=1,ROUND(SUMIF($G$4:$G$503,G12,$E$4:$E$503),2),"") | R12: =IF(P12=1,COUNTIFS($P$4:$P$503,1,$Q$4:$Q$503,">"&Q12)+COUNTIFS($P$4:P12,1,$Q$4:Q12,Q12),"") | S12: =IF(H12="",0,IF(COUNTIF($H$4:H12,H12)=1,1,0)) -> 0 | T12: =IF(S12=1,ROUND(SUMIF($H$4:$H$503,H12,$E$4:$E$503),2),"") | U12: =IF(S12=1,COUNTIFS($S$4:$S$503,1,$T$4:$T$503,">"&T12)+COUNTIFS($S$4:S12,1,$T$4:T12,T12),"") | V12: =IF(D12=1,MIN(INDEX($R$4:$R$503,MATCH(G12,$G$4:$G$503,0)),IF($AL$7>9,9,999)),"") -> 5 | W12: =IF(OR($I12="",$E12=0),0,IF(OR($J12<W$3,$I12>W$2),0,IF($K12=0,IF(AND($I12>=W$3,$I12<=W$2),$E12,0),$E12*NETWORKDAYS(MAX($I12,W$3),MIN($J12,W$2),Data!$K$4:$K$203)/$K12))) -> 0 | X12: =IF(OR($I12="",$E12=0),0,IF(OR($J12<X$3,$I12>X$2),0,IF($K12=0,IF(AND($I12>=X$3,$I12<=X$2),$E12,0),$E12*NETWORKDAYS(MAX($I12,X$3),MIN($J12,X$2),Data!$K$4:$K$203)/$K12))) -> 0 | Y12: =IF(OR($I12="",$E12=0),0,IF(OR($J12<Y$3,$I12>Y$2),0,IF($K12=0,IF(AND($I12>=Y$3,$I12<=Y$2),$E12,0),$E12*NETWORKDAYS(MAX($I12,Y$3),MIN($J12,Y$2),Data!$K$4:$K$203)/$K12))) -> 0 | Z12: =IF(OR($I12="",$E12=0),0,IF(OR($J12<Z$3,$I12>Z$2),0,IF($K12=0,IF(AND($I12>=Z$3,$I12<=Z$2),$E12,0),$E12*NETWORKDAYS(MAX($I12,Z$3),MIN($J12,Z$2),Data!$K$4:$K$203)/$K12))) -> 57.5 | AA12: =IF(OR($I12="",$E12=0),0,IF(OR($J12<AA$3,$I12>AA$2),0,IF($K12=0,IF(AND($I12>=AA$3,$I12<=AA$2),$E12,0),$E12*NETWORKDAYS(MAX($I12,AA$3),MIN($J12,AA$2),Data!$K$4:$K$203)/$K12))) -> 52.5 | AB12: =IF(OR($I12="",$E12=0),0,IF(OR($J12<AB$3,$I12>AB$2),0,IF($K12=0,IF(AND($I12>=AB$3,$I12<=AB$2),$E12,0),$E12*NETWORKDAYS(MAX($I12,AB$3),MIN($J12,AB$2),Data!$K$4:$K$203)/$K12))) -> 50 | AC12: =IF(OR($I12="",$E12=0),0,IF(OR($J12<AC$3,$I12>AC$2),0,IF($K12=0,IF(AND($I12>=AC$3,$I12<=AC$2),$E12,0),$E12*NETWORKDAYS(MAX($I12,AC$3),MIN($J12,AC$2),Data!$K$4:$K$203)/$K12))) -> 0 | AD12: =IF(OR($I12="",$E12=0),0,IF(OR($J12<AD$3,$I12>AD$2),0,IF($K12=0,IF(AND($I12>=AD$3,$I12<=AD$2),$E12,0),$E12*NETWORKDAYS(MAX($I12,AD$3),MIN($J12,AD$2),Data!$K$4:$K$203)/$K12))) -> 0 | ... AH12: =IF(OR($I12="",$E12=0),0,IF(OR($J12<AH$3,$I12>AH$2),0,IF($K12=0,IF(AND($I12>=AH$3,$I12<=AH$2),$E12,0),$E12*NETWORKDAYS(MAX($I12,AH$3),MIN($J12,AH$2),Data!$K$4:$K$203)/$K12))) -> 0 | AI12: =SUM(W12:AH12) -> 160 | AK12: Avancement moyen pondéré par la charge | AL12: =IF(AL4=0,0,AL9/AL4) -> 0.098263386 | AN12: 9 | AO12: =AE$3 -> 46508 | AP12: =SUM(AE4:AE503) -> 322.11612 | AQ12: =SUMPRODUCT((AE4:AE503>0)/(COUNTIFS($EN$4:$EN$503,$EN$4:$EN$503,AE4:AE503,">0")+(AE4:AE503<=0))) -> 6 | AS12: 9 | AT12: =IF(AS12>$AL$7,"",IF($AL$7>9,"Autres projets ("&($AL$7-8)&")",INDEX($G$4:$G$503,MATCH(AS12,$R$4:$R$503,0)))) | AU12: =SUMIF($V$4:$V$503,AS12,$E$4:$E$503) -> 0 | AV12: =IF($AL$4=0,0,AU12/$AL$4) -> 0 | AW12: =SUMIF($V$4:$V$503,$AS12,W$4:W$503) -> 0 | AX12: =SUMIF($V$4:$V$503,$AS12,X$4:X$503) -> 0 | AY12: =SUMIF($V$4:$V$503,$AS12,Y$4:Y$503) -> 0 | AZ12: =SUMIF($V$4:$V$503,$AS12,Z$4:Z$503) -> 0 | BA12: =SUMIF($V$4:$V$503,$AS12,AA$4:AA$503) -> 0 | BB12: =SUMIF($V$4:$V$503,$AS12,AB$4:AB$503) -> 0 | BC12: =SUMIF($V$4:$V$503,$AS12,AC$4:AC$503) -> 0 | BD12: =SUMIF($V$4:$V$503,$AS12,AD$4:AD$503) -> 0 | ... BH12: =SUMIF($V$4:$V$503,$AS12,AH$4:AH$503) -> 0 | BW12: 9 | BX12: =IFERROR(MATCH(BW12,$EQ$4:$EQ$503,0),"") -> 4 | BZ12: =IF(D12=1,IF(TRIM(INDEX(Charge!$K:$K,ROW()))<>"",TRIM(INDEX(Charge!$K:$K,ROW())),IF(TRIM(INDEX(Charge!$L:$L,ROW()))<>"",TRIM(INDEX(Charge!$L:$L,ROW())),"(non affecté)")),"") -> Emma Faure | CA12: =IF(AND($CD$4<>"",BZ12=$CD$4),COUNTIFS($BZ$4:$BZ$503,$CD$4,$L$4:$L$503,"<"&L12)+1,"") | CC12: Mois le plus chargé : charge totale (h) | CD12: =MAX(CJ4:CJ15) -> 121.9697 | CF12: 9 | CG12: =AE$3 -> 46508 | CH12: =IF($CD$4="",0,$CD$7) -> 20 | CI12: =IF($CD$4="",0,SUMIF($BZ$4:$BZ$503,$CD$4,AE$4:AE$503)) -> 0 | CJ12: =CH12+CI12 -> 20 | CK12: =IF($CD$4="",0,$CD$6) -> 120 | CL12: =IF(CN12<0,MAX(0,MIN(CI12,CK12-CH12)),CI12) -> 0 | CM12: =CI12-CL12 -> 0 | CN12: =CK12-CP12 -> 100 | CO12: =IF(CK12<=0,IF(CP12>0,9.99,0),CP12/CK12) -> 0.16666667 | CP12: =ROUND(CJ12,0) -> 20 | CQ12: =IF(CN12<0,CF12,"") | CS12: 9 | CT12: =IF(OR(FA12="",COUNTIF($FA$4:FA11,FA12)>0),"",FA12) | CU12: =IF(CT12="","",IF(FB12="Interne",IF(ISNUMBER(INDEX(Data!$F:$F,12)),INDEX(Data!$F:$F,12),p_HeuresETP),IF(ISNUMBER(INDEX(Data!$I:$I,12-$CD$23)),INDEX(Data!$I:$I,12-$CD$23),p_HeuresETP))) | CV12: =IF(CT12="","",IF(FB12="Interne",IF(ISNUMBER(INDEX(Data!$G:$G,12)),INDEX(Data!$G:$G,12),p_ChargeFixe),IF(ISNUMBER(INDEX(Data!$J:$J,12-$CD$23)),INDEX(Data!$J:$J,12-$CD$23),p_ChargeFixe))) | CW12: =IF($CT12="","",SUMIF($BZ$4:$BZ$503,$CT12,W$4:W$503)) | CX12: =IF($CT12="","",SUMIF($BZ$4:$BZ$503,$CT12,X$4:X$503)) | CY12: =IF($CT12="","",SUMIF($BZ$4:$BZ$503,$CT12,Y$4:Y$503)) | CZ12: =IF($CT12="","",SUMIF($BZ$4:$BZ$503,$CT12,Z$4:Z$503)) | DA12: =IF($CT12="","",SUMIF($BZ$4:$BZ$503,$CT12,AA$4:AA$503)) | DB12: =IF($CT12="","",SUMIF($BZ$4:$BZ$503,$CT12,AB$4:AB$503)) | DC12: =IF($CT12="","",SUMIF($BZ$4:$BZ$503,$CT12,AC$4:AC$503)) | DD12: =IF($CT12="","",SUMIF($BZ$4:$BZ$503,$CT12,AD$4:AD$503)) | ... DH12: =IF($CT12="","",SUMIF($BZ$4:$BZ$503,$CT12,AH$4:AH$503)) | DI12: =IF($CT12="","",IF($CU12<=0,IF(ROUND($CV12+CW12,0)>0,9.99,0),ROUND($CV12+CW12,0)/$CU12)) | DJ12: =IF($CT12="","",IF($CU12<=0,IF(ROUND($CV12+CX12,0)>0,9.99,0),ROUND($CV12+CX12,0)/$CU12)) | DK12: =IF($CT12="","",IF($CU12<=0,IF(ROUND($CV12+CY12,0)>0,9.99,0),ROUND($CV12+CY12,0)/$CU12)) | DL12: =IF($CT12="","",IF($CU12<=0,IF(ROUND($CV12+CZ12,0)>0,9.99,0),ROUND($CV12+CZ12,0)/$CU12)) | DM12: =IF($CT12="","",IF($CU12<=0,IF(ROUND($CV12+DA12,0)>0,9.99,0),ROUND($CV12+DA12,0)/$CU12)) | DN12: =IF($CT12="","",IF($CU12<=0,IF(ROUND($CV12+DB12,0)>0,9.99,0),ROUND($CV12+DB12,0)/$CU12)) | DO12: =IF($CT12="","",IF($CU12<=0,IF(ROUND($CV12+DC12,0)>0,9.99,0),ROUND($CV12+DC12,0)/$CU12)) | DP12: =IF($CT12="","",IF($CU12<=0,IF(ROUND($CV12+DD12,0)>0,9.99,0),ROUND($CV12+DD12,0)/$CU12)) | ... DT12: =IF($CT12="","",IF($CU12<=0,IF(ROUND($CV12+DH12,0)>0,9.99,0),ROUND($CV12+DH12,0)/$CU12)) | DU12: =IF(CT12="","",MAX(DI12:DT12)) | DV12: =IF(CT12="","",SUM(CW12:DH12)) | DX12: 9 | DY12: =IFERROR(MATCH(DX12,$CA$4:$CA$503,0),"") | DZ12: =IF(DY12="","",INDEX(Charge!$B:$B,DY12+3)&"") | EA12: =IF(DY12="","",INDEX(Charge!$C:$C,DY12+3)&"") | EB12: =IF(DY12="","",INDEX(Charge!$D:$D,DY12+3)&"") | EC12: =IF(DY12="","",INDEX(Charge!$A:$A,DY12+3)&"") | ED12: =IF(DY12="","",INDEX($E$4:$E$503,DY12)) | EE12: =IF(DY12="","",INDEX($AI$4:$AI$503,DY12)) | EF12: =IF(DY12="","",IF(ISNUMBER(INDEX(Charge!$N:$N,DY12+3)),INDEX(Charge!$N:$N,DY12+3),"—")) | EG12: =IF(DY12="","",IF(ISNUMBER(INDEX(Charge!$F:$F,DY12+3)),INDEX(Charge!$F:$F,DY12+3),"—")) | EH12: =IF(DY12="","",INDEX($C$4:$C$503,DY12)) | EJ12: =TRIM(INDEX(Data!$E:$E,ROW())) | EK12: =TRIM(INDEX(Data!$H:$H,ROW())) | EM12: =IF(D12=1,IF(TRIM(INDEX(Charge!$K:$K,ROW()))<>"","Interne",IF(TRIM(INDEX(Charge!$L:$L,ROW()))<>"","Externe","Non affecté")),"") -> Interne | EN12: =IF(D12=1,LEFT(SUBSTITUTE(SUBSTITUTE(SUBSTITUTE(TRIM(SUBSTITUTE(INDEX(Charge!$B:$B,ROW()),CHAR(160)," "))&" | "&TRIM(SUBSTITUTE(INDEX(Charge!$C:$C,ROW()),CHAR(160)," "))&" | "&TRIM(SUBSTITUTE(INDEX(Charge!$D:$D,ROW()),CHAR(160)," ")),"~","-"),"*","+"),"?","!"),240),"") -> CASSIOPÉE | Rétrofit ligne 2 | Poste de contrôle | EO12: =IF(EN12="",0,IF(COUNTIF($EN$4:EN12,EN12)=1,1,0)) -> 1 | EP12: =IF(EO12=1,ROUND(SUMIF($EN$4:$EN$503,EN12,$E$4:$E$503),2),"") -> 240 | EQ12: =IF(EO12=1,COUNTIFS($EO$4:$EO$503,1,$EP$4:$EP$503,">"&EP12)+COUNTIFS($EO$4:EO12,1,$EP$4:EP12,EP12),"") -> 6 | ER12: =IF(EO12=1,COUNTIFS($EN$4:$EN$503,EN12,$EM$4:$EM$503,"Interne",$FE$4:$FE$503,1),"") -> 1 | ES12: =IF(EO12=1,COUNTIFS($EN$4:$EN$503,EN12,$EM$4:$EM$503,"Externe",$FE$4:$FE$503,1),"") -> 1 | ET12: =IF(EO12=1,IF(ER12+ES12=0,"à affecter",IF(ER12=0,ES12&" ext.",(ER12+ES12)&IF(ES12>0," dont "&ES12&" ext.",""))&IF(COUNTIFS($EN$4:$EN$503,EN12,$EM$4:$EM$503,"Non affecté")>0," + à affecter","")),"") -> 2 dont 1 ext. | EU12: =IF(EO12=1,IF(EP12>0,SUMPRODUCT(($EN$4:$EN$503=EN12)*$E$4:$E$503*$C$4:$C$503)/EP12,AVERAGEIF($EN$4:$EN$503,EN12,$C$4:$C$503)),"") -> 0.033333333 | EV12: =IF(ISNUMBER(I12),I12,2958465) -> 46357 | EW12: =IF(EO12=1,SUMPRODUCT(MIN(($EN$4:$EN$503=EN12)*$EV$4:$EV$503+($EN$4:$EN$503<>EN12)*2958465)),"") -> 46357 | EX12: =IF(AND(D12=1,ISNUMBER(INDEX(Charge!$F:$F,ROW()))),INDEX(Charge!$F:$F,ROW()),0) -> 46444 | EY12: =IF(EO12=1,SUMPRODUCT(MAX(($EN$4:$EN$503=EN12)*$EX$4:$EX$503)),"") -> 46444 | FA12: =IF(9<=$CD$23,INDEX($EJ$4:$EJ$203,9),IF(9-$CD$23<=$CD$26,INDEX($EK$4:$EK$203,9-$CD$23),"")) | FB12: =IF(FA12="","",IF(9<=$CD$23,"Interne","Externe")) | FD12: =IF(AND(B12=1,TRIM(INDEX(Charge!$K:$K,ROW()))<>"",TRIM(INDEX(Charge!$L:$L,ROW()))<>""),1,0) -> 0 | FE12: =IF(OR(EN12="",BZ12="(non affecté)"),0,IF(COUNTIFS($EN$4:EN12,EN12,$BZ$4:BZ12,BZ12)=1,1,0)) -> 1
A13: =ROW() -> 13 | B13: =IF(TRIM(INDEX(Charge!$B:$B,ROW()))<>"",1,0) -> 1 | C13: =IF(B13=1,MIN(1,MAX(0,N(INDEX(Charge!$O:$O,ROW())))),0) -> 0 | D13: =IF(B13=1,IF(OR(p_Perimetre="Tous les projets",C13<1),1,0),0) -> 1 | E13: =IF(D13=1,MAX(0,N(INDEX(Charge!$M:$M,ROW()))),0) -> 80 | F13: =IF(D13=1,IF(TRIM(INDEX(Charge!$A:$A,ROW()))="","(non renseigné)",TRIM(INDEX(Charge!$A:$A,ROW()))),"") -> Sophie Lefèvre | G13: =IF(D13=1,TRIM(INDEX(Charge!$B:$B,ROW())),"") -> CASSIOPÉE | H13: =IF(D13=1,IF(TRIM(INDEX(Charge!$E:$E,ROW()))="","(non renseigné)",TRIM(INDEX(Charge!$E:$E,ROW()))),"") -> Étude de conception | I13: =IF(AND(D13=1,ISNUMBER(INDEX(Charge!$N:$N,ROW()))),INDEX(Charge!$N:$N,ROW()),"") -> 46357 | J13: =IF(I13="","",IF(AND(p_Repartition="Lissée jusqu'à la date de besoin",ISNUMBER(INDEX(Charge!$F:$F,ROW()))),IF(INDEX(Charge!$F:$F,ROW())>=I13,INDEX(Charge!$F:$F,ROW()),I13),I13)) -> 46444 | K13: =IF(I13="","",NETWORKDAYS(I13,J13,Data!$K$4:$K$203)) -> 64 | L13: =IF(D13=1,COUNTIFS($D$4:$D$503,1,$E$4:$E$503,">"&E13)+COUNTIFS($D$4:$D13,1,$E$4:$E13,E13),"") -> 18 | M13: =IF(F13="",0,IF(COUNTIF($F$4:F13,F13)=1,1,0)) -> 0 | N13: =IF(M13=1,ROUND(SUMIF($F$4:$F$503,F13,$E$4:$E$503),2),"") | O13: =IF(M13=1,COUNTIFS($M$4:$M$503,1,$N$4:$N$503,">"&N13)+COUNTIFS($M$4:M13,1,$N$4:N13,N13),"") | P13: =IF(G13="",0,IF(COUNTIF($G$4:G13,G13)=1,1,0)) -> 0 | Q13: =IF(P13=1,ROUND(SUMIF($G$4:$G$503,G13,$E$4:$E$503),2),"") | R13: =IF(P13=1,COUNTIFS($P$4:$P$503,1,$Q$4:$Q$503,">"&Q13)+COUNTIFS($P$4:P13,1,$Q$4:Q13,Q13),"") | S13: =IF(H13="",0,IF(COUNTIF($H$4:H13,H13)=1,1,0)) -> 0 | T13: =IF(S13=1,ROUND(SUMIF($H$4:$H$503,H13,$E$4:$E$503),2),"") | U13: =IF(S13=1,COUNTIFS($S$4:$S$503,1,$T$4:$T$503,">"&T13)+COUNTIFS($S$4:S13,1,$T$4:T13,T13),"") | V13: =IF(D13=1,MIN(INDEX($R$4:$R$503,MATCH(G13,$G$4:$G$503,0)),IF($AL$7>9,9,999)),"") -> 5 | W13: =IF(OR($I13="",$E13=0),0,IF(OR($J13<W$3,$I13>W$2),0,IF($K13=0,IF(AND($I13>=W$3,$I13<=W$2),$E13,0),$E13*NETWORKDAYS(MAX($I13,W$3),MIN($J13,W$2),Data!$K$4:$K$203)/$K13))) -> 0 | X13: =IF(OR($I13="",$E13=0),0,IF(OR($J13<X$3,$I13>X$2),0,IF($K13=0,IF(AND($I13>=X$3,$I13<=X$2),$E13,0),$E13*NETWORKDAYS(MAX($I13,X$3),MIN($J13,X$2),Data!$K$4:$K$203)/$K13))) -> 0 | Y13: =IF(OR($I13="",$E13=0),0,IF(OR($J13<Y$3,$I13>Y$2),0,IF($K13=0,IF(AND($I13>=Y$3,$I13<=Y$2),$E13,0),$E13*NETWORKDAYS(MAX($I13,Y$3),MIN($J13,Y$2),Data!$K$4:$K$203)/$K13))) -> 0 | Z13: =IF(OR($I13="",$E13=0),0,IF(OR($J13<Z$3,$I13>Z$2),0,IF($K13=0,IF(AND($I13>=Z$3,$I13<=Z$2),$E13,0),$E13*NETWORKDAYS(MAX($I13,Z$3),MIN($J13,Z$2),Data!$K$4:$K$203)/$K13))) -> 28.75 | AA13: =IF(OR($I13="",$E13=0),0,IF(OR($J13<AA$3,$I13>AA$2),0,IF($K13=0,IF(AND($I13>=AA$3,$I13<=AA$2),$E13,0),$E13*NETWORKDAYS(MAX($I13,AA$3),MIN($J13,AA$2),Data!$K$4:$K$203)/$K13))) -> 26.25 | AB13: =IF(OR($I13="",$E13=0),0,IF(OR($J13<AB$3,$I13>AB$2),0,IF($K13=0,IF(AND($I13>=AB$3,$I13<=AB$2),$E13,0),$E13*NETWORKDAYS(MAX($I13,AB$3),MIN($J13,AB$2),Data!$K$4:$K$203)/$K13))) -> 25 | AC13: =IF(OR($I13="",$E13=0),0,IF(OR($J13<AC$3,$I13>AC$2),0,IF($K13=0,IF(AND($I13>=AC$3,$I13<=AC$2),$E13,0),$E13*NETWORKDAYS(MAX($I13,AC$3),MIN($J13,AC$2),Data!$K$4:$K$203)/$K13))) -> 0 | AD13: =IF(OR($I13="",$E13=0),0,IF(OR($J13<AD$3,$I13>AD$2),0,IF($K13=0,IF(AND($I13>=AD$3,$I13<=AD$2),$E13,0),$E13*NETWORKDAYS(MAX($I13,AD$3),MIN($J13,AD$2),Data!$K$4:$K$203)/$K13))) -> 0 | ... AH13: =IF(OR($I13="",$E13=0),0,IF(OR($J13<AH$3,$I13>AH$2),0,IF($K13=0,IF(AND($I13>=AH$3,$I13<=AH$2),$E13,0),$E13*NETWORKDAYS(MAX($I13,AH$3),MIN($J13,AH$2),Data!$K$4:$K$203)/$K13))) -> 0 | AI13: =SUM(W13:AH13) -> 80 | AK13: 1er mois automatique (1er début planifié) | AL13: =IF(COUNT(I4:I503)=0,DATE(YEAR(TODAY()),MONTH(TODAY()),1),DATE(YEAR(MIN(I4:I503)),MONTH(MIN(I4:I503)),1)) -> 46266 | AN13: 10 | AO13: =AF$3 -> 46539 | AP13: =SUM(AF4:AF503) -> 252.5026 | AQ13: =SUMPRODUCT((AF4:AF503>0)/(COUNTIFS($EN$4:$EN$503,$EN$4:$EN$503,AF4:AF503,">0")+(AF4:AF503<=0))) -> 4 | AT13: Total | AU13: =SUM(AU4:AU12) -> 3455 | AW13: =ROUND(SUM(AW4:AW12),0) -> 28 | AX13: =ROUND(SUM(AX4:AX12),0) -> 166 | AY13: =ROUND(SUM(AY4:AY12),0) -> 316 | AZ13: =ROUND(SUM(AZ4:AZ12),0) -> 382 | BA13: =ROUND(SUM(BA4:BA12),0) -> 321 | BB13: =ROUND(SUM(BB4:BB12),0) -> 377 | BC13: =ROUND(SUM(BC4:BC12),0) -> 508 | BD13: =ROUND(SUM(BD4:BD12),0) -> 417 | ... BH13: =ROUND(SUM(BH4:BH12),0) -> 120 | BW13: 10 | BX13: =IFERROR(MATCH(BW13,$EQ$4:$EQ$503,0),"") -> 15 | BZ13: =IF(D13=1,IF(TRIM(INDEX(Charge!$K:$K,ROW()))<>"",TRIM(INDEX(Charge!$K:$K,ROW())),IF(TRIM(INDEX(Charge!$L:$L,ROW()))<>"",TRIM(INDEX(Charge!$L:$L,ROW())),"(non affecté)")),"") -> Paul Girard | CA13: =IF(AND($CD$4<>"",BZ13=$CD$4),COUNTIFS($BZ$4:$BZ$503,$CD$4,$L$4:$L$503,"<"&L13)+1,"") | CC13: Rang du mois le plus chargé | CD13: =MATCH(CD12,CJ4:CJ15,0) -> 3 | CF13: 10 | CG13: =AF$3 -> 46539 | CH13: =IF($CD$4="",0,$CD$7) -> 20 | CI13: =IF($CD$4="",0,SUMIF($BZ$4:$BZ$503,$CD$4,AF$4:AF$503)) -> 0 | CJ13: =CH13+CI13 -> 20 | CK13: =IF($CD$4="",0,$CD$6) -> 120 | CL13: =IF(CN13<0,MAX(0,MIN(CI13,CK13-CH13)),CI13) -> 0 | CM13: =CI13-CL13 -> 0 | CN13: =CK13-CP13 -> 100 | CO13: =IF(CK13<=0,IF(CP13>0,9.99,0),CP13/CK13) -> 0.16666667 | CP13: =ROUND(CJ13,0) -> 20 | CQ13: =IF(CN13<0,CF13,"") | CS13: 10 | CT13: =IF(OR(FA13="",COUNTIF($FA$4:FA12,FA13)>0),"",FA13) | CU13: =IF(CT13="","",IF(FB13="Interne",IF(ISNUMBER(INDEX(Data!$F:$F,13)),INDEX(Data!$F:$F,13),p_HeuresETP),IF(ISNUMBER(INDEX(Data!$I:$I,13-$CD$23)),INDEX(Data!$I:$I,13-$CD$23),p_HeuresETP))) | CV13: =IF(CT13="","",IF(FB13="Interne",IF(ISNUMBER(INDEX(Data!$G:$G,13)),INDEX(Data!$G:$G,13),p_ChargeFixe),IF(ISNUMBER(INDEX(Data!$J:$J,13-$CD$23)),INDEX(Data!$J:$J,13-$CD$23),p_ChargeFixe))) | CW13: =IF($CT13="","",SUMIF($BZ$4:$BZ$503,$CT13,W$4:W$503)) | CX13: =IF($CT13="","",SUMIF($BZ$4:$BZ$503,$CT13,X$4:X$503)) | CY13: =IF($CT13="","",SUMIF($BZ$4:$BZ$503,$CT13,Y$4:Y$503)) | CZ13: =IF($CT13="","",SUMIF($BZ$4:$BZ$503,$CT13,Z$4:Z$503)) | DA13: =IF($CT13="","",SUMIF($BZ$4:$BZ$503,$CT13,AA$4:AA$503)) | DB13: =IF($CT13="","",SUMIF($BZ$4:$BZ$503,$CT13,AB$4:AB$503)) | DC13: =IF($CT13="","",SUMIF($BZ$4:$BZ$503,$CT13,AC$4:AC$503)) | DD13: =IF($CT13="","",SUMIF($BZ$4:$BZ$503,$CT13,AD$4:AD$503)) | ... DH13: =IF($CT13="","",SUMIF($BZ$4:$BZ$503,$CT13,AH$4:AH$503)) | DI13: =IF($CT13="","",IF($CU13<=0,IF(ROUND($CV13+CW13,0)>0,9.99,0),ROUND($CV13+CW13,0)/$CU13)) | DJ13: =IF($CT13="","",IF($CU13<=0,IF(ROUND($CV13+CX13,0)>0,9.99,0),ROUND($CV13+CX13,0)/$CU13)) | DK13: =IF($CT13="","",IF($CU13<=0,IF(ROUND($CV13+CY13,0)>0,9.99,0),ROUND($CV13+CY13,0)/$CU13)) | DL13: =IF($CT13="","",IF($CU13<=0,IF(ROUND($CV13+CZ13,0)>0,9.99,0),ROUND($CV13+CZ13,0)/$CU13)) | DM13: =IF($CT13="","",IF($CU13<=0,IF(ROUND($CV13+DA13,0)>0,9.99,0),ROUND($CV13+DA13,0)/$CU13)) | DN13: =IF($CT13="","",IF($CU13<=0,IF(ROUND($CV13+DB13,0)>0,9.99,0),ROUND($CV13+DB13,0)/$CU13)) | DO13: =IF($CT13="","",IF($CU13<=0,IF(ROUND($CV13+DC13,0)>0,9.99,0),ROUND($CV13+DC13,0)/$CU13)) | DP13: =IF($CT13="","",IF($CU13<=0,IF(ROUND($CV13+DD13,0)>0,9.99,0),ROUND($CV13+DD13,0)/$CU13)) | ... DT13: =IF($CT13="","",IF($CU13<=0,IF(ROUND($CV13+DH13,0)>0,9.99,0),ROUND($CV13+DH13,0)/$CU13)) | DU13: =IF(CT13="","",MAX(DI13:DT13)) | DV13: =IF(CT13="","",SUM(CW13:DH13)) | DX13: 10 | DY13: =IFERROR(MATCH(DX13,$CA$4:$CA$503,0),"") | DZ13: =IF(DY13="","",INDEX(Charge!$B:$B,DY13+3)&"") | EA13: =IF(DY13="","",INDEX(Charge!$C:$C,DY13+3)&"") | EB13: =IF(DY13="","",INDEX(Charge!$D:$D,DY13+3)&"") | EC13: =IF(DY13="","",INDEX(Charge!$A:$A,DY13+3)&"") | ED13: =IF(DY13="","",INDEX($E$4:$E$503,DY13)) | EE13: =IF(DY13="","",INDEX($AI$4:$AI$503,DY13)) | EF13: =IF(DY13="","",IF(ISNUMBER(INDEX(Charge!$N:$N,DY13+3)),INDEX(Charge!$N:$N,DY13+3),"—")) | EG13: =IF(DY13="","",IF(ISNUMBER(INDEX(Charge!$F:$F,DY13+3)),INDEX(Charge!$F:$F,DY13+3),"—")) | EH13: =IF(DY13="","",INDEX($C$4:$C$503,DY13)) | EJ13: =TRIM(INDEX(Data!$E:$E,ROW())) | EK13: =TRIM(INDEX(Data!$H:$H,ROW())) | EM13: =IF(D13=1,IF(TRIM(INDEX(Charge!$K:$K,ROW()))<>"","Interne",IF(TRIM(INDEX(Charge!$L:$L,ROW()))<>"","Externe","Non affecté")),"") -> Externe | EN13: =IF(D13=1,LEFT(SUBSTITUTE(SUBSTITUTE(SUBSTITUTE(TRIM(SUBSTITUTE(INDEX(Charge!$B:$B,ROW()),CHAR(160)," "))&" | "&TRIM(SUBSTITUTE(INDEX(Charge!$C:$C,ROW()),CHAR(160)," "))&" | "&TRIM(SUBSTITUTE(INDEX(Charge!$D:$D,ROW()),CHAR(160)," ")),"~","-"),"*","+"),"?","!"),240),"") -> CASSIOPÉE | Rétrofit ligne 2 | Poste de contrôle | EO13: =IF(EN13="",0,IF(COUNTIF($EN$4:EN13,EN13)=1,1,0)) -> 0 | EP13: =IF(EO13=1,ROUND(SUMIF($EN$4:$EN$503,EN13,$E$4:$E$503),2),"") | EQ13: =IF(EO13=1,COUNTIFS($EO$4:$EO$503,1,$EP$4:$EP$503,">"&EP13)+COUNTIFS($EO$4:EO13,1,$EP$4:EP13,EP13),"") | ER13: =IF(EO13=1,COUNTIFS($EN$4:$EN$503,EN13,$EM$4:$EM$503,"Interne",$FE$4:$FE$503,1),"") | ES13: =IF(EO13=1,COUNTIFS($EN$4:$EN$503,EN13,$EM$4:$EM$503,"Externe",$FE$4:$FE$503,1),"") | ET13: =IF(EO13=1,IF(ER13+ES13=0,"à affecter",IF(ER13=0,ES13&" ext.",(ER13+ES13)&IF(ES13>0," dont "&ES13&" ext.",""))&IF(COUNTIFS($EN$4:$EN$503,EN13,$EM$4:$EM$503,"Non affecté")>0," + à affecter","")),"") | EU13: =IF(EO13=1,IF(EP13>0,SUMPRODUCT(($EN$4:$EN$503=EN13)*$E$4:$E$503*$C$4:$C$503)/EP13,AVERAGEIF($EN$4:$EN$503,EN13,$C$4:$C$503)),"") | EV13: =IF(ISNUMBER(I13),I13,2958465) -> 46357 | EW13: =IF(EO13=1,SUMPRODUCT(MIN(($EN$4:$EN$503=EN13)*$EV$4:$EV$503+($EN$4:$EN$503<>EN13)*2958465)),"") | EX13: =IF(AND(D13=1,ISNUMBER(INDEX(Charge!$F:$F,ROW()))),INDEX(Charge!$F:$F,ROW()),0) -> 46444 | EY13: =IF(EO13=1,SUMPRODUCT(MAX(($EN$4:$EN$503=EN13)*$EX$4:$EX$503)),"") | FA13: =IF(10<=$CD$23,INDEX($EJ$4:$EJ$203,10),IF(10-$CD$23<=$CD$26,INDEX($EK$4:$EK$203,10-$CD$23),"")) | FB13: =IF(FA13="","",IF(10<=$CD$23,"Interne","Externe")) | FD13: =IF(AND(B13=1,TRIM(INDEX(Charge!$K:$K,ROW()))<>"",TRIM(INDEX(Charge!$L:$L,ROW()))<>""),1,0) -> 0 | FE13: =IF(OR(EN13="",BZ13="(non affecté)"),0,IF(COUNTIFS($EN$4:EN13,EN13,$BZ$4:BZ13,BZ13)=1,1,0)) -> 1
